Workbook

Sheet LeesMij
A1: ART EYE — FINANCIEEL MODEL (36 maanden, maandelijks, 3 scenario's)
A2: Alle bedragen in A$ (AUD). Start = M1 = september 2026 (beta-launch rond Sydney Contemporary, 10-13 sep, Carriageworks).
A4: KLEURCODE
A5: Blauwe tekst = harde input / aanname (aanpasbaar). Zwart = formule. Groen = verwijzing naar ander blad. Gele vulling = kernaanname — begin hier met draaien.
A7: STRUCTUUR
A8: 1. Aannames — alle drivers, kolommen Bear / Basis / Bull, met bron/redenering per regel.
A9: 2. Retentie — maandelijkse cohort-retentiecurves (leeftijd 0-35 mnd) per scenario. Low-frequency use case: steile val na M1, plateau daarna.
A10: 3. ModelBear / ModelBasis / ModelBull — 36 maandregels: downloads, activatie, cohort-MAU, premium, venue-SaaS, fairs, kosten, cashflow. KPI-blok onderaan.
A11: 4. CohortBear/-Basis/-Bull — het volledige cohortdriehoek: rij = startcohort, kolom = kalendermaand; MAU = kolomsom. Model-MAU verwijst hierheen.
A12: 5. Sensitiviteit — live gevoeligheidstabellen (venue-MRR, consumer-omzet, venue-LTV).
A14: KERNCONCLUSIES (Basis-scenario)
A15: - Consumer-LTV per geactiveerde gebruiker is < A$1: consumer subscription kan NOOIT het verdienmodel zijn; hij bestaat alleen als bonus.
... A22: Volledige redenering: docs/finance/ART-EYE-financieel-strategieplan.md in deze repo.

Sheet Retentie
A1: Leeftijd (mnd) | B1: Bear | C1: Basis | D1: Bull | F1: Aandeel van een maandcohort dat in maand N na activatie nog actief is (>=1 sessie). IJkpunten: event-gedreven consumer apps halen D30 10-15% (Basis M1=40% van geactiveerden, niet van downloads); plateau 8-10% = de kern-loggers (Letterboxd-patroon voor niche-logboek-apps). Bear = geen habit; Bull = statusloop werkt.
A2: 0 | B2: 1 | C2: 1 | D2: 1
A3: 1 | B3: 0.28 | C3: 0.4 | D3: 0.52
A4: 2 | B4: 0.18 | C4: 0.3 | D4: 0.42
A5: 3 | B5: 0.13 | C5: 0.24 | D5: 0.35
A6: 4 | B6: 0.1 | C6: 0.2 | D6: 0.31
A7: 5 | B7: 0.085 | C7: 0.18 | D7: 0.28
A8: 6 | B8: 0.075 | C8: 0.16 | D8: 0.26
A9: 7 | B9: 0.068 | C9: 0.15 | D9: 0.245
A10: 8 | B10: 0.062 | C10: 0.14 | D10: 0.235
A11: 9 | B11: 0.058 | C11: 0.13 | D11: 0.225
A12: 10 | B12: 0.054 | C12: 0.12 | D12: 0.215
A13: 11 | B13: 0.051 | C13: 0.115 | D13: 0.21
... A37: 35 | B37: 0.027 | C37: 0.081 | D37: 0.17
A38: Som (verwachte actieve mnd) | B38: =SUM(B2:B37) -> 2.99 | C38: =SUM(C2:C37) -> 5.376 | D38: =SUM(D2:D37) -> 8.674

Sheet Aannames
A1: AANNAMES — alle bedragen A$; percentages als fractie
A2: Driver | B2: Bear | C2: Basis | D2: Bull | E2: Redenering / bron
A3: CONSUMER
A4: Launch-downloads M1 (sep '26) | B4: 500 | C4: 900 | D4: 1500 | E4: Fair-weekend Sydney Contemporary (~25-30k bezoekers) + pers + posters bij venues. 900 = 3% van fairbezoek; geen betaalde installs.
A5: Organische downloads/mnd (start) | B5: 140 | C5: 260 | D5: 400 | E5: ASO 'sydney art exhibitions', venue-QR's, Instagram-shares. Referentie: niche-stadsapps zonder budget.
A6: Groei organisch %/mnd | B6: 0 | C6: 0.04 | D6: 0.06 | E6: Word-of-mouth + registergroei. Bear: geen loop, vlak.
A7: Fair-boost (extra % in sept) | B7: 0.8 | C7: 1.5 | D7: 2.5 | E7: Elke september (Sydney Contemporary) piekt discovery; M13/M25.
A8: Activatie (signup + >=1 save) | B8: 0.45 | C8: 0.55 | D8: 0.62 | E8: App vraagt account voor kernloop; benchmark consumer 40-60%. Meetbaar maken in analytics (nu NIET geinstrumenteerd in de code!).
A9: Premium-conversie (% van MAU) | B9: 0.01 | C9: 0.025 | D9: 0.04 | E9: Letterboxd Pro-achtig: 1-5% van actieven betaalt voor stats/Wrapped/vroege fairgidsen.
A10: Premium-prijs A$/mnd | B10: 4.49 | C10: 4.49 | D10: 5.99 | E10: Onder de koffie-drempel; jaarplan later (A$34.99).
A11: App Store-fee | B11: 0.15 | C11: 0.15 | D11: 0.15 | E11: Apple Small Business Program (<US$1M omzet) = 15%, geen 30%.
A12: Retentiecurve | E12: Zie blad Retentie (kolom per scenario) — de belangrijkste aanname van dit hele model.
A13: VENUE-SAAS
A14: Start verkoop (maand #) | B14: 9 | C14: 7 | D14: 6 | E14: Pas verkopen met bewijs: >=1.500 MAU + doorkliks per venue meetbaar. Eerder pitchen verbrandt de markt.
A15: Outreach venues/mnd | B15: 12 | C15: 20 | D15: 25 | E15: Avondwerk-plafond: ~5 gerichte pitches/week (e-mail + 1 bezoek). Solo-constraint, geen sales-team.
A16: Close rate | B16: 0.06 | C16: 0.12 | D16: 0.18 | E16: Galeries betalen al voor listings (Art Guide Australia / Art Almanac): budgetregel bestaat. 12% = 1 op 8 pitches.
A17: Venue-prijs A$/mnd | B17: 39 | C17: 45 | D17: 55 | E17: Onder Art Guide-print-listingtarief; featured plaatsing + analytics + eigen media (foto/video/reel) + claim.
A18: Venue-churn %/mnd | B18: 0.05 | C18: 0.025 | D18: 0.015 | E18: Kleine galeries sluiten/bezuinigen; 2,5%/mnd = ~26%/jaar. Skok: netto-retentie is de hele SaaS-case.
A19: Adresseerbare venues Sydney | B19: 60 | C19: 70 | D19: 80 | E19: Register telt 143 venues (104 galleries/23 musea/16 ARI's); alleen commerciele galeries + betaalkrachtige non-profits kopen.
A20: Max. penetratie | B20: 0.25 | C20: 0.35 | D20: 0.45 | E20: Art Guide haalt vergelijkbare dekking in AU; nooit 100% — een deel betaalt nooit ergens voor.
A21: Venue-CAC (A$) | B21: 150 | C21: 120 | D21: 100 | E21: Founder-tijd + bezoek + demo; geen betaalde acquisitie.
A22: Venue-brutomarge | B22: 0.92 | C22: 0.94 | D22: 0.95 | E22: Stripe-fees + support-tijd; software-marge.
A23: EXPANSIE
A24: Stad 2 launch (maand #) | B24: 99 | C24: 18 | D24: 13 | E24: Alleen na Sydney-gates (zie strategiedoc §4). Basis: Melbourne, feb '28 rond Melbourne Art Fair. Bear: nooit (99).
A25: Adresseerbare venues stad 2 | B25: 0 | C25: 85 | D25: 170 | E25: Melbourne heeft meer galeries dan Sydney; Bull bundelt Melbourne+Brisbane.
A26: Organische downloads/mnd stad 2 | B26: 0 | C26: 300 | D26: 500 | E26: Zelfde playbook, maar met bewijs + AU-pers uit Sydney.
A27: KOSTEN (A$/mnd tenzij anders)
A28: Infra basis (Supabase Pro e.d.) | B28: 60 | C28: 60 | D28: 60 | E28: Supabase Pro US$25 + storage/egress + Vercel/EAS-basis.
A29: Infra per MAU | B29: 0.02 | C29: 0.02 | D29: 0.02 | E29: Egress/beeld-CDN schaalt met gebruik.
A30: AI-pipeline per stad | B30: 80 | C30: 80 | D30: 80 | E30: Claude-calls validate/discover/enrich (cap 30 calls/run, zie supabase/functions) + web search.
A31: Tools (EAS, Resend, domein, mail) | B31: 70 | C31: 70 | D31: 70 | E31: Expo EAS production US$0-99, Resend, domein, e-mail.
A32: Apple Developer /jaar | B32: 150 | C32: 150 | D32: 150 | E32: US$99/jr; valt in M1, M13, M25.
A33: Marketing basis | B33: 50 | C33: 150 | D33: 300 | E33: Posters, print bij venues, af en toe een boost. Geen structurele paid acquisitie.
A34: Fair-marketing (elke sept) | B34: 300 | C34: 800 | D34: 1500 | E34: Posters/QR rond Sydney Contemporary; guerrilla, geen stand.
A35: Oprichting/legal eenmalig (M1) | B35: 400 | C35: 400 | D35: 400 | E35: Sole trader ABN + voorwaarden/privacy-templates. Pty Ltd pas bij venue-omzet.
A36: OVERIG
A37: Fair-partnership A$ (per sept, v.a. jr 2) | B37: 0 | C37: 5000 | D37: 10000 | E37: Officiele agenda-partner/gids van 1 fair. Distributie-deal eerst, geld pas met bewezen publiek. Lumpy — nooit primair.

Sheet ModelBear
A1: ART EYE — scenario BEAR (A$, M1 = sep 2026)
A2: Alle regels zijn formules op blad Aannames + Retentie. Niets hier hard aanpassen.
A7: Mnd | B7: Kalender | C7: Downloads Sydney | D7: Downloads stad 2+ | E7: Downloads totaal | F7: Nieuwe actieven | G7: MAU (cohort) | H7: Premium-abonnees | I7: Consumer-omzet netto | J7: Betalende venues | K7: Venue-MRR | L7: Fair/partnership | M7: Totale omzet | N7: Infra | O7: AI-pipeline | P7: Tools | Q7: Apple | R7: Marketing | S7: Eenmalig | T7: Totale kosten | U7: Netto cashflow | V7: Cumulatief
A8: 1 | B8: sep-26 | C8: =Aannames!$B$4 -> 500 | D8: =IF(A8>=Aannames!$B$24,Aannames!$B$26*(1+Aannames!$B$6)^(A8-Aannames!$B$24),0) -> 0 | E8: =C8+D8 -> 500 | F8: =E8*Aannames!$B$8 -> 225 | G8: =CohortBear!B$38 -> 225 | H8: =G8*Aannames!$B$9 -> 2.25 | I8: =H8*Aannames!$B$10*(1-Aannames!$B$11) -> 8.587125 | J8: =MIN(IF(A8>=Aannames!$B$14,Aannames!$B$15*Aannames!$B$16,0),(Aannames!$B$19+IF(A8>=Aannames!$B$24,Aannames!$B$25,0))*Aannames!$B$20) -> 0 | K8: =J8*Aannames!$B$17 -> 0 | L8: =IF(AND(A8>12,MOD(A8-1,12)=0),Aannames!$B$37,0) -> 0 | M8: =I8+K8+L8 -> 8.587125 | N8: =Aannames!$B$28+G8*Aannames!$B$29 -> 64.5 | O8: =Aannames!$B$30*(1+IF(A8>=Aannames!$B$24,1,0)) -> 80 | P8: =Aannames!$B$31 -> 70 | Q8: =IF(MOD(A8-1,12)=0,Aannames!$B$32,0) -> 150 | R8: =Aannames!$B$33+IF(MOD(A8-1,12)=0,Aannames!$B$34,0) -> 350 | S8: =IF(A8=1,Aannames!$B$35,0) -> 400 | T8: =SUM(N8:S8) -> 1114.5 | U8: =M8-T8 -> -1105.9129 | V8: =U8 -> -1105.9129
A9: 2 | B9: okt-26 | C9: =Aannames!$B$5*(1+Aannames!$B$6)^(A9-2)*(1+IF(MOD(A9-1,12)=0,Aannames!$B$7,0)) -> 140 | D9: =IF(A9>=Aannames!$B$24,Aannames!$B$26*(1+Aannames!$B$6)^(A9-Aannames!$B$24),0) -> 0 | E9: =C9+D9 -> 140 | F9: =E9*Aannames!$B$8 -> 63 | G9: =CohortBear!C$38 -> 126 | H9: =G9*Aannames!$B$9 -> 1.26 | I9: =H9*Aannames!$B$10*(1-Aannames!$B$11) -> 4.80879 | J9: =MIN(J8*(1-Aannames!$B$18)+IF(A9>=Aannames!$B$14,Aannames!$B$15*Aannames!$B$16,0),(Aannames!$B$19+IF(A9>=Aannames!$B$24,Aannames!$B$25,0))*Aannames!$B$20) -> 0 | K9: =J9*Aannames!$B$17 -> 0 | L9: =IF(AND(A9>12,MOD(A9-1,12)=0),Aannames!$B$37,0) -> 0 | M9: =I9+K9+L9 -> 4.80879 | N9: =Aannames!$B$28+G9*Aannames!$B$29 -> 62.52 | O9: =Aannames!$B$30*(1+IF(A9>=Aannames!$B$24,1,0)) -> 80 | P9: =Aannames!$B$31 -> 70 | Q9: =IF(MOD(A9-1,12)=0,Aannames!$B$32,0) -> 0 | R9: =Aannames!$B$33+IF(MOD(A9-1,12)=0,Aannames!$B$34,0) -> 50 | S9: =IF(A9=1,Aannames!$B$35,0) -> 0 | T9: =SUM(N9:S9) -> 262.52 | U9: =M9-T9 -> -257.71121 | V9: =V8+U9 -> -1363.6241
A10: 3 | B10: nov-26 | C10: =Aannames!$B$5*(1+Aannames!$B$6)^(A10-2)*(1+IF(MOD(A10-1,12)=0,Aannames!$B$7,0)) -> 140 | D10: =IF(A10>=Aannames!$B$24,Aannames!$B$26*(1+Aannames!$B$6)^(A10-Aannames!$B$24),0) -> 0 | E10: =C10+D10 -> 140 | F10: =E10*Aannames!$B$8 -> 63 | G10: =CohortBear!D$38 -> 121.14 | H10: =G10*Aannames!$B$9 -> 1.2114 | I10: =H10*Aannames!$B$10*(1-Aannames!$B$11) -> 4.6233081 | J10: =MIN(J9*(1-Aannames!$B$18)+IF(A10>=Aannames!$B$14,Aannames!$B$15*Aannames!$B$16,0),(Aannames!$B$19+IF(A10>=Aannames!$B$24,Aannames!$B$25,0))*Aannames!$B$20) -> 0 | K10: =J10*Aannames!$B$17 -> 0 | L10: =IF(AND(A10>12,MOD(A10-1,12)=0),Aannames!$B$37,0) -> 0 | M10: =I10+K10+L10 -> 4.6233081 | N10: =Aannames!$B$28+G10*Aannames!$B$29 -> 62.4228 | O10: =Aannames!$B$30*(1+IF(A10>=Aannames!$B$24,1,0)) -> 80 | P10: =Aannames!$B$31 -> 70 | Q10: =IF(MOD(A10-1,12)=0,Aannames!$B$32,0) -> 0 | R10: =Aannames!$B$33+IF(MOD(A10-1,12)=0,Aannames!$B$34,0) -> 50 | S10: =IF(A10=1,Aannames!$B$35,0) -> 0 | T10: =SUM(N10:S10) -> 262.4228 | U10: =M10-T10 -> -257.79949 | V10: =V9+U10 -> -1621.4236
A11: 4 | B11: dec-26 | C11: =Aannames!$B$5*(1+Aannames!$B$6)^(A11-2)*(1+IF(MOD(A11-1,12)=0,Aannames!$B$7,0)) -> 140 | D11: =IF(A11>=Aannames!$B$24,Aannames!$B$26*(1+Aannames!$B$6)^(A11-Aannames!$B$24),0) -> 0 | E11: =C11+D11 -> 140 | F11: =E11*Aannames!$B$8 -> 63 | G11: =CohortBear!E$38 -> 121.23 | H11: =G11*Aannames!$B$9 -> 1.2123 | I11: =H11*Aannames!$B$10*(1-Aannames!$B$11) -> 4.6267429 | J11: =MIN(J10*(1-Aannames!$B$18)+IF(A11>=Aannames!$B$14,Aannames!$B$15*Aannames!$B$16,0),(Aannames!$B$19+IF(A11>=Aannames!$B$24,Aannames!$B$25,0))*Aannames!$B$20) -> 0 | K11: =J11*Aannames!$B$17 -> 0 | L11: =IF(AND(A11>12,MOD(A11-1,12)=0),Aannames!$B$37,0) -> 0 | M11: =I11+K11+L11 -> 4.6267429 | N11: =Aannames!$B$28+G11*Aannames!$B$29 -> 62.4246 | O11: =Aannames!$B$30*(1+IF(A11>=Aannames!$B$24,1,0)) -> 80 | P11: =Aannames!$B$31 -> 70 | Q11: =IF(MOD(A11-1,12)=0,Aannames!$B$32,0) -> 0 | R11: =Aannames!$B$33+IF(MOD(A11-1,12)=0,Aannames!$B$34,0) -> 50 | S11: =IF(A11=1,Aannames!$B$35,0) -> 0 | T11: =SUM(N11:S11) -> 262.4246 | U11: =M11-T11 -> -257.79786 | V11: =V10+U11 -> -1879.2214
A12: 5 | B12: jan-27 | C12: =Aannames!$B$5*(1+Aannames!$B$6)^(A12-2)*(1+IF(MOD(A12-1,12)=0,Aannames!$B$7,0)) -> 140 | D12: =IF(A12>=Aannames!$B$24,Aannames!$B$26*(1+Aannames!$B$6)^(A12-Aannames!$B$24),0) -> 0 | E12: =C12+D12 -> 140 | F12: =E12*Aannames!$B$8 -> 63 | G12: =CohortBear!F$38 -> 122.67 | H12: =G12*Aannames!$B$9 -> 1.2267 | I12: =H12*Aannames!$B$10*(1-Aannames!$B$11) -> 4.6817006 | J12: =MIN(J11*(1-Aannames!$B$18)+IF(A12>=Aannames!$B$14,Aannames!$B$15*Aannames!$B$16,0),(Aannames!$B$19+IF(A12>=Aannames!$B$24,Aannames!$B$25,0))*Aannames!$B$20) -> 0 | K12: =J12*Aannames!$B$17 -> 0 | L12: =IF(AND(A12>12,MOD(A12-1,12)=0),Aannames!$B$37,0) -> 0 | M12: =I12+K12+L12 -> 4.6817006 | N12: =Aannames!$B$28+G12*Aannames!$B$29 -> 62.4534 | O12: =Aannames!$B$30*(1+IF(A12>=Aannames!$B$24,1,0)) -> 80 | P12: =Aannames!$B$31 -> 70 | Q12: =IF(MOD(A12-1,12)=0,Aannames!$B$32,0) -> 0 | R12: =Aannames!$B$33+IF(MOD(A12-1,12)=0,Aannames!$B$34,0) -> 50 | S12: =IF(A12=1,Aannames!$B$35,0) -> 0 | T12: =SUM(N12:S12) -> 262.4534 | U12: =M12-T12 -> -257.7717 | V12: =V11+U12 -> -2136.9931
A13: 6 | B13: feb-27 | C13: =Aannames!$B$5*(1+Aannames!$B$6)^(A13-2)*(1+IF(MOD(A13-1,12)=0,Aannames!$B$7,0)) -> 140 | D13: =IF(A13>=Aannames!$B$24,Aannames!$B$26*(1+Aannames!$B$6)^(A13-Aannames!$B$24),0) -> 0 | E13: =C13+D13 -> 140 | F13: =E13*Aannames!$B$8 -> 63 | G13: =CohortBear!G$38 -> 125.595 | H13: =G13*Aannames!$B$9 -> 1.25595 | I13: =H13*Aannames!$B$10*(1-Aannames!$B$11) -> 4.7933332 | J13: =MIN(J12*(1-Aannames!$B$18)+IF(A13>=Aannames!$B$14,Aannames!$B$15*Aannames!$B$16,0),(Aannames!$B$19+IF(A13>=Aannames!$B$24,Aannames!$B$25,0))*Aannames!$B$20) -> 0 | K13: =J13*Aannames!$B$17 -> 0 | L13: =IF(AND(A13>12,MOD(A13-1,12)=0),Aannames!$B$37,0) -> 0 | M13: =I13+K13+L13 -> 4.7933332 | N13: =Aannames!$B$28+G13*Aannames!$B$29 -> 62.5119 | O13: =Aannames!$B$30*(1+IF(A13>=Aannames!$B$24,1,0)) -> 80 | P13: =Aannames!$B$31 -> 70 | Q13: =IF(MOD(A13-1,12)=0,Aannames!$B$32,0) -> 0 | R13: =Aannames!$B$33+IF(MOD(A13-1,12)=0,Aannames!$B$34,0) -> 50 | S13: =IF(A13=1,Aannames!$B$35,0) -> 0 | T13: =SUM(N13:S13) -> 262.5119 | U13: =M13-T13 -> -257.71857 | V13: =V12+U13 -> -2394.7117
A14: 7 | B14: mrt-27 | C14: =Aannames!$B$5*(1+Aannames!$B$6)^(A14-2)*(1+IF(MOD(A14-1,12)=0,Aannames!$B$7,0)) -> 140 | D14: =IF(A14>=Aannames!$B$24,Aannames!$B$26*(1+Aannames!$B$6)^(A14-Aannames!$B$24),0) -> 0 | E14: =C14+D14 -> 140 | F14: =E14*Aannames!$B$8 -> 63 | G14: =CohortBear!H$38 -> 128.7 | H14: =G14*Aannames!$B$9 -> 1.287 | I14: =H14*Aannames!$B$10*(1-Aannames!$B$11) -> 4.9118355 | J14: =MIN(J13*(1-Aannames!$B$18)+IF(A14>=Aannames!$B$14,Aannames!$B$15*Aannames!$B$16,0),(Aannames!$B$19+IF(A14>=Aannames!$B$24,Aannames!$B$25,0))*Aannames!$B$20) -> 0 | K14: =J14*Aannames!$B$17 -> 0 | L14: =IF(AND(A14>12,MOD(A14-1,12)=0),Aannames!$B$37,0) -> 0 | M14: =I14+K14+L14 -> 4.9118355 | N14: =Aannames!$B$28+G14*Aannames!$B$29 -> 62.574 | O14: =Aannames!$B$30*(1+IF(A14>=Aannames!$B$24,1,0)) -> 80 | P14: =Aannames!$B$31 -> 70 | Q14: =IF(MOD(A14-1,12)=0,Aannames!$B$32,0) -> 0 | R14: =Aannames!$B$33+IF(MOD(A14-1,12)=0,Aannames!$B$34,0) -> 50 | S14: =IF(A14=1,Aannames!$B$35,0) -> 0 | T14: =SUM(N14:S14) -> 262.574 | U14: =M14-T14 -> -257.66216 | V14: =V13+U14 -> -2652.3739
A15: 8 | B15: apr-27 | C15: =Aannames!$B$5*(1+Aannames!$B$6)^(A15-2)*(1+IF(MOD(A15-1,12)=0,Aannames!$B$7,0)) -> 140 | D15: =IF(A15>=Aannames!$B$24,Aannames!$B$26*(1+Aannames!$B$6)^(A15-Aannames!$B$24),0) -> 0 | E15: =C15+D15 -> 140 | F15: =E15*Aannames!$B$8 -> 63 | G15: =CohortBear!I$38 -> 131.85 | H15: =G15*Aannames!$B$9 -> 1.3185 | I15: =H15*Aannames!$B$10*(1-Aannames!$B$11) -> 5.0320552 | J15: =MIN(J14*(1-Aannames!$B$18)+IF(A15>=Aannames!$B$14,Aannames!$B$15*Aannames!$B$16,0),(Aannames!$B$19+IF(A15>=Aannames!$B$24,Aannames!$B$25,0))*Aannames!$B$20) -> 0 | K15: =J15*Aannames!$B$17 -> 0 | L15: =IF(AND(A15>12,MOD(A15-1,12)=0),Aannames!$B$37,0) -> 0 | M15: =I15+K15+L15 -> 5.0320552 | N15: =Aannames!$B$28+G15*Aannames!$B$29 -> 62.637 | O15: =Aannames!$B$30*(1+IF(A15>=Aannames!$B$24,1,0)) -> 80 | P15: =Aannames!$B$31 -> 70 | Q15: =IF(MOD(A15-1,12)=0,Aannames!$B$32,0) -> 0 | R15: =Aannames!$B$33+IF(MOD(A15-1,12)=0,Aannames!$B$34,0) -> 50 | S15: =IF(A15=1,Aannames!$B$35,0) -> 0 | T15: =SUM(N15:S15) -> 262.637 | U15: =M15-T15 -> -257.60494 | V15: =V14+U15 -> -2909.9788
A16: 9 | B16: mei-27 | C16: =Aannames!$B$5*(1+Aannames!$B$6)^(A16-2)*(1+IF(MOD(A16-1,12)=0,Aannames!$B$7,0)) -> 140 | D16: =IF(A16>=Aannames!$B$24,Aannames!$B$26*(1+Aannames!$B$6)^(A16-Aannames!$B$24),0) -> 0 | E16: =C16+D16 -> 140 | F16: =E16*Aannames!$B$8 -> 63 | G16: =CohortBear!J$38 -> 134.784 | H16: =G16*Aannames!$B$9 -> 1.34784 | I16: =H16*Aannames!$B$10*(1-Aannames!$B$11) -> 5.1440314 | J16: =MIN(J15*(1-Aannames!$B$18)+IF(A16>=Aannames!$B$14,Aannames!$B$15*Aannames!$B$16,0),(Aannames!$B$19+IF(A16>=Aannames!$B$24,Aannames!$B$25,0))*Aannames!$B$20) -> 0.72 | K16: =J16*Aannames!$B$17 -> 28.08 | L16: =IF(AND(A16>12,MOD(A16-1,12)=0),Aannames!$B$37,0) -> 0 | M16: =I16+K16+L16 -> 33.224031 | N16: =Aannames!$B$28+G16*Aannames!$B$29 -> 62.69568 | O16: =Aannames!$B$30*(1+IF(A16>=Aannames!$B$24,1,0)) -> 80 | P16: =Aannames!$B$31 -> 70 | Q16: =IF(MOD(A16-1,12)=0,Aannames!$B$32,0) -> 0 | R16: =Aannames!$B$33+IF(MOD(A16-1,12)=0,Aannames!$B$34,0) -> 50 | S16: =IF(A16=1,Aannames!$B$35,0) -> 0 | T16: =SUM(N16:S16) -> 262.69568 | U16: =M16-T16 -> -229.47165 | V16: =V15+U16 -> -3139.4505
A17: 10 | B17: jun-27 | C17: =Aannames!$B$5*(1+Aannames!$B$6)^(A17-2)*(1+IF(MOD(A17-1,12)=0,Aannames!$B$7,0)) -> 140 | D17: =IF(A17>=Aannames!$B$24,Aannames!$B$26*(1+Aannames!$B$6)^(A17-Aannames!$B$24),0) -> 0 | E17: =C17+D17 -> 140 | F17: =E17*Aannames!$B$8 -> 63 | G17: =CohortBear!K$38 -> 137.79 | H17: =G17*Aannames!$B$9 -> 1.3779 | I17: =H17*Aannames!$B$10*(1-Aannames!$B$11) -> 5.2587554 | J17: =MIN(J16*(1-Aannames!$B$18)+IF(A17>=Aannames!$B$14,Aannames!$B$15*Aannames!$B$16,0),(Aannames!$B$19+IF(A17>=Aannames!$B$24,Aannames!$B$25,0))*Aannames!$B$20) -> 1.404 | K17: =J17*Aannames!$B$17 -> 54.756 | L17: =IF(AND(A17>12,MOD(A17-1,12)=0),Aannames!$B$37,0) -> 0 | M17: =I17+K17+L17 -> 60.014755 | N17: =Aannames!$B$28+G17*Aannames!$B$29 -> 62.7558 | O17: =Aannames!$B$30*(1+IF(A17>=Aannames!$B$24,1,0)) -> 80 | P17: =Aannames!$B$31 -> 70 | Q17: =IF(MOD(A17-1,12)=0,Aannames!$B$32,0) -> 0 | R17: =Aannames!$B$33+IF(MOD(A17-1,12)=0,Aannames!$B$34,0) -> 50 | S17: =IF(A17=1,Aannames!$B$35,0) -> 0 | T17: =SUM(N17:S17) -> 262.7558 | U17: =M17-T17 -> -202.74104 | V17: =V16+U17 -> -3342.1915
A18: 11 | B18: jul-27 | C18: =Aannames!$B$5*(1+Aannames!$B$6)^(A18-2)*(1+IF(MOD(A18-1,12)=0,Aannames!$B$7,0)) -> 140 | D18: =IF(A18>=Aannames!$B$24,Aannames!$B$26*(1+Aannames!$B$6)^(A18-Aannames!$B$24),0) -> 0 | E18: =C18+D18 -> 140 | F18: =E18*Aannames!$B$8 -> 63 | G18: =CohortBear!L$38 -> 140.544 | H18: =G18*Aannames!$B$9 -> 1.40544 | I18: =H18*Aannames!$B$10*(1-Aannames!$B$11) -> 5.3638618 | J18: =MIN(J17*(1-Aannames!$B$18)+IF(A18>=Aannames!$B$14,Aannames!$B$15*Aannames!$B$16,0),(Aannames!$B$19+IF(A18>=Aannames!$B$24,Aannames!$B$25,0))*Aannames!$B$20) -> 2.0538 | K18: =J18*Aannames!$B$17 -> 80.0982 | L18: =IF(AND(A18>12,MOD(A18-1,12)=0),Aannames!$B$37,0) -> 0 | M18: =I18+K18+L18 -> 85.462062 | N18: =Aannames!$B$28+G18*Aannames!$B$29 -> 62.81088 | O18: =Aannames!$B$30*(1+IF(A18>=Aannames!$B$24,1,0)) -> 80 | P18: =Aannames!$B$31 -> 70 | Q18: =IF(MOD(A18-1,12)=0,Aannames!$B$32,0) -> 0 | R18: =Aannames!$B$33+IF(MOD(A18-1,12)=0,Aannames!$B$34,0) -> 50 | S18: =IF(A18=1,Aannames!$B$35,0) -> 0 | T18: =SUM(N18:S18) -> 262.81088 | U18: =M18-T18 -> -177.34882 | V18: =V17+U18 -> -3519.5403
A19: 12 | B19: aug-27 | C19: =Aannames!$B$5*(1+Aannames!$B$6)^(A19-2)*(1+IF(MOD(A19-1,12)=0,Aannames!$B$7,0)) -> 140 | D19: =IF(A19>=Aannames!$B$24,Aannames!$B$26*(1+Aannames!$B$6)^(A19-Aannames!$B$24),0) -> 0 | E19: =C19+D19 -> 140 | F19: =E19*Aannames!$B$8 -> 63 | G19: =CohortBear!M$38 -> 143.271 | H19: =G19*Aannames!$B$9 -> 1.43271 | I19: =H19*Aannames!$B$10*(1-Aannames!$B$11) -> 5.4679377 | J19: =MIN(J18*(1-Aannames!$B$18)+IF(A19>=Aannames!$B$14,Aannames!$B$15*Aannames!$B$16,0),(Aannames!$B$19+IF(A19>=Aannames!$B$24,Aannames!$B$25,0))*Aannames!$B$20) -> 2.67111 | K19: =J19*Aannames!$B$17 -> 104.17329 | L19: =IF(AND(A19>12,MOD(A19-1,12)=0),Aannames!$B$37,0) -> 0 | M19: =I19+K19+L19 -> 109.64123 | N19: =Aannames!$B$28+G19*Aannames!$B$29 -> 62.86542 | O19: =Aannames!$B$30*(1+IF(A19>=Aannames!$B$24,1,0)) -> 80 | P19: =Aannames!$B$31 -> 70 | Q19: =IF(MOD(A19-1,12)=0,Aannames!$B$32,0) -> 0 | R19: =Aannames!$B$33+IF(MOD(A19-1,12)=0,Aannames!$B$34,0) -> 50 | S19: =IF(A19=1,Aannames!$B$35,0) -> 0 | T19: =SUM(N19:S19) -> 262.86542 | U19: =M19-T19 -> -153.22419 | V19: =V18+U19 -> -3672.7645
A20: 13 | B20: sep-27 | C20: =Aannames!$B$5*(1+Aannames!$B$6)^(A20-2)*(1+IF(MOD(A20-1,12)=0,Aannames!$B$7,0)) -> 252 | D20: =IF(A20>=Aannames!$B$24,Aannames!$B$26*(1+Aannames!$B$6)^(A20-Aannames!$B$24),0) -> 0 | E20: =C20+D20 -> 252 | F20: =E20*Aannames!$B$8 -> 113.4 | G20: =CohortBear!N$38 -> 196.209 | H20: =G20*Aannames!$B$9 -> 1.96209 | I20: =H20*Aannames!$B$10*(1-Aannames!$B$11) -> 7.4883165 | J20: =MIN(J19*(1-Aannames!$B$18)+IF(A20>=Aannames!$B$14,Aannames!$B$15*Aannames!$B$16,0),(Aannames!$B$19+IF(A20>=Aannames!$B$24,Aannames!$B$25,0))*Aannames!$B$20) -> 3.2575545 | K20: =J20*Aannames!$B$17 -> 127.04463 | L20: =IF(AND(A20>12,MOD(A20-1,12)=0),Aannames!$B$37,0) -> 0 | M20: =I20+K20+L20 -> 134.53294 | N20: =Aannames!$B$28+G20*Aannames!$B$29 -> 63.92418 | O20: =Aannames!$B$30*(1+IF(A20>=Aannames!$B$24,1,0)) -> 80 | P20: =Aannames!$B$31 -> 70 | Q20: =IF(MOD(A20-1,12)=0,Aannames!$B$32,0) -> 150 | R20: =Aannames!$B$33+IF(MOD(A20-1,12)=0,Aannames!$B$34,0) -> 350 | S20: =IF(A20=1,Aannames!$B$35,0) -> 0 | T20: =SUM(N20:S20) -> 713.92418 | U20: =M20-T20 -> -579.39124 | V20: =V19+U20 -> -4252.1558
A21: 14 | B21: okt-27 | C21: =Aannames!$B$5*(1+Aannames!$B$6)^(A21-2)*(1+IF(MOD(A21-1,12)=0,Aannames!$B$7,0)) -> 140 | D21: =IF(A21>=Aannames!$B$24,Aannames!$B$26*(1+Aannames!$B$6)^(A21-Aannames!$B$24),0) -> 0 | E21: =C21+D21 -> 140 | F21: =E21*Aannames!$B$8 -> 63 | G21: =CohortBear!O$38 -> 162.495 | H21: =G21*Aannames!$B$9 -> 1.62495 | I21: =H21*Aannames!$B$10*(1-Aannames!$B$11) -> 6.2016217 | J21: =MIN(J20*(1-Aannames!$B$18)+IF(A21>=Aannames!$B$14,Aannames!$B$15*Aannames!$B$16,0),(Aannames!$B$19+IF(A21>=Aannames!$B$24,Aannames!$B$25,0))*Aannames!$B$20) -> 3.8146768 | K21: =J21*Aannames!$B$17 -> 148.77239 | L21: =IF(AND(A21>12,MOD(A21-1,12)=0),Aannames!$B$37,0) -> 0 | M21: =I21+K21+L21 -> 154.97402 | N21: =Aannames!$B$28+G21*Aannames!$B$29 -> 63.2499 | O21: =Aannames!$B$30*(1+IF(A21>=Aannames!$B$24,1,0)) -> 80 | P21: =Aannames!$B$31 -> 70 | Q21: =IF(MOD(A21-1,12)=0,Aannames!$B$32,0) -> 0 | R21: =Aannames!$B$33+IF(MOD(A21-1,12)=0,Aannames!$B$34,0) -> 50 | S21: =IF(A21=1,Aannames!$B$35,0) -> 0 | T21: =SUM(N21:S21) -> 263.2499 | U21: =M21-T21 -> -108.27588 | V21: =V20+U21 -> -4360.4316
A22: 15 | B22: nov-27 | C22: =Aannames!$B$5*(1+Aannames!$B$6)^(A22-2)*(1+IF(MOD(A22-1,12)=0,Aannames!$B$7,0)) -> 140 | D22: =IF(A22>=Aannames!$B$24,Aannames!$B$26*(1+Aannames!$B$6)^(A22-Aannames!$B$24),0) -> 0 | E22: =C22+D22 -> 140 | F22: =E22*Aannames!$B$8 -> 63 | G22: =CohortBear!P$38 -> 159.903 | H22: =G22*Aannames!$B$9 -> 1.59903 | I22: =H22*Aannames!$B$10*(1-Aannames!$B$11) -> 6.102698 | J22: =MIN(J21*(1-Aannames!$B$18)+IF(A22>=Aannames!$B$14,Aannames!$B$15*Aannames!$B$16,0),(Aannames!$B$19+IF(A22>=Aannames!$B$24,Aannames!$B$25,0))*Aannames!$B$20) -> 4.3439429 | K22: =J22*Aannames!$B$17 -> 169.41377 | L22: =IF(AND(A22>12,MOD(A22-1,12)=0),Aannames!$B$37,0) -> 0 | M22: =I22+K22+L22 -> 175.51647 | N22: =Aannames!$B$28+G22*Aannames!$B$29 -> 63.19806 | O22: =Aannames!$B$30*(1+IF(A22>=Aannames!$B$24,1,0)) -> 80 | P22: =Aannames!$B$31 -> 70 | Q22: =IF(MOD(A22-1,12)=0,Aannames!$B$32,0) -> 0 | R22: =Aannames!$B$33+IF(MOD(A22-1,12)=0,Aannames!$B$34,0) -> 50 | S22: =IF(A22=1,Aannames!$B$35,0) -> 0 | T22: =SUM(N22:S22) -> 263.19806 | U22: =M22-T22 -> -87.681587 | V22: =V21+U22 -> -4448.1132
A23: 16 | B23: dec-27 | C23: =Aannames!$B$5*(1+Aannames!$B$6)^(A23-2)*(1+IF(MOD(A23-1,12)=0,Aannames!$B$7,0)) -> 140 | D23: =IF(A23>=Aannames!$B$24,Aannames!$B$26*(1+Aannames!$B$6)^(A23-Aannames!$B$24),0) -> 0 | E23: =C23+D23 -> 140 | F23: =E23*Aannames!$B$8 -> 63 | G23: =CohortBear!Q$38 -> 159.93 | H23: =G23*Aannames!$B$9 -> 1.5993 | I23: =H23*Aannames!$B$10*(1-Aannames!$B$11) -> 6.1037285 | J23: =MIN(J22*(1-Aannames!$B$18)+IF(A23>=Aannames!$B$14,Aannames!$B$15*Aannames!$B$16,0),(Aannames!$B$19+IF(A23>=Aannames!$B$24,Aannames!$B$25,0))*Aannames!$B$20) -> 4.8467458 | K23: =J23*Aannames!$B$17 -> 189.02309 | L23: =IF(AND(A23>12,MOD(A23-1,12)=0),Aannames!$B$37,0) -> 0 | M23: =I23+K23+L23 -> 195.12681 | N23: =Aannames!$B$28+G23*Aannames!$B$29 -> 63.1986 | O23: =Aannames!$B$30*(1+IF(A23>=Aannames!$B$24,1,0)) -> 80 | P23: =Aannames!$B$31 -> 70 | Q23: =IF(MOD(A23-1,12)=0,Aannames!$B$32,0) -> 0 | R23: =Aannames!$B$33+IF(MOD(A23-1,12)=0,Aannames!$B$34,0) -> 50 | S23: =IF(A23=1,Aannames!$B$35,0) -> 0 | T23: =SUM(N23:S23) -> 263.1986 | U23: =M23-T23 -> -68.071786 | V23: =V22+U23 -> -4516.185
A24: 17 | B24: jan-28 | C24: =Aannames!$B$5*(1+Aannames!$B$6)^(A24-2)*(1+IF(MOD(A24-1,12)=0,Aannames!$B$7,0)) -> 140 | D24: =IF(A24>=Aannames!$B$24,Aannames!$B$26*(1+Aannames!$B$6)^(A24-Aannames!$B$24),0) -> 0 | E24: =C24+D24 -> 140 | F24: =E24*Aannames!$B$8 -> 63 | G24: =CohortBear!R$38 -> 160.902 | H24: =G24*Aannames!$B$9 -> 1.60902 | I24: =H24*Aannames!$B$10*(1-Aannames!$B$11) -> 6.1408248 | J24: =MIN(J23*(1-Aannames!$B$18)+IF(A24>=Aannames!$B$14,Aannames!$B$15*Aannames!$B$16,0),(Aannames!$B$19+IF(A24>=Aannames!$B$24,Aannames!$B$25,0))*Aannames!$B$20) -> 5.3244085 | K24: =J24*Aannames!$B$17 -> 207.65193 | L24: =IF(AND(A24>12,MOD(A24-1,12)=0),Aannames!$B$37,0) -> 0 | M24: =I24+K24+L24 -> 213.79276 | N24: =Aannames!$B$28+G24*Aannames!$B$29 -> 63.21804 | O24: =Aannames!$B$30*(1+IF(A24>=Aannames!$B$24,1,0)) -> 80 | P24: =Aannames!$B$31 -> 70 | Q24: =IF(MOD(A24-1,12)=0,Aannames!$B$32,0) -> 0 | R24: =Aannames!$B$33+IF(MOD(A24-1,12)=0,Aannames!$B$34,0) -> 50 | S24: =IF(A24=1,Aannames!$B$35,0) -> 0 | T24: =SUM(N24:S24) -> 263.21804 | U24: =M24-T24 -> -49.425284 | V24: =V23+U24 -> -4565.6103
A25: 18 | B25: feb-28 | C25: =Aannames!$B$5*(1+Aannames!$B$6)^(A25-2)*(1+IF(MOD(A25-1,12)=0,Aannames!$B$7,0)) -> 140 | D25: =IF(A25>=Aannames!$B$24,Aannames!$B$26*(1+Aannames!$B$6)^(A25-Aannames!$B$24),0) -> 0 | E25: =C25+D25 -> 140 | F25: =E25*Aannames!$B$8 -> 63 | G25: =CohortBear!S$38 -> 162.567 | H25: =G25*Aannames!$B$9 -> 1.62567 | I25: =H25*Aannames!$B$10*(1-Aannames!$B$11) -> 6.2043696 | J25: =MIN(J24*(1-Aannames!$B$18)+IF(A25>=Aannames!$B$14,Aannames!$B$15*Aannames!$B$16,0),(Aannames!$B$19+IF(A25>=Aannames!$B$24,Aannames!$B$25,0))*Aannames!$B$20) -> 5.7781881 | K25: =J25*Aannames!$B$17 -> 225.34933 | L25: =IF(AND(A25>12,MOD(A25-1,12)=0),Aannames!$B$37,0) -> 0 | M25: =I25+K25+L25 -> 231.5537 | N25: =Aannames!$B$28+G25*Aannames!$B$29 -> 63.25134 | O25: =Aannames!$B$30*(1+IF(A25>=Aannames!$B$24,1,0)) -> 80 | P25: =Aannames!$B$31 -> 70 | Q25: =IF(MOD(A25-1,12)=0,Aannames!$B$32,0) -> 0 | R25: =Aannames!$B$33+IF(MOD(A25-1,12)=0,Aannames!$B$34,0) -> 50 | S25: =IF(A25=1,Aannames!$B$35,0) -> 0 | T25: =SUM(N25:S25) -> 263.25134 | U25: =M25-T25 -> -31.697636 | V25: =V24+U25 -> -4597.3079
A26: 19 | B26: mrt-28 | C26: =Aannames!$B$5*(1+Aannames!$B$6)^(A26-2)*(1+IF(MOD(A26-1,12)=0,Aannames!$B$7,0)) -> 140 | D26: =IF(A26>=Aannames!$B$24,Aannames!$B$26*(1+Aannames!$B$6)^(A26-Aannames!$B$24),0) -> 0 | E26: =C26+D26 -> 140 | F26: =E26*Aannames!$B$8 -> 63 | G26: =CohortBear!T$38 -> 164.421 | H26: =G26*Aannames!$B$9 -> 1.64421 | I26: =H26*Aannames!$B$10*(1-Aannames!$B$11) -> 6.2751275 | J26: =MIN(J25*(1-Aannames!$B$18)+IF(A26>=Aannames!$B$14,Aannames!$B$15*Aannames!$B$16,0),(Aannames!$B$19+IF(A26>=Aannames!$B$24,Aannames!$B$25,0))*Aannames!$B$20) -> 6.2092787 | K26: =J26*Aannames!$B$17 -> 242.16187 | L26: =IF(AND(A26>12,MOD(A26-1,12)=0),Aannames!$B$37,0) -> 0 | M26: =I26+K26+L26 -> 248.437 | N26: =Aannames!$B$28+G26*Aannames!$B$29 -> 63.28842 | O26: =Aannames!$B$30*(1+IF(A26>=Aannames!$B$24,1,0)) -> 80 | P26: =Aannames!$B$31 -> 70 | Q26: =IF(MOD(A26-1,12)=0,Aannames!$B$32,0) -> 0 | R26: =Aannames!$B$33+IF(MOD(A26-1,12)=0,Aannames!$B$34,0) -> 50 | S26: =IF(A26=1,Aannames!$B$35,0) -> 0 | T26: =SUM(N26:S26) -> 263.28842 | U26: =M26-T26 -> -14.851424 | V26: =V25+U26 -> -4612.1594
A27: 20 | B27: apr-28 | C27: =Aannames!$B$5*(1+Aannames!$B$6)^(A27-2)*(1+IF(MOD(A27-1,12)=0,Aannames!$B$7,0)) -> 140 | D27: =IF(A27>=Aannames!$B$24,Aannames!$B$26*(1+Aannames!$B$6)^(A27-Aannames!$B$24),0) -> 0 | E27: =C27+D27 -> 140 | F27: =E27*Aannames!$B$8 -> 63 | G27: =CohortBear!U$38 -> 166.3632 | H27: =G27*Aannames!$B$9 -> 1.663632 | I27: =H27*Aannames!$B$10*(1-Aannames!$B$11) -> 6.3492515 | J27: =MIN(J26*(1-Aannames!$B$18)+IF(A27>=Aannames!$B$14,Aannames!$B$15*Aannames!$B$16,0),(Aannames!$B$19+IF(A27>=Aannames!$B$24,Aannames!$B$25,0))*Aannames!$B$20) -> 6.6188147 | K27: =J27*Aannames!$B$17 -> 258.13377 | L27: =IF(AND(A27>12,MOD(A27-1,12)=0),Aannames!$B$37,0) -> 0 | M27: =I27+K27+L27 -> 264.48303 | N27: =Aannames!$B$28+G27*Aannames!$B$29 -> 63.327264 | O27: =Aannames!$B$30*(1+IF(A27>=Aannames!$B$24,1,0)) -> 80 | P27: =Aannames!$B$31 -> 70 | Q27: =IF(MOD(A27-1,12)=0,Aannames!$B$32,0) -> 0 | R27: =Aannames!$B$33+IF(MOD(A27-1,12)=0,Aannames!$B$34,0) -> 50 | S27: =IF(A27=1,Aannames!$B$35,0) -> 0 | T27: =SUM(N27:S27) -> 263.32726 | U27: =M27-T27 -> 1.1557623 | V27: =V26+U27 -> -4611.0036
A28: 21 | B28: mei-28 | C28: =Aannames!$B$5*(1+Aannames!$B$6)^(A28-2)*(1+IF(MOD(A28-1,12)=0,Aannames!$B$7,0)) -> 140 | D28: =IF(A28>=Aannames!$B$24,Aannames!$B$26*(1+Aannames!$B$6)^(A28-Aannames!$B$24),0) -> 0 | E28: =C28+D28 -> 140 | F28: =E28*Aannames!$B$8 -> 63 | G28: =CohortBear!V$38 -> 168.2928 | H28: =G28*Aannames!$B$9 -> 1.682928 | I28: =H28*Aannames!$B$10*(1-Aannames!$B$11) -> 6.4228947 | J28: =MIN(J27*(1-Aannames!$B$18)+IF(A28>=Aannames!$B$14,Aannames!$B$15*Aannames!$B$16,0),(Aannames!$B$19+IF(A28>=Aannames!$B$24,Aannames!$B$25,0))*Aannames!$B$20) -> 7.007874 | K28: =J28*Aannames!$B$17 -> 273.30709 | L28: =IF(AND(A28>12,MOD(A28-1,12)=0),Aannames!$B$37,0) -> 0 | M28: =I28+K28+L28 -> 279.72998 | N28: =Aannames!$B$28+G28*Aannames!$B$29 -> 63.365856 | O28: =Aannames!$B$30*(1+IF(A28>=Aannames!$B$24,1,0)) -> 80 | P28: =Aannames!$B$31 -> 70 | Q28: =IF(MOD(A28-1,12)=0,Aannames!$B$32,0) -> 0 | R28: =Aannames!$B$33+IF(MOD(A28-1,12)=0,Aannames!$B$34,0) -> 50 | S28: =IF(A28=1,Aannames!$B$35,0) -> 0 | T28: =SUM(N28:S28) -> 263.36586 | U28: =M28-T28 -> 16.364125 | V28: =V27+U28 -> -4594.6395
A29: 22 | B29: jun-28 | C29: =Aannames!$B$5*(1+Aannames!$B$6)^(A29-2)*(1+IF(MOD(A29-1,12)=0,Aannames!$B$7,0)) -> 140 | D29: =IF(A29>=Aannames!$B$24,Aannames!$B$26*(1+Aannames!$B$6)^(A29-Aannames!$B$24),0) -> 0 | E29: =C29+D29 -> 140 | F29: =E29*Aannames!$B$8 -> 63 | G29: =CohortBear!W$38 -> 170.2602 | H29: =G29*Aannames!$B$9 -> 1.702602 | I29: =H29*Aannames!$B$10*(1-Aannames!$B$11) -> 6.4979805 | J29: =MIN(J28*(1-Aannames!$B$18)+IF(A29>=Aannames!$B$14,Aannames!$B$15*Aannames!$B$16,0),(Aannames!$B$19+IF(A29>=Aannames!$B$24,Aannames!$B$25,0))*Aannames!$B$20) -> 7.3774803 | K29: =J29*Aannames!$B$17 -> 287.72173 | L29: =IF(AND(A29>12,MOD(A29-1,12)=0),Aannames!$B$37,0) -> 0 | M29: =I29+K29+L29 -> 294.21971 | N29: =Aannames!$B$28+G29*Aannames!$B$29 -> 63.405204 | O29: =Aannames!$B$30*(1+IF(A29>=Aannames!$B$24,1,0)) -> 80 | P29: =Aannames!$B$31 -> 70 | Q29: =IF(MOD(A29-1,12)=0,Aannames!$B$32,0) -> 0 | R29: =Aannames!$B$33+IF(MOD(A29-1,12)=0,Aannames!$B$34,0) -> 50 | S29: =IF(A29=1,Aannames!$B$35,0) -> 0 | T29: =SUM(N29:S29) -> 263.4052 | U29: =M29-T29 -> 30.814508 | V29: =V28+U29 -> -4563.825
A30: 23 | B30: jul-28 | C30: =Aannames!$B$5*(1+Aannames!$B$6)^(A30-2)*(1+IF(MOD(A30-1,12)=0,Aannames!$B$7,0)) -> 140 | D30: =IF(A30>=Aannames!$B$24,Aannames!$B$26*(1+Aannames!$B$6)^(A30-Aannames!$B$24),0) -> 0 | E30: =C30+D30 -> 140 | F30: =E30*Aannames!$B$8 -> 63 | G30: =CohortBear!X$38 -> 172.1646 | H30: =G30*Aannames!$B$9 -> 1.721646 | I30: =H30*Aannames!$B$10*(1-Aannames!$B$11) -> 6.570662 | J30: =MIN(J29*(1-Aannames!$B$18)+IF(A30>=Aannames!$B$14,Aannames!$B$15*Aannames!$B$16,0),(Aannames!$B$19+IF(A30>=Aannames!$B$24,Aannames!$B$25,0))*Aannames!$B$20) -> 7.7286063 | K30: =J30*Aannames!$B$17 -> 301.41565 | L30: =IF(AND(A30>12,MOD(A30-1,12)=0),Aannames!$B$37,0) -> 0 | M30: =I30+K30+L30 -> 307.98631 | N30: =Aannames!$B$28+G30*Aannames!$B$29 -> 63.443292 | O30: =Aannames!$B$30*(1+IF(A30>=Aannames!$B$24,1,0)) -> 80 | P30: =Aannames!$B$31 -> 70 | Q30: =IF(MOD(A30-1,12)=0,Aannames!$B$32,0) -> 0 | R30: =Aannames!$B$33+IF(MOD(A30-1,12)=0,Aannames!$B$34,0) -> 50 | S30: =IF(A30=1,Aannames!$B$35,0) -> 0 | T30: =SUM(N30:S30) -> 263.44329 | U30: =M30-T30 -> 44.543015 | V30: =V29+U30 -> -4519.2819
A31: 24 | B31: aug-28 | C31: =Aannames!$B$5*(1+Aannames!$B$6)^(A31-2)*(1+IF(MOD(A31-1,12)=0,Aannames!$B$7,0)) -> 140 | D31: =IF(A31>=Aannames!$B$24,Aannames!$B$26*(1+Aannames!$B$6)^(A31-Aannames!$B$24),0) -> 0 | E31: =C31+D31 -> 140 | F31: =E31*Aannames!$B$8 -> 63 | G31: =CohortBear!Y$38 -> 174.0564 | H31: =G31*Aannames!$B$9 -> 1.740564 | I31: =H31*Aannames!$B$10*(1-Aannames!$B$11) -> 6.6428625 | J31: =MIN(J30*(1-Aannames!$B$18)+IF(A31>=Aannames!$B$14,Aannames!$B$15*Aannames!$B$16,0),(Aannames!$B$19+IF(A31>=Aannames!$B$24,Aannames!$B$25,0))*Aannames!$B$20) -> 8.062176 | K31: =J31*Aannames!$B$17 -> 314.42486 | L31: =IF(AND(A31>12,MOD(A31-1,12)=0),Aannames!$B$37,0) -> 0 | M31: =I31+K31+L31 -> 321.06773 | N31: =Aannames!$B$28+G31*Aannames!$B$29 -> 63.481128 | O31: =Aannames!$B$30*(1+IF(A31>=Aannames!$B$24,1,0)) -> 80 | P31: =Aannames!$B$31 -> 70 | Q31: =IF(MOD(A31-1,12)=0,Aannames!$B$32,0) -> 0 | R31: =Aannames!$B$33+IF(MOD(A31-1,12)=0,Aannames!$B$34,0) -> 50 | S31: =IF(A31=1,Aannames!$B$35,0) -> 0 | T31: =SUM(N31:S31) -> 263.48113 | U31: =M31-T31 -> 57.586597 | V31: =V30+U31 -> -4461.6953
A32: 25 | B32: sep-28 | C32: =Aannames!$B$5*(1+Aannames!$B$6)^(A32-2)*(1+IF(MOD(A32-1,12)=0,Aannames!$B$7,0)) -> 252 | D32: =IF(A32>=Aannames!$B$24,Aannames!$B$26*(1+Aannames!$B$6)^(A32-Aannames!$B$24),0) -> 0 | E32: =C32+D32 -> 252 | F32: =E32*Aannames!$B$8 -> 113.4 | G32: =CohortBear!Z$38 -> 226.2852 | H32: =G32*Aannames!$B$9 -> 2.262852 | I32: =H32*Aannames!$B$10*(1-Aannames!$B$11) -> 8.6361747 | J32: =MIN(J31*(1-Aannames!$B$18)+IF(A32>=Aannames!$B$14,Aannames!$B$15*Aannames!$B$16,0),(Aannames!$B$19+IF(A32>=Aannames!$B$24,Aannames!$B$25,0))*Aannames!$B$20) -> 8.3790672 | K32: =J32*Aannames!$B$17 -> 326.78362 | L32: =IF(AND(A32>12,MOD(A32-1,12)=0),Aannames!$B$37,0) -> 0 | M32: =I32+K32+L32 -> 335.41979 | N32: =Aannames!$B$28+G32*Aannames!$B$29 -> 64.525704 | O32: =Aannames!$B$30*(1+IF(A32>=Aannames!$B$24,1,0)) -> 80 | P32: =Aannames!$B$31 -> 70 | Q32: =IF(MOD(A32-1,12)=0,Aannames!$B$32,0) -> 150 | R32: =Aannames!$B$33+IF(MOD(A32-1,12)=0,Aannames!$B$34,0) -> 350 | S32: =IF(A32=1,Aannames!$B$35,0) -> 0 | T32: =SUM(N32:S32) -> 714.5257 | U32: =M32-T32 -> -379.10591 | V32: =V31+U32 -> -4840.8013
A33: 26 | B33: okt-28 | C33: =Aannames!$B$5*(1+Aannames!$B$6)^(A33-2)*(1+IF(MOD(A33-1,12)=0,Aannames!$B$7,0)) -> 140 | D33: =IF(A33>=Aannames!$B$24,Aannames!$B$26*(1+Aannames!$B$6)^(A33-Aannames!$B$24),0) -> 0 | E33: =C33+D33 -> 140 | F33: =E33*Aannames!$B$8 -> 63 | G33: =CohortBear!AA$38 -> 191.8134 | H33: =G33*Aannames!$B$9 -> 1.918134 | I33: =H33*Aannames!$B$10*(1-Aannames!$B$11) -> 7.3205584 | J33: =MIN(J32*(1-Aannames!$B$18)+IF(A33>=Aannames!$B$14,Aannames!$B$15*Aannames!$B$16,0),(Aannames!$B$19+IF(A33>=Aannames!$B$24,Aannames!$B$25,0))*Aannames!$B$20) -> 8.6801138 | K33: =J33*Aannames!$B$17 -> 338.52444 | L33: =IF(AND(A33>12,MOD(A33-1,12)=0),Aannames!$B$37,0) -> 0 | M33: =I33+K33+L33 -> 345.845 | N33: =Aannames!$B$28+G33*Aannames!$B$29 -> 63.836268 | O33: =Aannames!$B$30*(1+IF(A33>=Aannames!$B$24,1,0)) -> 80 | P33: =Aannames!$B$31 -> 70 | Q33: =IF(MOD(A33-1,12)=0,Aannames!$B$32,0) -> 0 | R33: =Aannames!$B$33+IF(MOD(A33-1,12)=0,Aannames!$B$34,0) -> 50 | S33: =IF(A33=1,Aannames!$B$35,0) -> 0 | T33: =SUM(N33:S33) -> 263.83627 | U33: =M33-T33 -> 82.008729 | V33: =V32+U33 -> -4758.7925
A34: 27 | B34: nov-28 | C34: =Aannames!$B$5*(1+Aannames!$B$6)^(A34-2)*(1+IF(MOD(A34-1,12)=0,Aannames!$B$7,0)) -> 140 | D34: =IF(A34>=Aannames!$B$24,Aannames!$B$26*(1+Aannames!$B$6)^(A34-Aannames!$B$24),0) -> 0 | E34: =C34+D34 -> 140 | F34: =E34*Aannames!$B$8 -> 63 | G34: =CohortBear!AB$38 -> 188.5266 | H34: =G34*Aannames!$B$9 -> 1.885266 | I34: =H34*Aannames!$B$10*(1-Aannames!$B$11) -> 7.1951177 | J34: =MIN(J33*(1-Aannames!$B$18)+IF(A34>=Aannames!$B$14,Aannames!$B$15*Aannames!$B$16,0),(Aannames!$B$19+IF(A34>=Aannames!$B$24,Aannames!$B$25,0))*Aannames!$B$20) -> 8.9661081 | K34: =J34*Aannames!$B$17 -> 349.67822 | L34: =IF(AND(A34>12,MOD(A34-1,12)=0),Aannames!$B$37,0) -> 0 | M34: =I34+K34+L34 -> 356.87333 | N34: =Aannames!$B$28+G34*Aannames!$B$29 -> 63.770532 | O34: =Aannames!$B$30*(1+IF(A34>=Aannames!$B$24,1,0)) -> 80 | P34: =Aannames!$B$31 -> 70 | Q34: =IF(MOD(A34-1,12)=0,Aannames!$B$32,0) -> 0 | R34: =Aannames!$B$33+IF(MOD(A34-1,12)=0,Aannames!$B$34,0) -> 50 | S34: =IF(A34=1,Aannames!$B$35,0) -> 0 | T34: =SUM(N34:S34) -> 263.77053 | U34: =M34-T34 -> 93.102803 | V34: =V33+U34 -> -4665.6897
A35: 28 | B35: dec-28 | C35: =Aannames!$B$5*(1+Aannames!$B$6)^(A35-2)*(1+IF(MOD(A35-1,12)=0,Aannames!$B$7,0)) -> 140 | D35: =IF(A35>=Aannames!$B$24,Aannames!$B$26*(1+Aannames!$B$6)^(A35-Aannames!$B$24),0) -> 0 | E35: =C35+D35 -> 140 | F35: =E35*Aannames!$B$8 -> 63 | G35: =CohortBear!AC$38 -> 187.7472 | H35: =G35*Aannames!$B$9 -> 1.877472 | I35: =H35*Aannames!$B$10*(1-Aannames!$B$11) -> 7.1653719 | J35: =MIN(J34*(1-Aannames!$B$18)+IF(A35>=Aannames!$B$14,Aannames!$B$15*Aannames!$B$16,0),(Aannames!$B$19+IF(A35>=Aannames!$B$24,Aannames!$B$25,0))*Aannames!$B$20) -> 9.2378027 | K35: =J35*Aannames!$B$17 -> 360.27431 | L35: =IF(AND(A35>12,MOD(A35-1,12)=0),Aannames!$B$37,0) -> 0 | M35: =I35+K35+L35 -> 367.43968 | N35: =Aannames!$B$28+G35*Aannames!$B$29 -> 63.754944 | O35: =Aannames!$B$30*(1+IF(A35>=Aannames!$B$24,1,0)) -> 80 | P35: =Aannames!$B$31 -> 70 | Q35: =IF(MOD(A35-1,12)=0,Aannames!$B$32,0) -> 0 | R35: =Aannames!$B$33+IF(MOD(A35-1,12)=0,Aannames!$B$34,0) -> 50 | S35: =IF(A35=1,Aannames!$B$35,0) -> 0 | T35: =SUM(N35:S35) -> 263.75494 | U35: =M35-T35 -> 103.68473 | V35: =V34+U35 -> -4562.005
A36: 29 | B36: jan-29 | C36: =Aannames!$B$5*(1+Aannames!$B$6)^(A36-2)*(1+IF(MOD(A36-1,12)=0,Aannames!$B$7,0)) -> 140 | D36: =IF(A36>=Aannames!$B$24,Aannames!$B$26*(1+Aannames!$B$6)^(A36-Aannames!$B$24),0) -> 0 | E36: =C36+D36 -> 140 | F36: =E36*Aannames!$B$8 -> 63 | G36: =CohortBear!AD$38 -> 187.9128 | H36: =G36*Aannames!$B$9 -> 1.879128 | I36: =H36*Aannames!$B$10*(1-Aannames!$B$11) -> 7.171692 | J36: =MIN(J35*(1-Aannames!$B$18)+IF(A36>=Aannames!$B$14,Aannames!$B$15*Aannames!$B$16,0),(Aannames!$B$19+IF(A36>=Aannames!$B$24,Aannames!$B$25,0))*Aannames!$B$20) -> 9.4959126 | K36: =J36*Aannames!$B$17 -> 370.34059 | L36: =IF(AND(A36>12,MOD(A36-1,12)=0),Aannames!$B$37,0) -> 0 | M36: =I36+K36+L36 -> 377.51228 | N36: =Aannames!$B$28+G36*Aannames!$B$29 -> 63.758256 | O36: =Aannames!$B$30*(1+IF(A36>=Aannames!$B$24,1,0)) -> 80 | P36: =Aannames!$B$31 -> 70 | Q36: =IF(MOD(A36-1,12)=0,Aannames!$B$32,0) -> 0 | R36: =Aannames!$B$33+IF(MOD(A36-1,12)=0,Aannames!$B$34,0) -> 50 | S36: =IF(A36=1,Aannames!$B$35,0) -> 0 | T36: =SUM(N36:S36) -> 263.75826 | U36: =M36-T36 -> 113.75403 | V36: =V35+U36 -> -4448.251
A37: 30 | B37: feb-29 | C37: =Aannames!$B$5*(1+Aannames!$B$6)^(A37-2)*(1+IF(MOD(A37-1,12)=0,Aannames!$B$7,0)) -> 140 | D37: =IF(A37>=Aannames!$B$24,Aannames!$B$26*(1+Aannames!$B$6)^(A37-Aannames!$B$24),0) -> 0 | E37: =C37+D37 -> 140 | F37: =E37*Aannames!$B$8 -> 63 | G37: =CohortBear!AE$38 -> 188.9964 | H37: =G37*Aannames!$B$9 -> 1.889964 | I37: =H37*Aannames!$B$10*(1-Aannames!$B$11) -> 7.2130476 | J37: =MIN(J36*(1-Aannames!$B$18)+IF(A37>=Aannames!$B$14,Aannames!$B$15*Aannames!$B$16,0),(Aannames!$B$19+IF(A37>=Aannames!$B$24,Aannames!$B$25,0))*Aannames!$B$20) -> 9.741117 | K37: =J37*Aannames!$B$17 -> 379.90356 | L37: =IF(AND(A37>12,MOD(A37-1,12)=0),Aannames!$B$37,0) -> 0 | M37: =I37+K37+L37 -> 387.11661 | N37: =Aannames!$B$28+G37*Aannames!$B$29 -> 63.779928 | O37: =Aannames!$B$30*(1+IF(A37>=Aannames!$B$24,1,0)) -> 80 | P37: =Aannames!$B$31 -> 70 | Q37: =IF(MOD(A37-1,12)=0,Aannames!$B$32,0) -> 0 | R37: =Aannames!$B$33+IF(MOD(A37-1,12)=0,Aannames!$B$34,0) -> 50 | S37: =IF(A37=1,Aannames!$B$35,0) -> 0 | T37: =SUM(N37:S37) -> 263.77993 | U37: =M37-T37 -> 123.33668 | V37: =V36+U37 -> -4324.9143
A38: 31 | B38: mrt-29 | C38: =Aannames!$B$5*(1+Aannames!$B$6)^(A38-2)*(1+IF(MOD(A38-1,12)=0,Aannames!$B$7,0)) -> 140 | D38: =IF(A38>=Aannames!$B$24,Aannames!$B$26*(1+Aannames!$B$6)^(A38-Aannames!$B$24),0) -> 0 | E38: =C38+D38 -> 140 | F38: =E38*Aannames!$B$8 -> 63 | G38: =CohortBear!AF$38 -> 190.107 | H38: =G38*Aannames!$B$9 -> 1.90107 | I38: =H38*Aannames!$B$10*(1-Aannames!$B$11) -> 7.2554337 | J38: =MIN(J37*(1-Aannames!$B$18)+IF(A38>=Aannames!$B$14,Aannames!$B$15*Aannames!$B$16,0),(Aannames!$B$19+IF(A38>=Aannames!$B$24,Aannames!$B$25,0))*Aannames!$B$20) -> 9.9740611 | K38: =J38*Aannames!$B$17 -> 388.98838 | L38: =IF(AND(A38>12,MOD(A38-1,12)=0),Aannames!$B$37,0) -> 0 | M38: =I38+K38+L38 -> 396.24382 | N38: =Aannames!$B$28+G38*Aannames!$B$29 -> 63.80214 | O38: =Aannames!$B$30*(1+IF(A38>=Aannames!$B$24,1,0)) -> 80 | P38: =Aannames!$B$31 -> 70 | Q38: =IF(MOD(A38-1,12)=0,Aannames!$B$32,0) -> 0 | R38: =Aannames!$B$33+IF(MOD(A38-1,12)=0,Aannames!$B$34,0) -> 50 | S38: =IF(A38=1,Aannames!$B$35,0) -> 0 | T38: =SUM(N38:S38) -> 263.80214 | U38: =M38-T38 -> 132.44168 | V38: =V37+U38 -> -4192.4726
A39: 32 | B39: apr-29 | C39: =Aannames!$B$5*(1+Aannames!$B$6)^(A39-2)*(1+IF(MOD(A39-1,12)=0,Aannames!$B$7,0)) -> 140 | D39: =IF(A39>=Aannames!$B$24,Aannames!$B$26*(1+Aannames!$B$6)^(A39-Aannames!$B$24),0) -> 0 | E39: =C39+D39 -> 140 | F39: =E39*Aannames!$B$8 -> 63 | G39: =CohortBear!AG$38 -> 191.5308 | H39: =G39*Aannames!$B$9 -> 1.915308 | I39: =H39*Aannames!$B$10*(1-Aannames!$B$11) -> 7.309773 | J39: =MIN(J38*(1-Aannames!$B$18)+IF(A39>=Aannames!$B$14,Aannames!$B$15*Aannames!$B$16,0),(Aannames!$B$19+IF(A39>=Aannames!$B$24,Aannames!$B$25,0))*Aannames!$B$20) -> 10.195358 | K39: =J39*Aannames!$B$17 -> 397.61896 | L39: =IF(AND(A39>12,MOD(A39-1,12)=0),Aannames!$B$37,0) -> 0 | M39: =I39+K39+L39 -> 404.92874 | N39: =Aannames!$B$28+G39*Aannames!$B$29 -> 63.830616 | O39: =Aannames!$B$30*(1+IF(A39>=Aannames!$B$24,1,0)) -> 80 | P39: =Aannames!$B$31 -> 70 | Q39: =IF(MOD(A39-1,12)=0,Aannames!$B$32,0) -> 0 | R39: =Aannames!$B$33+IF(MOD(A39-1,12)=0,Aannames!$B$34,0) -> 50 | S39: =IF(A39=1,Aannames!$B$35,0) -> 0 | T39: =SUM(N39:S39) -> 263.83062 | U39: =M39-T39 -> 141.09812 | V39: =V38+U39 -> -4051.3745
A40: 33 | B40: mei-29 | C40: =Aannames!$B$5*(1+Aannames!$B$6)^(A40-2)*(1+IF(MOD(A40-1,12)=0,Aannames!$B$7,0)) -> 140 | D40: =IF(A40>=Aannames!$B$24,Aannames!$B$26*(1+Aannames!$B$6)^(A40-Aannames!$B$24),0) -> 0 | E40: =C40+D40 -> 140 | F40: =E40*Aannames!$B$8 -> 63 | G40: =CohortBear!AH$38 -> 192.78 | H40: =G40*Aannames!$B$9 -> 1.9278 | I40: =H40*Aannames!$B$10*(1-Aannames!$B$11) -> 7.3574487 | J40: =MIN(J39*(1-Aannames!$B$18)+IF(A40>=Aannames!$B$14,Aannames!$B$15*Aannames!$B$16,0),(Aannames!$B$19+IF(A40>=Aannames!$B$24,Aannames!$B$25,0))*Aannames!$B$20) -> 10.40559 | K40: =J40*Aannames!$B$17 -> 405.81802 | L40: =IF(AND(A40>12,MOD(A40-1,12)=0),Aannames!$B$37,0) -> 0 | M40: =I40+K40+L40 -> 413.17546 | N40: =Aannames!$B$28+G40*Aannames!$B$29 -> 63.8556 | O40: =Aannames!$B$30*(1+IF(A40>=Aannames!$B$24,1,0)) -> 80 | P40: =Aannames!$B$31 -> 70 | Q40: =IF(MOD(A40-1,12)=0,Aannames!$B$32,0) -> 0 | R40: =Aannames!$B$33+IF(MOD(A40-1,12)=0,Aannames!$B$34,0) -> 50 | S40: =IF(A40=1,Aannames!$B$35,0) -> 0 | T40: =SUM(N40:S40) -> 263.8556 | U40: =M40-T40 -> 149.31986 | V40: =V39+U40 -> -3902.0546
A41: 34 | B41: jun-29 | C41: =Aannames!$B$5*(1+Aannames!$B$6)^(A41-2)*(1+IF(MOD(A41-1,12)=0,Aannames!$B$7,0)) -> 140 | D41: =IF(A41>=Aannames!$B$24,Aannames!$B$26*(1+Aannames!$B$6)^(A41-Aannames!$B$24),0) -> 0 | E41: =C41+D41 -> 140 | F41: =E41*Aannames!$B$8 -> 63 | G41: =CohortBear!AI$38 -> 194.292 | H41: =G41*Aannames!$B$9 -> 1.94292 | I41: =H41*Aannames!$B$10*(1-Aannames!$B$11) -> 7.4151542 | J41: =MIN(J40*(1-Aannames!$B$18)+IF(A41>=Aannames!$B$14,Aannames!$B$15*Aannames!$B$16,0),(Aannames!$B$19+IF(A41>=Aannames!$B$24,Aannames!$B$25,0))*Aannames!$B$20) -> 10.605311 | K41: =J41*Aannames!$B$17 -> 413.60711 | L41: =IF(AND(A41>12,MOD(A41-1,12)=0),Aannames!$B$37,0) -> 0 | M41: =I41+K41+L41 -> 421.02227 | N41: =Aannames!$B$28+G41*Aannames!$B$29 -> 63.88584 | O41: =Aannames!$B$30*(1+IF(A41>=Aannames!$B$24,1,0)) -> 80 | P41: =Aannames!$B$31 -> 70 | Q41: =IF(MOD(A41-1,12)=0,Aannames!$B$32,0) -> 0 | R41: =Aannames!$B$33+IF(MOD(A41-1,12)=0,Aannames!$B$34,0) -> 50 | S41: =IF(A41=1,Aannames!$B$35,0) -> 0 | T41: =SUM(N41:S41) -> 263.88584 | U41: =M41-T41 -> 157.13643 | V41: =V40+U41 -> -3744.9182
A42: 35 | B42: jul-29 | C42: =Aannames!$B$5*(1+Aannames!$B$6)^(A42-2)*(1+IF(MOD(A42-1,12)=0,Aannames!$B$7,0)) -> 140 | D42: =IF(A42>=Aannames!$B$24,Aannames!$B$26*(1+Aannames!$B$6)^(A42-Aannames!$B$24),0) -> 0 | E42: =C42+D42 -> 140 | F42: =E42*Aannames!$B$8 -> 63 | G42: =CohortBear!AJ$38 -> 195.579 | H42: =G42*Aannames!$B$9 -> 1.95579 | I42: =H42*Aannames!$B$10*(1-Aannames!$B$11) -> 7.4642725 | J42: =MIN(J41*(1-Aannames!$B$18)+IF(A42>=Aannames!$B$14,Aannames!$B$15*Aannames!$B$16,0),(Aannames!$B$19+IF(A42>=Aannames!$B$24,Aannames!$B$25,0))*Aannames!$B$20) -> 10.795045 | K42: =J42*Aannames!$B$17 -> 421.00676 | L42: =IF(AND(A42>12,MOD(A42-1,12)=0),Aannames!$B$37,0) -> 0 | M42: =I42+K42+L42 -> 428.47103 | N42: =Aannames!$B$28+G42*Aannames!$B$29 -> 63.91158 | O42: =Aannames!$B$30*(1+IF(A42>=Aannames!$B$24,1,0)) -> 80 | P42: =Aannames!$B$31 -> 70 | Q42: =IF(MOD(A42-1,12)=0,Aannames!$B$32,0) -> 0 | R42: =Aannames!$B$33+IF(MOD(A42-1,12)=0,Aannames!$B$34,0) -> 50 | S42: =IF(A42=1,Aannames!$B$35,0) -> 0 | T42: =SUM(N42:S42) -> 263.91158 | U42: =M42-T42 -> 164.55945 | V42: =V41+U42 -> -3580.3587
A43: 36 | B43: aug-29 | C43: =Aannames!$B$5*(1+Aannames!$B$6)^(A43-2)*(1+IF(MOD(A43-1,12)=0,Aannames!$B$7,0)) -> 140 | D43: =IF(A43>=Aannames!$B$24,Aannames!$B$26*(1+Aannames!$B$6)^(A43-Aannames!$B$24),0) -> 0 | E43: =C43+D43 -> 140 | F43: =E43*Aannames!$B$8 -> 63 | G43: =CohortBear!AK$38 -> 197.0784 | H43: =G43*Aannames!$B$9 -> 1.970784 | I43: =H43*Aannames!$B$10*(1-Aannames!$B$11) -> 7.5214971 | J43: =MIN(J42*(1-Aannames!$B$18)+IF(A43>=Aannames!$B$14,Aannames!$B$15*Aannames!$B$16,0),(Aannames!$B$19+IF(A43>=Aannames!$B$24,Aannames!$B$25,0))*Aannames!$B$20) -> 10.975293 | K43: =J43*Aannames!$B$17 -> 428.03642 | L43: =IF(AND(A43>12,MOD(A43-1,12)=0),Aannames!$B$37,0) -> 0 | M43: =I43+K43+L43 -> 435.55792 | N43: =Aannames!$B$28+G43*Aannames!$B$29 -> 63.941568 | O43: =Aannames!$B$30*(1+IF(A43>=Aannames!$B$24,1,0)) -> 80 | P43: =Aannames!$B$31 -> 70 | Q43: =IF(MOD(A43-1,12)=0,Aannames!$B$32,0) -> 0 | R43: =Aannames!$B$33+IF(MOD(A43-1,12)=0,Aannames!$B$34,0) -> 50 | S43: =IF(A43=1,Aannames!$B$35,0) -> 0 | T43: =SUM(N43:S43) -> 263.94157 | U43: =M43-T43 -> 171.61635 | V43: =V42+U43 -> -3408.7424
A45: KPI's
A46: MAU M12 | C46: =G19 -> 143.271
A47: MAU M24 | C47: =G31 -> 174.0564
A48: MAU M36 | C48: =G43 -> 197.0784
A49: Betalende venues M36 | C49: =J43 -> 10.975293
A50: MRR M36 (venue + consumer) | C50: =K43+I43 -> 435.55792
A51: Omzet jaar 3 (M25-M36) | C51: =SUM(M32:M43) -> 4669.6059
A52: Blended ARPU M36 (A$/MAU/mnd) | C52: =IF(G43=0,0,M43/G43) -> 2.2100744
A53: Consumer-LTV per geactiveerde gebruiker | C53: =Retentie!$B$38*Aannames!$B$9*Aannames!$B$10*(1-Aannames!$B$11) -> 0.11411335
A54: Blended consumer-CAC (marketing/actieve) | C54: =SUM(R8:R43)/SUM(F8:F43) -> 1.0668563
A55: LTV:CAC consumer | C55: =IF(C54=0,0,C53/C54) -> 0.10696225
A56: Venue-LTV (prijs x marge / churn) | C56: =Aannames!$B$17*Aannames!$B$22/Aannames!$B$18 -> 717.6
A57: Venue-CAC | C57: =Aannames!$B$21 -> 150
A58: LTV:CAC venue | C58: =IF(C57=0,0,C56/C57) -> 4.784
A59: Venue-payback (mnd) | C59: =Aannames!$B$21/(Aannames!$B$17*Aannames!$B$22) -> 4.180602
A60: Max. cumulatieve burn | C60: =-MIN(V8:V43) -> 4840.8013
A61: Cumulatieve cashflow M36 | C61: =V43 -> -3408.7424
A62: Break-even (cumulatief), maand # | C62: =IF(V43<0,"niet in 36 mnd",SUMPRODUCT(--($V$8:$V$43<0))+1) -> niet in 36 mnd | E62: Break-even-telling klopt zodra het cumulatief na de eerste kruising positief blijft (in alle drie scenario's het geval).

Sheet CohortBear
A1: Cohort \ kalendermaand | B1: 1 | C1: 2 | D1: 3 | E1: 4 | F1: 5 | G1: 6 | H1: 7 | I1: 8 | J1: 9 | K1: 10 | L1: 11 | M1: 12 | N1: 13 | O1: 14 | P1: 15 | Q1: 16 | R1: 17 | S1: 18 | T1: 19 | U1: 20 | V1: 21 | W1: 22 | X1: 23 | Y1: 24 | Z1: 25 | AA1: 26 | AB1: 27 | AC1: 28 | AD1: 29 | AE1: 30 | AF1: 31 | AG1: 32 | AH1: 33 | AI1: 34 | AJ1: 35 | AK1: 36
A2: 1 | B2: =ModelBear!$F$8*Retentie!$B$2 -> 225 | C2: =ModelBear!$F$8*Retentie!$B$3 -> 63 | D2: =ModelBear!$F$8*Retentie!$B$4 -> 40.5 | E2: =ModelBear!$F$8*Retentie!$B$5 -> 29.25 | F2: =ModelBear!$F$8*Retentie!$B$6 -> 22.5 | G2: =ModelBear!$F$8*Retentie!$B$7 -> 19.125 | H2: =ModelBear!$F$8*Retentie!$B$8 -> 16.875 | I2: =ModelBear!$F$8*Retentie!$B$9 -> 15.3 | J2: =ModelBear!$F$8*Retentie!$B$10 -> 13.95 | K2: =ModelBear!$F$8*Retentie!$B$11 -> 13.05 | L2: =ModelBear!$F$8*Retentie!$B$12 -> 12.15 | M2: =ModelBear!$F$8*Retentie!$B$13 -> 11.475 | N2: =ModelBear!$F$8*Retentie!$B$14 -> 10.8 | O2: =ModelBear!$F$8*Retentie!$B$15 -> 10.35 | P2: =ModelBear!$F$8*Retentie!$B$16 -> 9.9 | Q2: =ModelBear!$F$8*Retentie!$B$17 -> 9.675 | R2: =ModelBear!$F$8*Retentie!$B$18 -> 9.45 | S2: =ModelBear!$F$8*Retentie!$B$19 -> 9.225 | T2: =ModelBear!$F$8*Retentie!$B$20 -> 9 | U2: =ModelBear!$F$8*Retentie!$B$21 -> 8.775 | V2: =ModelBear!$F$8*Retentie!$B$22 -> 8.55 | W2: =ModelBear!$F$8*Retentie!$B$23 -> 8.325 | X2: =ModelBear!$F$8*Retentie!$B$24 -> 8.1 | Y2: =ModelBear!$F$8*Retentie!$B$25 -> 7.875 | Z2: =ModelBear!$F$8*Retentie!$B$26 -> 7.65 | AA2: =ModelBear!$F$8*Retentie!$B$27 -> 7.425 | AB2: =ModelBear!$F$8*Retentie!$B$28 -> 7.2 | AC2: =ModelBear!$F$8*Retentie!$B$29 -> 6.975 | AD2: =ModelBear!$F$8*Retentie!$B$30 -> 6.75 | AE2: =ModelBear!$F$8*Retentie!$B$31 -> 6.75 | AF2: =ModelBear!$F$8*Retentie!$B$32 -> 6.525 | AG2: =ModelBear!$F$8*Retentie!$B$33 -> 6.525 | AH2: =ModelBear!$F$8*Retentie!$B$34 -> 6.3 | AI2: =ModelBear!$F$8*Retentie!$B$35 -> 6.3 | AJ2: =ModelBear!$F$8*Retentie!$B$36 -> 6.075 | AK2: =ModelBear!$F$8*Retentie!$B$37 -> 6.075
A3: 2 | C3: =ModelBear!$F$9*Retentie!$B$2 -> 63 | D3: =ModelBear!$F$9*Retentie!$B$3 -> 17.64 | E3: =ModelBear!$F$9*Retentie!$B$4 -> 11.34 | F3: =ModelBear!$F$9*Retentie!$B$5 -> 8.19 | G3: =ModelBear!$F$9*Retentie!$B$6 -> 6.3 | H3: =ModelBear!$F$9*Retentie!$B$7 -> 5.355 | I3: =ModelBear!$F$9*Retentie!$B$8 -> 4.725 | J3: =ModelBear!$F$9*Retentie!$B$9 -> 4.284 | K3: =ModelBear!$F$9*Retentie!$B$10 -> 3.906 | L3: =ModelBear!$F$9*Retentie!$B$11 -> 3.654 | M3: =ModelBear!$F$9*Retentie!$B$12 -> 3.402 | N3: =ModelBear!$F$9*Retentie!$B$13 -> 3.213 | O3: =ModelBear!$F$9*Retentie!$B$14 -> 3.024 | P3: =ModelBear!$F$9*Retentie!$B$15 -> 2.898 | Q3: =ModelBear!$F$9*Retentie!$B$16 -> 2.772 | R3: =ModelBear!$F$9*Retentie!$B$17 -> 2.709 | S3: =ModelBear!$F$9*Retentie!$B$18 -> 2.646 | T3: =ModelBear!$F$9*Retentie!$B$19 -> 2.583 | U3: =ModelBear!$F$9*Retentie!$B$20 -> 2.52 | V3: =ModelBear!$F$9*Retentie!$B$21 -> 2.457 | W3: =ModelBear!$F$9*Retentie!$B$22 -> 2.394 | X3: =ModelBear!$F$9*Retentie!$B$23 -> 2.331 | Y3: =ModelBear!$F$9*Retentie!$B$24 -> 2.268 | Z3: =ModelBear!$F$9*Retentie!$B$25 -> 2.205 | AA3: =ModelBear!$F$9*Retentie!$B$26 -> 2.142 | AB3: =ModelBear!$F$9*Retentie!$B$27 -> 2.079 | AC3: =ModelBear!$F$9*Retentie!$B$28 -> 2.016 | AD3: =ModelBear!$F$9*Retentie!$B$29 -> 1.953 | AE3: =ModelBear!$F$9*Retentie!$B$30 -> 1.89 | AF3: =ModelBear!$F$9*Retentie!$B$31 -> 1.89 | AG3: =ModelBear!$F$9*Retentie!$B$32 -> 1.827 | AH3: =ModelBear!$F$9*Retentie!$B$33 -> 1.827 | AI3: =ModelBear!$F$9*Retentie!$B$34 -> 1.764 | AJ3: =ModelBear!$F$9*Retentie!$B$35 -> 1.764 | AK3: =ModelBear!$F$9*Retentie!$B$36 -> 1.701
A4: 3 | D4: =ModelBear!$F$10*Retentie!$B$2 -> 63 | E4: =ModelBear!$F$10*Retentie!$B$3 -> 17.64 | F4: =ModelBear!$F$10*Retentie!$B$4 -> 11.34 | G4: =ModelBear!$F$10*Retentie!$B$5 -> 8.19 | H4: =ModelBear!$F$10*Retentie!$B$6 -> 6.3 | I4: =ModelBear!$F$10*Retentie!$B$7 -> 5.355 | J4: =ModelBear!$F$10*Retentie!$B$8 -> 4.725 | K4: =ModelBear!$F$10*Retentie!$B$9 -> 4.284 | L4: =ModelBear!$F$10*Retentie!$B$10 -> 3.906 | M4: =ModelBear!$F$10*Retentie!$B$11 -> 3.654 | N4: =ModelBear!$F$10*Retentie!$B$12 -> 3.402 | O4: =ModelBear!$F$10*Retentie!$B$13 -> 3.213 | P4: =ModelBear!$F$10*Retentie!$B$14 -> 3.024 | Q4: =ModelBear!$F$10*Retentie!$B$15 -> 2.898 | R4: =ModelBear!$F$10*Retentie!$B$16 -> 2.772 | S4: =ModelBear!$F$10*Retentie!$B$17 -> 2.709 | T4: =ModelBear!$F$10*Retentie!$B$18 -> 2.646 | U4: =ModelBear!$F$10*Retentie!$B$19 -> 2.583 | V4: =ModelBear!$F$10*Retentie!$B$20 -> 2.52 | W4: =ModelBear!$F$10*Retentie!$B$21 -> 2.457 | X4: =ModelBear!$F$10*Retentie!$B$22 -> 2.394 | Y4: =ModelBear!$F$10*Retentie!$B$23 -> 2.331 | Z4: =ModelBear!$F$10*Retentie!$B$24 -> 2.268 | AA4: =ModelBear!$F$10*Retentie!$B$25 -> 2.205 | AB4: =ModelBear!$F$10*Retentie!$B$26 -> 2.142 | AC4: =ModelBear!$F$10*Retentie!$B$27 -> 2.079 | AD4: =ModelBear!$F$10*Retentie!$B$28 -> 2.016 | AE4: =ModelBear!$F$10*Retentie!$B$29 -> 1.953 | AF4: =ModelBear!$F$10*Retentie!$B$30 -> 1.89 | AG4: =ModelBear!$F$10*Retentie!$B$31 -> 1.89 | AH4: =ModelBear!$F$10*Retentie!$B$32 -> 1.827 | AI4: =ModelBear!$F$10*Retentie!$B$33 -> 1.827 | AJ4: =ModelBear!$F$10*Retentie!$B$34 -> 1.764 | AK4: =ModelBear!$F$10*Retentie!$B$35 -> 1.764
A5: 4 | E5: =ModelBear!$F$11*Retentie!$B$2 -> 63 | F5: =ModelBear!$F$11*Retentie!$B$3 -> 17.64 | G5: =ModelBear!$F$11*Retentie!$B$4 -> 11.34 | H5: =ModelBear!$F$11*Retentie!$B$5 -> 8.19 | I5: =ModelBear!$F$11*Retentie!$B$6 -> 6.3 | J5: =ModelBear!$F$11*Retentie!$B$7 -> 5.355 | K5: =ModelBear!$F$11*Retentie!$B$8 -> 4.725 | L5: =ModelBear!$F$11*Retentie!$B$9 -> 4.284 | M5: =ModelBear!$F$11*Retentie!$B$10 -> 3.906 | N5: =ModelBear!$F$11*Retentie!$B$11 -> 3.654 | O5: =ModelBear!$F$11*Retentie!$B$12 -> 3.402 | P5: =ModelBear!$F$11*Retentie!$B$13 -> 3.213 | Q5: =ModelBear!$F$11*Retentie!$B$14 -> 3.024 | R5: =ModelBear!$F$11*Retentie!$B$15 -> 2.898 | S5: =ModelBear!$F$11*Retentie!$B$16 -> 2.772 | T5: =ModelBear!$F$11*Retentie!$B$17 -> 2.709 | U5: =ModelBear!$F$11*Retentie!$B$18 -> 2.646 | V5: =ModelBear!$F$11*Retentie!$B$19 -> 2.583 | W5: =ModelBear!$F$11*Retentie!$B$20 -> 2.52 | X5: =ModelBear!$F$11*Retentie!$B$21 -> 2.457 | Y5: =ModelBear!$F$11*Retentie!$B$22 -> 2.394 | Z5: =ModelBear!$F$11*Retentie!$B$23 -> 2.331 | AA5: =ModelBear!$F$11*Retentie!$B$24 -> 2.268 | AB5: =ModelBear!$F$11*Retentie!$B$25 -> 2.205 | AC5: =ModelBear!$F$11*Retentie!$B$26 -> 2.142 | AD5: =ModelBear!$F$11*Retentie!$B$27 -> 2.079 | AE5: =ModelBear!$F$11*Retentie!$B$28 -> 2.016 | AF5: =ModelBear!$F$11*Retentie!$B$29 -> 1.953 | AG5: =ModelBear!$F$11*Retentie!$B$30 -> 1.89 | AH5: =ModelBear!$F$11*Retentie!$B$31 -> 1.89 | AI5: =ModelBear!$F$11*Retentie!$B$32 -> 1.827 | AJ5: =ModelBear!$F$11*Retentie!$B$33 -> 1.827 | AK5: =ModelBear!$F$11*Retentie!$B$34 -> 1.764
A6: 5 | F6: =ModelBear!$F$12*Retentie!$B$2 -> 63 | G6: =ModelBear!$F$12*Retentie!$B$3 -> 17.64 | H6: =ModelBear!$F$12*Retentie!$B$4 -> 11.34 | I6: =ModelBear!$F$12*Retentie!$B$5 -> 8.19 | J6: =ModelBear!$F$12*Retentie!$B$6 -> 6.3 | K6: =ModelBear!$F$12*Retentie!$B$7 -> 5.355 | L6: =ModelBear!$F$12*Retentie!$B$8 -> 4.725 | M6: =ModelBear!$F$12*Retentie!$B$9 -> 4.284 | N6: =ModelBear!$F$12*Retentie!$B$10 -> 3.906 | O6: =ModelBear!$F$12*Retentie!$B$11 -> 3.654 | P6: =ModelBear!$F$12*Retentie!$B$12 -> 3.402 | Q6: =ModelBear!$F$12*Retentie!$B$13 -> 3.213 | R6: =ModelBear!$F$12*Retentie!$B$14 -> 3.024 | S6: =ModelBear!$F$12*Retentie!$B$15 -> 2.898 | T6: =ModelBear!$F$12*Retentie!$B$16 -> 2.772 | U6: =ModelBear!$F$12*Retentie!$B$17 -> 2.709 | V6: =ModelBear!$F$12*Retentie!$B$18 -> 2.646 | W6: =ModelBear!$F$12*Retentie!$B$19 -> 2.583 | X6: =ModelBear!$F$12*Retentie!$B$20 -> 2.52 | Y6: =ModelBear!$F$12*Retentie!$B$21 -> 2.457 | Z6: =ModelBear!$F$12*Retentie!$B$22 -> 2.394 | AA6: =ModelBear!$F$12*Retentie!$B$23 -> 2.331 | AB6: =ModelBear!$F$12*Retentie!$B$24 -> 2.268 | AC6: =ModelBear!$F$12*Retentie!$B$25 -> 2.205 | AD6: =ModelBear!$F$12*Retentie!$B$26 -> 2.142 | AE6: =ModelBear!$F$12*Retentie!$B$27 -> 2.079 | AF6: =ModelBear!$F$12*Retentie!$B$28 -> 2.016 | AG6: =ModelBear!$F$12*Retentie!$B$29 -> 1.953 | AH6: =ModelBear!$F$12*Retentie!$B$30 -> 1.89 | AI6: =ModelBear!$F$12*Retentie!$B$31 -> 1.89 | AJ6: =ModelBear!$F$12*Retentie!$B$32 -> 1.827 | AK6: =ModelBear!$F$12*Retentie!$B$33 -> 1.827
A7: 6 | G7: =ModelBear!$F$13*Retentie!$B$2 -> 63 | H7: =ModelBear!$F$13*Retentie!$B$3 -> 17.64 | I7: =ModelBear!$F$13*Retentie!$B$4 -> 11.34 | J7: =ModelBear!$F$13*Retentie!$B$5 -> 8.19 | K7: =ModelBear!$F$13*Retentie!$B$6 -> 6.3 | L7: =ModelBear!$F$13*Retentie!$B$7 -> 5.355 | M7: =ModelBear!$F$13*Retentie!$B$8 -> 4.725 | N7: =ModelBear!$F$13*Retentie!$B$9 -> 4.284 | O7: =ModelBear!$F$13*Retentie!$B$10 -> 3.906 | P7: =ModelBear!$F$13*Retentie!$B$11 -> 3.654 | Q7: =ModelBear!$F$13*Retentie!$B$12 -> 3.402 | R7: =ModelBear!$F$13*Retentie!$B$13 -> 3.213 | S7: =ModelBear!$F$13*Retentie!$B$14 -> 3.024 | T7: =ModelBear!$F$13*Retentie!$B$15 -> 2.898 | U7: =ModelBear!$F$13*Retentie!$B$16 -> 2.772 | V7: =ModelBear!$F$13*Retentie!$B$17 -> 2.709 | W7: =ModelBear!$F$13*Retentie!$B$18 -> 2.646 | X7: =ModelBear!$F$13*Retentie!$B$19 -> 2.583 | Y7: =ModelBear!$F$13*Retentie!$B$20 -> 2.52 | Z7: =ModelBear!$F$13*Retentie!$B$21 -> 2.457 | AA7: =ModelBear!$F$13*Retentie!$B$22 -> 2.394 | AB7: =ModelBear!$F$13*Retentie!$B$23 -> 2.331 | AC7: =ModelBear!$F$13*Retentie!$B$24 -> 2.268 | AD7: =ModelBear!$F$13*Retentie!$B$25 -> 2.205 | AE7: =ModelBear!$F$13*Retentie!$B$26 -> 2.142 | AF7: =ModelBear!$F$13*Retentie!$B$27 -> 2.079 | AG7: =ModelBear!$F$13*Retentie!$B$28 -> 2.016 | AH7: =ModelBear!$F$13*Retentie!$B$29 -> 1.953 | AI7: =ModelBear!$F$13*Retentie!$B$30 -> 1.89 | AJ7: =ModelBear!$F$13*Retentie!$B$31 -> 1.89 | AK7: =ModelBear!$F$13*Retentie!$B$32 -> 1.827
A8: 7 | H8: =ModelBear!$F$14*Retentie!$B$2 -> 63 | I8: =ModelBear!$F$14*Retentie!$B$3 -> 17.64 | J8: =ModelBear!$F$14*Retentie!$B$4 -> 11.34 | K8: =ModelBear!$F$14*Retentie!$B$5 -> 8.19 | L8: =ModelBear!$F$14*Retentie!$B$6 -> 6.3 | M8: =ModelBear!$F$14*Retentie!$B$7 -> 5.355 | N8: =ModelBear!$F$14*Retentie!$B$8 -> 4.725 | O8: =ModelBear!$F$14*Retentie!$B$9 -> 4.284 | P8: =ModelBear!$F$14*Retentie!$B$10 -> 3.906 | Q8: =ModelBear!$F$14*Retentie!$B$11 -> 3.654 | R8: =ModelBear!$F$14*Retentie!$B$12 -> 3.402 | S8: =ModelBear!$F$14*Retentie!$B$13 -> 3.213 | T8: =ModelBear!$F$14*Retentie!$B$14 -> 3.024 | U8: =ModelBear!$F$14*Retentie!$B$15 -> 2.898 | V8: =ModelBear!$F$14*Retentie!$B$16 -> 2.772 | W8: =ModelBear!$F$14*Retentie!$B$17 -> 2.709 | X8: =ModelBear!$F$14*Retentie!$B$18 -> 2.646 | Y8: =ModelBear!$F$14*Retentie!$B$19 -> 2.583 | Z8: =ModelBear!$F$14*Retentie!$B$20 -> 2.52 | AA8: =ModelBear!$F$14*Retentie!$B$21 -> 2.457 | AB8: =ModelBear!$F$14*Retentie!$B$22 -> 2.394 | AC8: =ModelBear!$F$14*Retentie!$B$23 -> 2.331 | AD8: =ModelBear!$F$14*Retentie!$B$24 -> 2.268 | AE8: =ModelBear!$F$14*Retentie!$B$25 -> 2.205 | AF8: =ModelBear!$F$14*Retentie!$B$26 -> 2.142 | AG8: =ModelBear!$F$14*Retentie!$B$27 -> 2.079 | AH8: =ModelBear!$F$14*Retentie!$B$28 -> 2.016 | AI8: =ModelBear!$F$14*Retentie!$B$29 -> 1.953 | AJ8: =ModelBear!$F$14*Retentie!$B$30 -> 1.89 | AK8: =ModelBear!$F$14*Retentie!$B$31 -> 1.89
A9: 8 | I9: =ModelBear!$F$15*Retentie!$B$2 -> 63 | J9: =ModelBear!$F$15*Retentie!$B$3 -> 17.64 | K9: =ModelBear!$F$15*Retentie!$B$4 -> 11.34 | L9: =ModelBear!$F$15*Retentie!$B$5 -> 8.19 | M9: =ModelBear!$F$15*Retentie!$B$6 -> 6.3 | N9: =ModelBear!$F$15*Retentie!$B$7 -> 5.355 | O9: =ModelBear!$F$15*Retentie!$B$8 -> 4.725 | P9: =ModelBear!$F$15*Retentie!$B$9 -> 4.284 | Q9: =ModelBear!$F$15*Retentie!$B$10 -> 3.906 | R9: =ModelBear!$F$15*Retentie!$B$11 -> 3.654 | S9: =ModelBear!$F$15*Retentie!$B$12 -> 3.402 | T9: =ModelBear!$F$15*Retentie!$B$13 -> 3.213 | U9: =ModelBear!$F$15*Retentie!$B$14 -> 3.024 | V9: =ModelBear!$F$15*Retentie!$B$15 -> 2.898 | W9: =ModelBear!$F$15*Retentie!$B$16 -> 2.772 | X9: =ModelBear!$F$15*Retentie!$B$17 -> 2.709 | Y9: =ModelBear!$F$15*Retentie!$B$18 -> 2.646 | Z9: =ModelBear!$F$15*Retentie!$B$19 -> 2.583 | AA9: =ModelBear!$F$15*Retentie!$B$20 -> 2.52 | AB9: =ModelBear!$F$15*Retentie!$B$21 -> 2.457 | AC9: =ModelBear!$F$15*Retentie!$B$22 -> 2.394 | AD9: =ModelBear!$F$15*Retentie!$B$23 -> 2.331 | AE9: =ModelBear!$F$15*Retentie!$B$24 -> 2.268 | AF9: =ModelBear!$F$15*Retentie!$B$25 -> 2.205 | AG9: =ModelBear!$F$15*Retentie!$B$26 -> 2.142 | AH9: =ModelBear!$F$15*Retentie!$B$27 -> 2.079 | AI9: =ModelBear!$F$15*Retentie!$B$28 -> 2.016 | AJ9: =ModelBear!$F$15*Retentie!$B$29 -> 1.953 | AK9: =ModelBear!$F$15*Retentie!$B$30 -> 1.89
A10: 9 | J10: =ModelBear!$F$16*Retentie!$B$2 -> 63 | K10: =ModelBear!$F$16*Retentie!$B$3 -> 17.64 | L10: =ModelBear!$F$16*Retentie!$B$4 -> 11.34 | M10: =ModelBear!$F$16*Retentie!$B$5 -> 8.19 | N10: =ModelBear!$F$16*Retentie!$B$6 -> 6.3 | O10: =ModelBear!$F$16*Retentie!$B$7 -> 5.355 | P10: =ModelBear!$F$16*Retentie!$B$8 -> 4.725 | Q10: =ModelBear!$F$16*Retentie!$B$9 -> 4.284 | R10: =ModelBear!$F$16*Retentie!$B$10 -> 3.906 | S10: =ModelBear!$F$16*Retentie!$B$11 -> 3.654 | T10: =ModelBear!$F$16*Retentie!$B$12 -> 3.402 | U10: =ModelBear!$F$16*Retentie!$B$13 -> 3.213 | V10: =ModelBear!$F$16*Retentie!$B$14 -> 3.024 | W10: =ModelBear!$F$16*Retentie!$B$15 -> 2.898 | X10: =ModelBear!$F$16*Retentie!$B$16 -> 2.772 | Y10: =ModelBear!$F$16*Retentie!$B$17 -> 2.709 | Z10: =ModelBear!$F$16*Retentie!$B$18 -> 2.646 | AA10: =ModelBear!$F$16*Retentie!$B$19 -> 2.583 | AB10: =ModelBear!$F$16*Retentie!$B$20 -> 2.52 | AC10: =ModelBear!$F$16*Retentie!$B$21 -> 2.457 | AD10: =ModelBear!$F$16*Retentie!$B$22 -> 2.394 | AE10: =ModelBear!$F$16*Retentie!$B$23 -> 2.331 | AF10: =ModelBear!$F$16*Retentie!$B$24 -> 2.268 | AG10: =ModelBear!$F$16*Retentie!$B$25 -> 2.205 | AH10: =ModelBear!$F$16*Retentie!$B$26 -> 2.142 | AI10: =ModelBear!$F$16*Retentie!$B$27 -> 2.079 | AJ10: =ModelBear!$F$16*Retentie!$B$28 -> 2.016 | AK10: =ModelBear!$F$16*Retentie!$B$29 -> 1.953
A11: 10 | K11: =ModelBear!$F$17*Retentie!$B$2 -> 63 | L11: =ModelBear!$F$17*Retentie!$B$3 -> 17.64 | M11: =ModelBear!$F$17*Retentie!$B$4 -> 11.34 | N11: =ModelBear!$F$17*Retentie!$B$5 -> 8.19 | O11: =ModelBear!$F$17*Retentie!$B$6 -> 6.3 | P11: =ModelBear!$F$17*Retentie!$B$7 -> 5.355 | Q11: =ModelBear!$F$17*Retentie!$B$8 -> 4.725 | R11: =ModelBear!$F$17*Retentie!$B$9 -> 4.284 | S11: =ModelBear!$F$17*Retentie!$B$10 -> 3.906 | T11: =ModelBear!$F$17*Retentie!$B$11 -> 3.654 | U11: =ModelBear!$F$17*Retentie!$B$12 -> 3.402 | V11: =ModelBear!$F$17*Retentie!$B$13 -> 3.213 | W11: =ModelBear!$F$17*Retentie!$B$14 -> 3.024 | X11: =ModelBear!$F$17*Retentie!$B$15 -> 2.898 | Y11: =ModelBear!$F$17*Retentie!$B$16 -> 2.772 | Z11: =ModelBear!$F$17*Retentie!$B$17 -> 2.709 | AA11: =ModelBear!$F$17*Retentie!$B$18 -> 2.646 | AB11: =ModelBear!$F$17*Retentie!$B$19 -> 2.583 | AC11: =ModelBear!$F$17*Retentie!$B$20 -> 2.52 | AD11: =ModelBear!$F$17*Retentie!$B$21 -> 2.457 | AE11: =ModelBear!$F$17*Retentie!$B$22 -> 2.394 | AF11: =ModelBear!$F$17*Retentie!$B$23 -> 2.331 | AG11: =ModelBear!$F$17*Retentie!$B$24 -> 2.268 | AH11: =ModelBear!$F$17*Retentie!$B$25 -> 2.205 | AI11: =ModelBear!$F$17*Retentie!$B$26 -> 2.142 | AJ11: =ModelBear!$F$17*Retentie!$B$27 -> 2.079 | AK11: =ModelBear!$F$17*Retentie!$B$28 -> 2.016
A12: 11 | L12: =ModelBear!$F$18*Retentie!$B$2 -> 63 | M12: =ModelBear!$F$18*Retentie!$B$3 -> 17.64 | N12: =ModelBear!$F$18*Retentie!$B$4 -> 11.34 | O12: =ModelBear!$F$18*Retentie!$B$5 -> 8.19 | P12: =ModelBear!$F$18*Retentie!$B$6 -> 6.3 | Q12: =ModelBear!$F$18*Retentie!$B$7 -> 5.355 | R12: =ModelBear!$F$18*Retentie!$B$8 -> 4.725 | S12: =ModelBear!$F$18*Retentie!$B$9 -> 4.284 | T12: =ModelBear!$F$18*Retentie!$B$10 -> 3.906 | U12: =ModelBear!$F$18*Retentie!$B$11 -> 3.654 | V12: =ModelBear!$F$18*Retentie!$B$12 -> 3.402 | W12: =ModelBear!$F$18*Retentie!$B$13 -> 3.213 | X12: =ModelBear!$F$18*Retentie!$B$14 -> 3.024 | Y12: =ModelBear!$F$18*Retentie!$B$15 -> 2.898 | Z12: =ModelBear!$F$18*Retentie!$B$16 -> 2.772 | AA12: =ModelBear!$F$18*Retentie!$B$17 -> 2.709 | AB12: =ModelBear!$F$18*Retentie!$B$18 -> 2.646 | AC12: =ModelBear!$F$18*Retentie!$B$19 -> 2.583 | AD12: =ModelBear!$F$18*Retentie!$B$20 -> 2.52 | AE12: =ModelBear!$F$18*Retentie!$B$21 -> 2.457 | AF12: =ModelBear!$F$18*Retentie!$B$22 -> 2.394 | AG12: =ModelBear!$F$18*Retentie!$B$23 -> 2.331 | AH12: =ModelBear!$F$18*Retentie!$B$24 -> 2.268 | AI12: =ModelBear!$F$18*Retentie!$B$25 -> 2.205 | AJ12: =ModelBear!$F$18*Retentie!$B$26 -> 2.142 | AK12: =ModelBear!$F$18*Retentie!$B$27 -> 2.079
A13: 12 | M13: =ModelBear!$F$19*Retentie!$B$2 -> 63 | N13: =ModelBear!$F$19*Retentie!$B$3 -> 17.64 | O13: =ModelBear!$F$19*Retentie!$B$4 -> 11.34 | P13: =ModelBear!$F$19*Retentie!$B$5 -> 8.19 | Q13: =ModelBear!$F$19*Retentie!$B$6 -> 6.3 | R13: =ModelBear!$F$19*Retentie!$B$7 -> 5.355 | S13: =ModelBear!$F$19*Retentie!$B$8 -> 4.725 | T13: =ModelBear!$F$19*Retentie!$B$9 -> 4.284 | U13: =ModelBear!$F$19*Retentie!$B$10 -> 3.906 | V13: =ModelBear!$F$19*Retentie!$B$11 -> 3.654 | W13: =ModelBear!$F$19*Retentie!$B$12 -> 3.402 | X13: =ModelBear!$F$19*Retentie!$B$13 -> 3.213 | Y13: =ModelBear!$F$19*Retentie!$B$14 -> 3.024 | Z13: =ModelBear!$F$19*Retentie!$B$15 -> 2.898 | AA13: =ModelBear!$F$19*Retentie!$B$16 -> 2.772 | AB13: =ModelBear!$F$19*Retentie!$B$17 -> 2.709 | AC13: =ModelBear!$F$19*Retentie!$B$18 -> 2.646 | AD13: =ModelBear!$F$19*Retentie!$B$19 -> 2.583 | AE13: =ModelBear!$F$19*Retentie!$B$20 -> 2.52 | AF13: =ModelBear!$F$19*Retentie!$B$21 -> 2.457 | AG13: =ModelBear!$F$19*Retentie!$B$22 -> 2.394 | AH13: =ModelBear!$F$19*Retentie!$B$23 -> 2.331 | AI13: =ModelBear!$F$19*Retentie!$B$24 -> 2.268 | AJ13: =ModelBear!$F$19*Retentie!$B$25 -> 2.205 | AK13: =ModelBear!$F$19*Retentie!$B$26 -> 2.142
A14: 13 | N14: =ModelBear!$F$20*Retentie!$B$2 -> 113.4 | O14: =ModelBear!$F$20*Retentie!$B$3 -> 31.752 | P14: =ModelBear!$F$20*Retentie!$B$4 -> 20.412 | Q14: =ModelBear!$F$20*Retentie!$B$5 -> 14.742 | R14: =ModelBear!$F$20*Retentie!$B$6 -> 11.34 | S14: =ModelBear!$F$20*Retentie!$B$7 -> 9.639 | T14: =ModelBear!$F$20*Retentie!$B$8 -> 8.505 | U14: =ModelBear!$F$20*Retentie!$B$9 -> 7.7112 | V14: =ModelBear!$F$20*Retentie!$B$10 -> 7.0308 | W14: =ModelBear!$F$20*Retentie!$B$11 -> 6.5772 | X14: =ModelBear!$F$20*Retentie!$B$12 -> 6.1236 | Y14: =ModelBear!$F$20*Retentie!$B$13 -> 5.7834 | Z14: =ModelBear!$F$20*Retentie!$B$14 -> 5.4432 | AA14: =ModelBear!$F$20*Retentie!$B$15 -> 5.2164 | AB14: =ModelBear!$F$20*Retentie!$B$16 -> 4.9896 | AC14: =ModelBear!$F$20*Retentie!$B$17 -> 4.8762 | AD14: =ModelBear!$F$20*Retentie!$B$18 -> 4.7628 | AE14: =ModelBear!$F$20*Retentie!$B$19 -> 4.6494 | AF14: =ModelBear!$F$20*Retentie!$B$20 -> 4.536 | AG14: =ModelBear!$F$20*Retentie!$B$21 -> 4.4226 | AH14: =ModelBear!$F$20*Retentie!$B$22 -> 4.3092 | AI14: =ModelBear!$F$20*Retentie!$B$23 -> 4.1958 | AJ14: =ModelBear!$F$20*Retentie!$B$24 -> 4.0824 | AK14: =ModelBear!$F$20*Retentie!$B$25 -> 3.969
A15: 14 | O15: =ModelBear!$F$21*Retentie!$B$2 -> 63 | P15: =ModelBear!$F$21*Retentie!$B$3 -> 17.64 | Q15: =ModelBear!$F$21*Retentie!$B$4 -> 11.34 | R15: =ModelBear!$F$21*Retentie!$B$5 -> 8.19 | S15: =ModelBear!$F$21*Retentie!$B$6 -> 6.3 | T15: =ModelBear!$F$21*Retentie!$B$7 -> 5.355 | U15: =ModelBear!$F$21*Retentie!$B$8 -> 4.725 | V15: =ModelBear!$F$21*Retentie!$B$9 -> 4.284 | W15: =ModelBear!$F$21*Retentie!$B$10 -> 3.906 | X15: =ModelBear!$F$21*Retentie!$B$11 -> 3.654 | Y15: =ModelBear!$F$21*Retentie!$B$12 -> 3.402 | Z15: =ModelBear!$F$21*Retentie!$B$13 -> 3.213 | AA15: =ModelBear!$F$21*Retentie!$B$14 -> 3.024 | AB15: =ModelBear!$F$21*Retentie!$B$15 -> 2.898 | AC15: =ModelBear!$F$21*Retentie!$B$16 -> 2.772 | AD15: =ModelBear!$F$21*Retentie!$B$17 -> 2.709 | AE15: =ModelBear!$F$21*Retentie!$B$18 -> 2.646 | AF15: =ModelBear!$F$21*Retentie!$B$19 -> 2.583 | AG15: =ModelBear!$F$21*Retentie!$B$20 -> 2.52 | AH15: =ModelBear!$F$21*Retentie!$B$21 -> 2.457 | AI15: =ModelBear!$F$21*Retentie!$B$22 -> 2.394 | AJ15: =ModelBear!$F$21*Retentie!$B$23 -> 2.331 | AK15: =ModelBear!$F$21*Retentie!$B$24 -> 2.268
A16: 15 | P16: =ModelBear!$F$22*Retentie!$B$2 -> 63 | Q16: =ModelBear!$F$22*Retentie!$B$3 -> 17.64 | R16: =ModelBear!$F$22*Retentie!$B$4 -> 11.34 | S16: =ModelBear!$F$22*Retentie!$B$5 -> 8.19 | T16: =ModelBear!$F$22*Retentie!$B$6 -> 6.3 | U16: =ModelBear!$F$22*Retentie!$B$7 -> 5.355 | V16: =ModelBear!$F$22*Retentie!$B$8 -> 4.725 | W16: =ModelBear!$F$22*Retentie!$B$9 -> 4.284 | X16: =ModelBear!$F$22*Retentie!$B$10 -> 3.906 | Y16: =ModelBear!$F$22*Retentie!$B$11 -> 3.654 | Z16: =ModelBear!$F$22*Retentie!$B$12 -> 3.402 | AA16: =ModelBear!$F$22*Retentie!$B$13 -> 3.213 | AB16: =ModelBear!$F$22*Retentie!$B$14 -> 3.024 | AC16: =ModelBear!$F$22*Retentie!$B$15 -> 2.898 | AD16: =ModelBear!$F$22*Retentie!$B$16 -> 2.772 | AE16: =ModelBear!$F$22*Retentie!$B$17 -> 2.709 | AF16: =ModelBear!$F$22*Retentie!$B$18 -> 2.646 | AG16: =ModelBear!$F$22*Retentie!$B$19 -> 2.583 | AH16: =ModelBear!$F$22*Retentie!$B$20 -> 2.52 | AI16: =ModelBear!$F$22*Retentie!$B$21 -> 2.457 | AJ16: =ModelBear!$F$22*Retentie!$B$22 -> 2.394 | AK16: =ModelBear!$F$22*Retentie!$B$23 -> 2.331
A17: 16 | Q17: =ModelBear!$F$23*Retentie!$B$2 -> 63 | R17: =ModelBear!$F$23*Retentie!$B$3 -> 17.64 | S17: =ModelBear!$F$23*Retentie!$B$4 -> 11.34 | T17: =ModelBear!$F$23*Retentie!$B$5 -> 8.19 | U17: =ModelBear!$F$23*Retentie!$B$6 -> 6.3 | V17: =ModelBear!$F$23*Retentie!$B$7 -> 5.355 | W17: =ModelBear!$F$23*Retentie!$B$8 -> 4.725 | X17: =ModelBear!$F$23*Retentie!$B$9 -> 4.284 | Y17: =ModelBear!$F$23*Retentie!$B$10 -> 3.906 | Z17: =ModelBear!$F$23*Retentie!$B$11 -> 3.654 | AA17: =ModelBear!$F$23*Retentie!$B$12 -> 3.402 | AB17: =ModelBear!$F$23*Retentie!$B$13 -> 3.213 | AC17: =ModelBear!$F$23*Retentie!$B$14 -> 3.024 | AD17: =ModelBear!$F$23*Retentie!$B$15 -> 2.898 | AE17: =ModelBear!$F$23*Retentie!$B$16 -> 2.772 | AF17: =ModelBear!$F$23*Retentie!$B$17 -> 2.709 | AG17: =ModelBear!$F$23*Retentie!$B$18 -> 2.646 | AH17: =ModelBear!$F$23*Retentie!$B$19 -> 2.583 | AI17: =ModelBear!$F$23*Retentie!$B$20 -> 2.52 | AJ17: =ModelBear!$F$23*Retentie!$B$21 -> 2.457 | AK17: =ModelBear!$F$23*Retentie!$B$22 -> 2.394
A18: 17 | R18: =ModelBear!$F$24*Retentie!$B$2 -> 63 | S18: =ModelBear!$F$24*Retentie!$B$3 -> 17.64 | T18: =ModelBear!$F$24*Retentie!$B$4 -> 11.34 | U18: =ModelBear!$F$24*Retentie!$B$5 -> 8.19 | V18: =ModelBear!$F$24*Retentie!$B$6 -> 6.3 | W18: =ModelBear!$F$24*Retentie!$B$7 -> 5.355 | X18: =ModelBear!$F$24*Retentie!$B$8 -> 4.725 | Y18: =ModelBear!$F$24*Retentie!$B$9 -> 4.284 | Z18: =ModelBear!$F$24*Retentie!$B$10 -> 3.906 | AA18: =ModelBear!$F$24*Retentie!$B$11 -> 3.654 | AB18: =ModelBear!$F$24*Retentie!$B$12 -> 3.402 | AC18: =ModelBear!$F$24*Retentie!$B$13 -> 3.213 | AD18: =ModelBear!$F$24*Retentie!$B$14 -> 3.024 | AE18: =ModelBear!$F$24*Retentie!$B$15 -> 2.898 | AF18: =ModelBear!$F$24*Retentie!$B$16 -> 2.772 | AG18: =ModelBear!$F$24*Retentie!$B$17 -> 2.709 | AH18: =ModelBear!$F$24*Retentie!$B$18 -> 2.646 | AI18: =ModelBear!$F$24*Retentie!$B$19 -> 2.583 | AJ18: =ModelBear!$F$24*Retentie!$B$20 -> 2.52 | AK18: =ModelBear!$F$24*Retentie!$B$21 -> 2.457
A19: 18 | S19: =ModelBear!$F$25*Retentie!$B$2 -> 63 | T19: =ModelBear!$F$25*Retentie!$B$3 -> 17.64 | U19: =ModelBear!$F$25*Retentie!$B$4 -> 11.34 | V19: =ModelBear!$F$25*Retentie!$B$5 -> 8.19 | W19: =ModelBear!$F$25*Retentie!$B$6 -> 6.3 | X19: =ModelBear!$F$25*Retentie!$B$7 -> 5.355 | Y19: =ModelBear!$F$25*Retentie!$B$8 -> 4.725 | Z19: =ModelBear!$F$25*Retentie!$B$9 -> 4.284 | AA19: =ModelBear!$F$25*Retentie!$B$10 -> 3.906 | AB19: =ModelBear!$F$25*Retentie!$B$11 -> 3.654 | AC19: =ModelBear!$F$25*Retentie!$B$12 -> 3.402 | AD19: =ModelBear!$F$25*Retentie!$B$13 -> 3.213 | AE19: =ModelBear!$F$25*Retentie!$B$14 -> 3.024 | AF19: =ModelBear!$F$25*Retentie!$B$15 -> 2.898 | AG19: =ModelBear!$F$25*Retentie!$B$16 -> 2.772 | AH19: =ModelBear!$F$25*Retentie!$B$17 -> 2.709 | AI19: =ModelBear!$F$25*Retentie!$B$18 -> 2.646 | AJ19: =ModelBear!$F$25*Retentie!$B$19 -> 2.583 | AK19: =ModelBear!$F$25*Retentie!$B$20 -> 2.52
A20: 19 | T20: =ModelBear!$F$26*Retentie!$B$2 -> 63 | U20: =ModelBear!$F$26*Retentie!$B$3 -> 17.64 | V20: =ModelBear!$F$26*Retentie!$B$4 -> 11.34 | W20: =ModelBear!$F$26*Retentie!$B$5 -> 8.19 | X20: =ModelBear!$F$26*Retentie!$B$6 -> 6.3 | Y20: =ModelBear!$F$26*Retentie!$B$7 -> 5.355 | Z20: =ModelBear!$F$26*Retentie!$B$8 -> 4.725 | AA20: =ModelBear!$F$26*Retentie!$B$9 -> 4.284 | AB20: =ModelBear!$F$26*Retentie!$B$10 -> 3.906 | AC20: =ModelBear!$F$26*Retentie!$B$11 -> 3.654 | AD20: =ModelBear!$F$26*Retentie!$B$12 -> 3.402 | AE20: =ModelBear!$F$26*Retentie!$B$13 -> 3.213 | AF20: =ModelBear!$F$26*Retentie!$B$14 -> 3.024 | AG20: =ModelBear!$F$26*Retentie!$B$15 -> 2.898 | AH20: =ModelBear!$F$26*Retentie!$B$16 -> 2.772 | AI20: =ModelBear!$F$26*Retentie!$B$17 -> 2.709 | AJ20: =ModelBear!$F$26*Retentie!$B$18 -> 2.646 | AK20: =ModelBear!$F$26*Retentie!$B$19 -> 2.583
A21: 20 | U21: =ModelBear!$F$27*Retentie!$B$2 -> 63 | V21: =ModelBear!$F$27*Retentie!$B$3 -> 17.64 | W21: =ModelBear!$F$27*Retentie!$B$4 -> 11.34 | X21: =ModelBear!$F$27*Retentie!$B$5 -> 8.19 | Y21: =ModelBear!$F$27*Retentie!$B$6 -> 6.3 | Z21: =ModelBear!$F$27*Retentie!$B$7 -> 5.355 | AA21: =ModelBear!$F$27*Retentie!$B$8 -> 4.725 | AB21: =ModelBear!$F$27*Retentie!$B$9 -> 4.284 | AC21: =ModelBear!$F$27*Retentie!$B$10 -> 3.906 | AD21: =ModelBear!$F$27*Retentie!$B$11 -> 3.654 | AE21: =ModelBear!$F$27*Retentie!$B$12 -> 3.402 | AF21: =ModelBear!$F$27*Retentie!$B$13 -> 3.213 | AG21: =ModelBear!$F$27*Retentie!$B$14 -> 3.024 | AH21: =ModelBear!$F$27*Retentie!$B$15 -> 2.898 | AI21: =ModelBear!$F$27*Retentie!$B$16 -> 2.772 | AJ21: =ModelBear!$F$27*Retentie!$B$17 -> 2.709 | AK21: =ModelBear!$F$27*Retentie!$B$18 -> 2.646
A22: 21 | V22: =ModelBear!$F$28*Retentie!$B$2 -> 63 | W22: =ModelBear!$F$28*Retentie!$B$3 -> 17.64 | X22: =ModelBear!$F$28*Retentie!$B$4 -> 11.34 | Y22: =ModelBear!$F$28*Retentie!$B$5 -> 8.19 | Z22: =ModelBear!$F$28*Retentie!$B$6 -> 6.3 | AA22: =ModelBear!$F$28*Retentie!$B$7 -> 5.355 | AB22: =ModelBear!$F$28*Retentie!$B$8 -> 4.725 | AC22: =ModelBear!$F$28*Retentie!$B$9 -> 4.284 | AD22: =ModelBear!$F$28*Retentie!$B$10 -> 3.906 | AE22: =ModelBear!$F$28*Retentie!$B$11 -> 3.654 | AF22: =ModelBear!$F$28*Retentie!$B$12 -> 3.402 | AG22: =ModelBear!$F$28*Retentie!$B$13 -> 3.213 | AH22: =ModelBear!$F$28*Retentie!$B$14 -> 3.024 | AI22: =ModelBear!$F$28*Retentie!$B$15 -> 2.898 | AJ22: =ModelBear!$F$28*Retentie!$B$16 -> 2.772 | AK22: =ModelBear!$F$28*Retentie!$B$17 -> 2.709
A23: 22 | W23: =ModelBear!$F$29*Retentie!$B$2 -> 63 | X23: =ModelBear!$F$29*Retentie!$B$3 -> 17.64 | Y23: =ModelBear!$F$29*Retentie!$B$4 -> 11.34 | Z23: =ModelBear!$F$29*Retentie!$B$5 -> 8.19 | AA23: =ModelBear!$F$29*Retentie!$B$6 -> 6.3 | AB23: =ModelBear!$F$29*Retentie!$B$7 -> 5.355 | AC23: =ModelBear!$F$29*Retentie!$B$8 -> 4.725 | AD23: =ModelBear!$F$29*Retentie!$B$9 -> 4.284 | AE23: =ModelBear!$F$29*Retentie!$B$10 -> 3.906 | AF23: =ModelBear!$F$29*Retentie!$B$11 -> 3.654 | AG23: =ModelBear!$F$29*Retentie!$B$12 -> 3.402 | AH23: =ModelBear!$F$29*Retentie!$B$13 -> 3.213 | AI23: =ModelBear!$F$29*Retentie!$B$14 -> 3.024 | AJ23: =ModelBear!$F$29*Retentie!$B$15 -> 2.898 | AK23: =ModelBear!$F$29*Retentie!$B$16 -> 2.772
A24: 23 | X24: =ModelBear!$F$30*Retentie!$B$2 -> 63 | Y24: =ModelBear!$F$30*Retentie!$B$3 -> 17.64 | Z24: =ModelBear!$F$30*Retentie!$B$4 -> 11.34 | AA24: =ModelBear!$F$30*Retentie!$B$5 -> 8.19 | AB24: =ModelBear!$F$30*Retentie!$B$6 -> 6.3 | AC24: =ModelBear!$F$30*Retentie!$B$7 -> 5.355 | AD24: =ModelBear!$F$30*Retentie!$B$8 -> 4.725 | AE24: =ModelBear!$F$30*Retentie!$B$9 -> 4.284 | AF24: =ModelBear!$F$30*Retentie!$B$10 -> 3.906 | AG24: =ModelBear!$F$30*Retentie!$B$11 -> 3.654 | AH24: =ModelBear!$F$30*Retentie!$B$12 -> 3.402 | AI24: =ModelBear!$F$30*Retentie!$B$13 -> 3.213 | AJ24: =ModelBear!$F$30*Retentie!$B$14 -> 3.024 | AK24: =ModelBear!$F$30*Retentie!$B$15 -> 2.898
A25: 24 | Y25: =ModelBear!$F$31*Retentie!$B$2 -> 63 | Z25: =ModelBear!$F$31*Retentie!$B$3 -> 17.64 | AA25: =ModelBear!$F$31*Retentie!$B$4 -> 11.34 | AB25: =ModelBear!$F$31*Retentie!$B$5 -> 8.19 | AC25: =ModelBear!$F$31*Retentie!$B$6 -> 6.3 | AD25: =ModelBear!$F$31*Retentie!$B$7 -> 5.355 | AE25: =ModelBear!$F$31*Retentie!$B$8 -> 4.725 | AF25: =ModelBear!$F$31*Retentie!$B$9 -> 4.284 | AG25: =ModelBear!$F$31*Retentie!$B$10 -> 3.906 | AH25: =ModelBear!$F$31*Retentie!$B$11 -> 3.654 | AI25: =ModelBear!$F$31*Retentie!$B$12 -> 3.402 | AJ25: =ModelBear!$F$31*Retentie!$B$13 -> 3.213 | AK25: =ModelBear!$F$31*Retentie!$B$14 -> 3.024
A26: 25 | Z26: =ModelBear!$F$32*Retentie!$B$2 -> 113.4 | AA26: =ModelBear!$F$32*Retentie!$B$3 -> 31.752 | AB26: =ModelBear!$F$32*Retentie!$B$4 -> 20.412 | AC26: =ModelBear!$F$32*Retentie!$B$5 -> 14.742 | AD26: =ModelBear!$F$32*Retentie!$B$6 -> 11.34 | AE26: =ModelBear!$F$32*Retentie!$B$7 -> 9.639 | AF26: =ModelBear!$F$32*Retentie!$B$8 -> 8.505 | AG26: =ModelBear!$F$32*Retentie!$B$9 -> 7.7112 | AH26: =ModelBear!$F$32*Retentie!$B$10 -> 7.0308 | AI26: =ModelBear!$F$32*Retentie!$B$11 -> 6.5772 | AJ26: =ModelBear!$F$32*Retentie!$B$12 -> 6.1236 | AK26: =ModelBear!$F$32*Retentie!$B$13 -> 5.7834
A27: 26 | AA27: =ModelBear!$F$33*Retentie!$B$2 -> 63 | AB27: =ModelBear!$F$33*Retentie!$B$3 -> 17.64 | AC27: =ModelBear!$F$33*Retentie!$B$4 -> 11.34 | AD27: =ModelBear!$F$33*Retentie!$B$5 -> 8.19 | AE27: =ModelBear!$F$33*Retentie!$B$6 -> 6.3 | AF27: =ModelBear!$F$33*Retentie!$B$7 -> 5.355 | AG27: =ModelBear!$F$33*Retentie!$B$8 -> 4.725 | AH27: =ModelBear!$F$33*Retentie!$B$9 -> 4.284 | AI27: =ModelBear!$F$33*Retentie!$B$10 -> 3.906 | AJ27: =ModelBear!$F$33*Retentie!$B$11 -> 3.654 | AK27: =ModelBear!$F$33*Retentie!$B$12 -> 3.402
A28: 27 | AB28: =ModelBear!$F$34*Retentie!$B$2 -> 63 | AC28: =ModelBear!$F$34*Retentie!$B$3 -> 17.64 | AD28: =ModelBear!$F$34*Retentie!$B$4 -> 11.34 | AE28: =ModelBear!$F$34*Retentie!$B$5 -> 8.19 | AF28: =ModelBear!$F$34*Retentie!$B$6 -> 6.3 | AG28: =ModelBear!$F$34*Retentie!$B$7 -> 5.355 | AH28: =ModelBear!$F$34*Retentie!$B$8 -> 4.725 | AI28: =ModelBear!$F$34*Retentie!$B$9 -> 4.284 | AJ28: =ModelBear!$F$34*Retentie!$B$10 -> 3.906 | AK28: =ModelBear!$F$34*Retentie!$B$11 -> 3.654
A29: 28 | AC29: =ModelBear!$F$35*Retentie!$B$2 -> 63 | AD29: =ModelBear!$F$35*Retentie!$B$3 -> 17.64 | AE29: =ModelBear!$F$35*Retentie!$B$4 -> 11.34 | AF29: =ModelBear!$F$35*Retentie!$B$5 -> 8.19 | AG29: =ModelBear!$F$35*Retentie!$B$6 -> 6.3 | AH29: =ModelBear!$F$35*Retentie!$B$7 -> 5.355 | AI29: =ModelBear!$F$35*Retentie!$B$8 -> 4.725 | AJ29: =ModelBear!$F$35*Retentie!$B$9 -> 4.284 | AK29: =ModelBear!$F$35*Retentie!$B$10 -> 3.906
A30: 29 | AD30: =ModelBear!$F$36*Retentie!$B$2 -> 63 | AE30: =ModelBear!$F$36*Retentie!$B$3 -> 17.64 | AF30: =ModelBear!$F$36*Retentie!$B$4 -> 11.34 | AG30: =ModelBear!$F$36*Retentie!$B$5 -> 8.19 | AH30: =ModelBear!$F$36*Retentie!$B$6 -> 6.3 | AI30: =ModelBear!$F$36*Retentie!$B$7 -> 5.355 | AJ30: =ModelBear!$F$36*Retentie!$B$8 -> 4.725 | AK30: =ModelBear!$F$36*Retentie!$B$9 -> 4.284
A31: 30 | AE31: =ModelBear!$F$37*Retentie!$B$2 -> 63 | AF31: =ModelBear!$F$37*Retentie!$B$3 -> 17.64 | AG31: =ModelBear!$F$37*Retentie!$B$4 -> 11.34 | AH31: =ModelBear!$F$37*Retentie!$B$5 -> 8.19 | AI31: =ModelBear!$F$37*Retentie!$B$6 -> 6.3 | AJ31: =ModelBear!$F$37*Retentie!$B$7 -> 5.355 | AK31: =ModelBear!$F$37*Retentie!$B$8 -> 4.725
A32: 31 | AF32: =ModelBear!$F$38*Retentie!$B$2 -> 63 | AG32: =ModelBear!$F$38*Retentie!$B$3 -> 17.64 | AH32: =ModelBear!$F$38*Retentie!$B$4 -> 11.34 | AI32: =ModelBear!$F$38*Retentie!$B$5 -> 8.19 | AJ32: =ModelBear!$F$38*Retentie!$B$6 -> 6.3 | AK32: =ModelBear!$F$38*Retentie!$B$7 -> 5.355
A33: 32 | AG33: =ModelBear!$F$39*Retentie!$B$2 -> 63 | AH33: =ModelBear!$F$39*Retentie!$B$3 -> 17.64 | AI33: =ModelBear!$F$39*Retentie!$B$4 -> 11.34 | AJ33: =ModelBear!$F$39*Retentie!$B$5 -> 8.19 | AK33: =ModelBear!$F$39*Retentie!$B$6 -> 6.3
A34: 33 | AH34: =ModelBear!$F$40*Retentie!$B$2 -> 63 | AI34: =ModelBear!$F$40*Retentie!$B$3 -> 17.64 | AJ34: =ModelBear!$F$40*Retentie!$B$4 -> 11.34 | AK34: =ModelBear!$F$40*Retentie!$B$5 -> 8.19
A35: 34 | AI35: =ModelBear!$F$41*Retentie!$B$2 -> 63 | AJ35: =ModelBear!$F$41*Retentie!$B$3 -> 17.64 | AK35: =ModelBear!$F$41*Retentie!$B$4 -> 11.34
A36: 35 | AJ36: =ModelBear!$F$42*Retentie!$B$2 -> 63 | AK36: =ModelBear!$F$42*Retentie!$B$3 -> 17.64
A37: 36 | AK37: =ModelBear!$F$43*Retentie!$B$2 -> 63
A38: MAU | B38: =SUM(B2:B37) -> 225 | C38: =SUM(C2:C37) -> 126 | D38: =SUM(D2:D37) -> 121.14 | E38: =SUM(E2:E37) -> 121.23 | F38: =SUM(F2:F37) -> 122.67 | G38: =SUM(G2:G37) -> 125.595 | H38: =SUM(H2:H37) -> 128.7 | I38: =SUM(I2:I37) -> 131.85 | ... AK38: =SUM(AK2:AK37) -> 197.0784

Sheet ModelBasis
A1: ART EYE — scenario BASIS (A$, M1 = sep 2026)
A2: Alle regels zijn formules op blad Aannames + Retentie. Niets hier hard aanpassen.
A7: Mnd | B7: Kalender | C7: Downloads Sydney | D7: Downloads stad 2+ | E7: Downloads totaal | F7: Nieuwe actieven | G7: MAU (cohort) | H7: Premium-abonnees | I7: Consumer-omzet netto | J7: Betalende venues | K7: Venue-MRR | L7: Fair/partnership | M7: Totale omzet | N7: Infra | O7: AI-pipeline | P7: Tools | Q7: Apple | R7: Marketing | S7: Eenmalig | T7: Totale kosten | U7: Netto cashflow | V7: Cumulatief
A8: 1 | B8: sep-26 | C8: =Aannames!$C$4 -> 900 | D8: =IF(A8>=Aannames!$C$24,Aannames!$C$26*(1+Aannames!$C$6)^(A8-Aannames!$C$24),0) -> 0 | E8: =C8+D8 -> 900 | F8: =E8*Aannames!$C$8 -> 495 | G8: =CohortBasis!B$38 -> 495 | H8: =G8*Aannames!$C$9 -> 12.375 | I8: =H8*Aannames!$C$10*(1-Aannames!$C$11) -> 47.229188 | J8: =MIN(IF(A8>=Aannames!$C$14,Aannames!$C$15*Aannames!$C$16,0),(Aannames!$C$19+IF(A8>=Aannames!$C$24,Aannames!$C$25,0))*Aannames!$C$20) -> 0 | K8: =J8*Aannames!$C$17 -> 0 | L8: =IF(AND(A8>12,MOD(A8-1,12)=0),Aannames!$C$37,0) -> 0 | M8: =I8+K8+L8 -> 47.229188 | N8: =Aannames!$C$28+G8*Aannames!$C$29 -> 69.9 | O8: =Aannames!$C$30*(1+IF(A8>=Aannames!$C$24,1,0)) -> 80 | P8: =Aannames!$C$31 -> 70 | Q8: =IF(MOD(A8-1,12)=0,Aannames!$C$32,0) -> 150 | R8: =Aannames!$C$33+IF(MOD(A8-1,12)=0,Aannames!$C$34,0) -> 950 | S8: =IF(A8=1,Aannames!$C$35,0) -> 400 | T8: =SUM(N8:S8) -> 1719.9 | U8: =M8-T8 -> -1672.6708 | V8: =U8 -> -1672.6708
A9: 2 | B9: okt-26 | C9: =Aannames!$C$5*(1+Aannames!$C$6)^(A9-2)*(1+IF(MOD(A9-1,12)=0,Aannames!$C$7,0)) -> 260 | D9: =IF(A9>=Aannames!$C$24,Aannames!$C$26*(1+Aannames!$C$6)^(A9-Aannames!$C$24),0) -> 0 | E9: =C9+D9 -> 260 | F9: =E9*Aannames!$C$8 -> 143 | G9: =CohortBasis!C$38 -> 341 | H9: =G9*Aannames!$C$9 -> 8.525 | I9: =H9*Aannames!$C$10*(1-Aannames!$C$11) -> 32.535663 | J9: =MIN(J8*(1-Aannames!$C$18)+IF(A9>=Aannames!$C$14,Aannames!$C$15*Aannames!$C$16,0),(Aannames!$C$19+IF(A9>=Aannames!$C$24,Aannames!$C$25,0))*Aannames!$C$20) -> 0 | K9: =J9*Aannames!$C$17 -> 0 | L9: =IF(AND(A9>12,MOD(A9-1,12)=0),Aannames!$C$37,0) -> 0 | M9: =I9+K9+L9 -> 32.535663 | N9: =Aannames!$C$28+G9*Aannames!$C$29 -> 66.82 | O9: =Aannames!$C$30*(1+IF(A9>=Aannames!$C$24,1,0)) -> 80 | P9: =Aannames!$C$31 -> 70 | Q9: =IF(MOD(A9-1,12)=0,Aannames!$C$32,0) -> 0 | R9: =Aannames!$C$33+IF(MOD(A9-1,12)=0,Aannames!$C$34,0) -> 150 | S9: =IF(A9=1,Aannames!$C$35,0) -> 0 | T9: =SUM(N9:S9) -> 366.82 | U9: =M9-T9 -> -334.28434 | V9: =V8+U9 -> -2006.9552
A10: 3 | B10: nov-26 | C10: =Aannames!$C$5*(1+Aannames!$C$6)^(A10-2)*(1+IF(MOD(A10-1,12)=0,Aannames!$C$7,0)) -> 270.4 | D10: =IF(A10>=Aannames!$C$24,Aannames!$C$26*(1+Aannames!$C$6)^(A10-Aannames!$C$24),0) -> 0 | E10: =C10+D10 -> 270.4 | F10: =E10*Aannames!$C$8 -> 148.72 | G10: =CohortBasis!D$38 -> 354.42 | H10: =G10*Aannames!$C$9 -> 8.8605 | I10: =H10*Aannames!$C$10*(1-Aannames!$C$11) -> 33.816098 | J10: =MIN(J9*(1-Aannames!$C$18)+IF(A10>=Aannames!$C$14,Aannames!$C$15*Aannames!$C$16,0),(Aannames!$C$19+IF(A10>=Aannames!$C$24,Aannames!$C$25,0))*Aannames!$C$20) -> 0 | K10: =J10*Aannames!$C$17 -> 0 | L10: =IF(AND(A10>12,MOD(A10-1,12)=0),Aannames!$C$37,0) -> 0 | M10: =I10+K10+L10 -> 33.816098 | N10: =Aannames!$C$28+G10*Aannames!$C$29 -> 67.0884 | O10: =Aannames!$C$30*(1+IF(A10>=Aannames!$C$24,1,0)) -> 80 | P10: =Aannames!$C$31 -> 70 | Q10: =IF(MOD(A10-1,12)=0,Aannames!$C$32,0) -> 0 | R10: =Aannames!$C$33+IF(MOD(A10-1,12)=0,Aannames!$C$34,0) -> 150 | S10: =IF(A10=1,Aannames!$C$35,0) -> 0 | T10: =SUM(N10:S10) -> 367.0884 | U10: =M10-T10 -> -333.2723 | V10: =V9+U10 -> -2340.2275
A11: 4 | B11: dec-26 | C11: =Aannames!$C$5*(1+Aannames!$C$6)^(A11-2)*(1+IF(MOD(A11-1,12)=0,Aannames!$C$7,0)) -> 281.216 | D11: =IF(A11>=Aannames!$C$24,Aannames!$C$26*(1+Aannames!$C$6)^(A11-Aannames!$C$24),0) -> 0 | E11: =C11+D11 -> 281.216 | F11: =E11*Aannames!$C$8 -> 154.6688 | G11: =CohortBasis!E$38 -> 375.8568 | H11: =G11*Aannames!$C$9 -> 9.39642 | I11: =H11*Aannames!$C$10*(1-Aannames!$C$11) -> 35.861437 | J11: =MIN(J10*(1-Aannames!$C$18)+IF(A11>=Aannames!$C$14,Aannames!$C$15*Aannames!$C$16,0),(Aannames!$C$19+IF(A11>=Aannames!$C$24,Aannames!$C$25,0))*Aannames!$C$20) -> 0 | K11: =J11*Aannames!$C$17 -> 0 | L11: =IF(AND(A11>12,MOD(A11-1,12)=0),Aannames!$C$37,0) -> 0 | M11: =I11+K11+L11 -> 35.861437 | N11: =Aannames!$C$28+G11*Aannames!$C$29 -> 67.517136 | O11: =Aannames!$C$30*(1+IF(A11>=Aannames!$C$24,1,0)) -> 80 | P11: =Aannames!$C$31 -> 70 | Q11: =IF(MOD(A11-1,12)=0,Aannames!$C$32,0) -> 0 | R11: =Aannames!$C$33+IF(MOD(A11-1,12)=0,Aannames!$C$34,0) -> 150 | S11: =IF(A11=1,Aannames!$C$35,0) -> 0 | T11: =SUM(N11:S11) -> 367.51714 | U11: =M11-T11 -> -331.6557 | V11: =V10+U11 -> -2671.8832
A12: 5 | B12: jan-27 | C12: =Aannames!$C$5*(1+Aannames!$C$6)^(A12-2)*(1+IF(MOD(A12-1,12)=0,Aannames!$C$7,0)) -> 292.46464 | D12: =IF(A12>=Aannames!$C$24,Aannames!$C$26*(1+Aannames!$C$6)^(A12-Aannames!$C$24),0) -> 0 | E12: =C12+D12 -> 292.46464 | F12: =E12*Aannames!$C$8 -> 160.85555 | G12: =CohortBasis!F$38 -> 400.65907 | H12: =G12*Aannames!$C$9 -> 10.016477 | I12: =H12*Aannames!$C$10*(1-Aannames!$C$11) -> 38.227884 | J12: =MIN(J11*(1-Aannames!$C$18)+IF(A12>=Aannames!$C$14,Aannames!$C$15*Aannames!$C$16,0),(Aannames!$C$19+IF(A12>=Aannames!$C$24,Aannames!$C$25,0))*Aannames!$C$20) -> 0 | K12: =J12*Aannames!$C$17 -> 0 | L12: =IF(AND(A12>12,MOD(A12-1,12)=0),Aannames!$C$37,0) -> 0 | M12: =I12+K12+L12 -> 38.227884 | N12: =Aannames!$C$28+G12*Aannames!$C$29 -> 68.013181 | O12: =Aannames!$C$30*(1+IF(A12>=Aannames!$C$24,1,0)) -> 80 | P12: =Aannames!$C$31 -> 70 | Q12: =IF(MOD(A12-1,12)=0,Aannames!$C$32,0) -> 0 | R12: =Aannames!$C$33+IF(MOD(A12-1,12)=0,Aannames!$C$34,0) -> 150 | S12: =IF(A12=1,Aannames!$C$35,0) -> 0 | T12: =SUM(N12:S12) -> 368.01318 | U12: =M12-T12 -> -329.7853 | V12: =V11+U12 -> -3001.6684
A13: 6 | B13: feb-27 | C13: =Aannames!$C$5*(1+Aannames!$C$6)^(A13-2)*(1+IF(MOD(A13-1,12)=0,Aannames!$C$7,0)) -> 304.16323 | D13: =IF(A13>=Aannames!$C$24,Aannames!$C$26*(1+Aannames!$C$6)^(A13-Aannames!$C$24),0) -> 0 | E13: =C13+D13 -> 304.16323 | F13: =E13*Aannames!$C$8 -> 167.28977 | G13: =CohortBasis!G$38 -> 431.42543 | H13: =G13*Aannames!$C$9 -> 10.785636 | I13: =H13*Aannames!$C$10*(1-Aannames!$C$11) -> 41.163379 | J13: =MIN(J12*(1-Aannames!$C$18)+IF(A13>=Aannames!$C$14,Aannames!$C$15*Aannames!$C$16,0),(Aannames!$C$19+IF(A13>=Aannames!$C$24,Aannames!$C$25,0))*Aannames!$C$20) -> 0 | K13: =J13*Aannames!$C$17 -> 0 | L13: =IF(AND(A13>12,MOD(A13-1,12)=0),Aannames!$C$37,0) -> 0 | M13: =I13+K13+L13 -> 41.163379 | N13: =Aannames!$C$28+G13*Aannames!$C$29 -> 68.628509 | O13: =Aannames!$C$30*(1+IF(A13>=Aannames!$C$24,1,0)) -> 80 | P13: =Aannames!$C$31 -> 70 | Q13: =IF(MOD(A13-1,12)=0,Aannames!$C$32,0) -> 0 | R13: =Aannames!$C$33+IF(MOD(A13-1,12)=0,Aannames!$C$34,0) -> 150 | S13: =IF(A13=1,Aannames!$C$35,0) -> 0 | T13: =SUM(N13:S13) -> 368.62851 | U13: =M13-T13 -> -327.46513 | V13: =V12+U13 -> -3329.1336
A14: 7 | B14: mrt-27 | C14: =Aannames!$C$5*(1+Aannames!$C$6)^(A14-2)*(1+IF(MOD(A14-1,12)=0,Aannames!$C$7,0)) -> 316.32975 | D14: =IF(A14>=Aannames!$C$24,Aannames!$C$26*(1+Aannames!$C$6)^(A14-Aannames!$C$24),0) -> 0 | E14: =C14+D14 -> 316.32975 | F14: =E14*Aannames!$C$8 -> 173.98137 | G14: =CohortBasis!H$38 -> 460.95845 | H14: =G14*Aannames!$C$9 -> 11.523961 | I14: =H14*Aannames!$C$10*(1-Aannames!$C$11) -> 43.981198 | J14: =MIN(J13*(1-Aannames!$C$18)+IF(A14>=Aannames!$C$14,Aannames!$C$15*Aannames!$C$16,0),(Aannames!$C$19+IF(A14>=Aannames!$C$24,Aannames!$C$25,0))*Aannames!$C$20) -> 2.4 | K14: =J14*Aannames!$C$17 -> 108 | L14: =IF(AND(A14>12,MOD(A14-1,12)=0),Aannames!$C$37,0) -> 0 | M14: =I14+K14+L14 -> 151.9812 | N14: =Aannames!$C$28+G14*Aannames!$C$29 -> 69.219169 | O14: =Aannames!$C$30*(1+IF(A14>=Aannames!$C$24,1,0)) -> 80 | P14: =Aannames!$C$31 -> 70 | Q14: =IF(MOD(A14-1,12)=0,Aannames!$C$32,0) -> 0 | R14: =Aannames!$C$33+IF(MOD(A14-1,12)=0,Aannames!$C$34,0) -> 150 | S14: =IF(A14=1,Aannames!$C$35,0) -> 0 | T14: =SUM(N14:S14) -> 369.21917 | U14: =M14-T14 -> -217.23797 | V14: =V13+U14 -> -3546.3715
A15: 8 | B15: apr-27 | C15: =Aannames!$C$5*(1+Aannames!$C$6)^(A15-2)*(1+IF(MOD(A15-1,12)=0,Aannames!$C$7,0)) -> 328.98294 | D15: =IF(A15>=Aannames!$C$24,Aannames!$C$26*(1+Aannames!$C$6)^(A15-Aannames!$C$24),0) -> 0 | E15: =C15+D15 -> 328.98294 | F15: =E15*Aannames!$C$8 -> 180.94062 | G15: =CohortBasis!I$38 -> 494.15879 | H15: =G15*Aannames!$C$9 -> 12.35397 | I15: =H15*Aannames!$C$10*(1-Aannames!$C$11) -> 47.148926 | J15: =MIN(J14*(1-Aannames!$C$18)+IF(A15>=Aannames!$C$14,Aannames!$C$15*Aannames!$C$16,0),(Aannames!$C$19+IF(A15>=Aannames!$C$24,Aannames!$C$25,0))*Aannames!$C$20) -> 4.74 | K15: =J15*Aannames!$C$17 -> 213.3 | L15: =IF(AND(A15>12,MOD(A15-1,12)=0),Aannames!$C$37,0) -> 0 | M15: =I15+K15+L15 -> 260.44893 | N15: =Aannames!$C$28+G15*Aannames!$C$29 -> 69.883176 | O15: =Aannames!$C$30*(1+IF(A15>=Aannames!$C$24,1,0)) -> 80 | P15: =Aannames!$C$31 -> 70 | Q15: =IF(MOD(A15-1,12)=0,Aannames!$C$32,0) -> 0 | R15: =Aannames!$C$33+IF(MOD(A15-1,12)=0,Aannames!$C$34,0) -> 150 | S15: =IF(A15=1,Aannames!$C$35,0) -> 0 | T15: =SUM(N15:S15) -> 369.88318 | U15: =M15-T15 -> -109.43425 | V15: =V14+U15 -> -3655.8058
A16: 9 | B16: mei-27 | C16: =Aannames!$C$5*(1+Aannames!$C$6)^(A16-2)*(1+IF(MOD(A16-1,12)=0,Aannames!$C$7,0)) -> 342.14226 | D16: =IF(A16>=Aannames!$C$24,Aannames!$C$26*(1+Aannames!$C$6)^(A16-Aannames!$C$24),0) -> 0 | E16: =C16+D16 -> 342.14226 | F16: =E16*Aannames!$C$8 -> 188.17824 | G16: =CohortBasis!J$38 -> 527.45514 | H16: =G16*Aannames!$C$9 -> 13.186379 | I16: =H16*Aannames!$C$10*(1-Aannames!$C$11) -> 50.325814 | J16: =MIN(J15*(1-Aannames!$C$18)+IF(A16>=Aannames!$C$14,Aannames!$C$15*Aannames!$C$16,0),(Aannames!$C$19+IF(A16>=Aannames!$C$24,Aannames!$C$25,0))*Aannames!$C$20) -> 7.0215 | K16: =J16*Aannames!$C$17 -> 315.9675 | L16: =IF(AND(A16>12,MOD(A16-1,12)=0),Aannames!$C$37,0) -> 0 | M16: =I16+K16+L16 -> 366.29331 | N16: =Aannames!$C$28+G16*Aannames!$C$29 -> 70.549103 | O16: =Aannames!$C$30*(1+IF(A16>=Aannames!$C$24,1,0)) -> 80 | P16: =Aannames!$C$31 -> 70 | Q16: =IF(MOD(A16-1,12)=0,Aannames!$C$32,0) -> 0 | R16: =Aannames!$C$33+IF(MOD(A16-1,12)=0,Aannames!$C$34,0) -> 150 | S16: =IF(A16=1,Aannames!$C$35,0) -> 0 | T16: =SUM(N16:S16) -> 370.5491 | U16: =M16-T16 -> -4.2557891 | V16: =V15+U16 -> -3660.0616
A17: 10 | B17: jun-27 | C17: =Aannames!$C$5*(1+Aannames!$C$6)^(A17-2)*(1+IF(MOD(A17-1,12)=0,Aannames!$C$7,0)) -> 355.82795 | D17: =IF(A17>=Aannames!$C$24,Aannames!$C$26*(1+Aannames!$C$6)^(A17-Aannames!$C$24),0) -> 0 | E17: =C17+D17 -> 355.82795 | F17: =E17*Aannames!$C$8 -> 195.70537 | G17: =CohortBasis!K$38 -> 560.85135 | H17: =G17*Aannames!$C$9 -> 14.021284 | I17: =H17*Aannames!$C$10*(1-Aannames!$C$11) -> 53.512229 | J17: =MIN(J16*(1-Aannames!$C$18)+IF(A17>=Aannames!$C$14,Aannames!$C$15*Aannames!$C$16,0),(Aannames!$C$19+IF(A17>=Aannames!$C$24,Aannames!$C$25,0))*Aannames!$C$20) -> 9.2459625 | K17: =J17*Aannames!$C$17 -> 416.06831 | L17: =IF(AND(A17>12,MOD(A17-1,12)=0),Aannames!$C$37,0) -> 0 | M17: =I17+K17+L17 -> 469.58054 | N17: =Aannames!$C$28+G17*Aannames!$C$29 -> 71.217027 | O17: =Aannames!$C$30*(1+IF(A17>=Aannames!$C$24,1,0)) -> 80 | P17: =Aannames!$C$31 -> 70 | Q17: =IF(MOD(A17-1,12)=0,Aannames!$C$32,0) -> 0 | R17: =Aannames!$C$33+IF(MOD(A17-1,12)=0,Aannames!$C$34,0) -> 150 | S17: =IF(A17=1,Aannames!$C$35,0) -> 0 | T17: =SUM(N17:S17) -> 371.21703 | U17: =M17-T17 -> 98.363515 | V17: =V16+U17 -> -3561.6981
A18: 11 | B18: jul-27 | C18: =Aannames!$C$5*(1+Aannames!$C$6)^(A18-2)*(1+IF(MOD(A18-1,12)=0,Aannames!$C$7,0)) -> 370.06107 | D18: =IF(A18>=Aannames!$C$24,Aannames!$C$26*(1+Aannames!$C$6)^(A18-Aannames!$C$24),0) -> 0 | E18: =C18+D18 -> 370.06107 | F18: =E18*Aannames!$C$8 -> 203.53359 | G18: =CohortBasis!L$38 -> 594.3514 | H18: =G18*Aannames!$C$9 -> 14.858785 | I18: =H18*Aannames!$C$10*(1-Aannames!$C$11) -> 56.708553 | J18: =MIN(J17*(1-Aannames!$C$18)+IF(A18>=Aannames!$C$14,Aannames!$C$15*Aannames!$C$16,0),(Aannames!$C$19+IF(A18>=Aannames!$C$24,Aannames!$C$25,0))*Aannames!$C$20) -> 11.414813 | K18: =J18*Aannames!$C$17 -> 513.6666 | L18: =IF(AND(A18>12,MOD(A18-1,12)=0),Aannames!$C$37,0) -> 0 | M18: =I18+K18+L18 -> 570.37516 | N18: =Aannames!$C$28+G18*Aannames!$C$29 -> 71.887028 | O18: =Aannames!$C$30*(1+IF(A18>=Aannames!$C$24,1,0)) -> 80 | P18: =Aannames!$C$31 -> 70 | Q18: =IF(MOD(A18-1,12)=0,Aannames!$C$32,0) -> 0 | R18: =Aannames!$C$33+IF(MOD(A18-1,12)=0,Aannames!$C$34,0) -> 150 | S18: =IF(A18=1,Aannames!$C$35,0) -> 0 | T18: =SUM(N18:S18) -> 371.88703 | U18: =M18-T18 -> 198.48813 | V18: =V17+U18 -> -3363.2099
A19: 12 | B19: aug-27 | C19: =Aannames!$C$5*(1+Aannames!$C$6)^(A19-2)*(1+IF(MOD(A19-1,12)=0,Aannames!$C$7,0)) -> 384.86351 | D19: =IF(A19>=Aannames!$C$24,Aannames!$C$26*(1+Aannames!$C$6)^(A19-Aannames!$C$24),0) -> 0 | E19: =C19+D19 -> 384.86351 | F19: =E19*Aannames!$C$8 -> 211.67493 | G19: =CohortBasis!M$38 -> 630.43446 | H19: =G19*Aannames!$C$9 -> 15.760861 | I19: =H19*Aannames!$C$10*(1-Aannames!$C$11) -> 60.151328 | J19: =MIN(J18*(1-Aannames!$C$18)+IF(A19>=Aannames!$C$14,Aannames!$C$15*Aannames!$C$16,0),(Aannames!$C$19+IF(A19>=Aannames!$C$24,Aannames!$C$25,0))*Aannames!$C$20) -> 13.529443 | K19: =J19*Aannames!$C$17 -> 608.82494 | L19: =IF(AND(A19>12,MOD(A19-1,12)=0),Aannames!$C$37,0) -> 0 | M19: =I19+K19+L19 -> 668.97627 | N19: =Aannames!$C$28+G19*Aannames!$C$29 -> 72.608689 | O19: =Aannames!$C$30*(1+IF(A19>=Aannames!$C$24,1,0)) -> 80 | P19: =Aannames!$C$31 -> 70 | Q19: =IF(MOD(A19-1,12)=0,Aannames!$C$32,0) -> 0 | R19: =Aannames!$C$33+IF(MOD(A19-1,12)=0,Aannames!$C$34,0) -> 150 | S19: =IF(A19=1,Aannames!$C$35,0) -> 0 | T19: =SUM(N19:S19) -> 372.60869 | U19: =M19-T19 -> 296.36758 | V19: =V18+U19 -> -3066.8424
A20: 13 | B20: sep-27 | C20: =Aannames!$C$5*(1+Aannames!$C$6)^(A20-2)*(1+IF(MOD(A20-1,12)=0,Aannames!$C$7,0)) -> 1000.6451 | D20: =IF(A20>=Aannames!$C$24,Aannames!$C$26*(1+Aannames!$C$6)^(A20-Aannames!$C$24),0) -> 0 | E20: =C20+D20 -> 1000.6451 | F20: =E20*Aannames!$C$8 -> 550.35483 | G20: =CohortBasis!N$38 -> 997.55773 | H20: =G20*Aannames!$C$9 -> 24.938943 | I20: =H20*Aannames!$C$10*(1-Aannames!$C$11) -> 95.179477 | J20: =MIN(J19*(1-Aannames!$C$18)+IF(A20>=Aannames!$C$14,Aannames!$C$15*Aannames!$C$16,0),(Aannames!$C$19+IF(A20>=Aannames!$C$24,Aannames!$C$25,0))*Aannames!$C$20) -> 15.591207 | K20: =J20*Aannames!$C$17 -> 701.60432 | L20: =IF(AND(A20>12,MOD(A20-1,12)=0),Aannames!$C$37,0) -> 5000 | M20: =I20+K20+L20 -> 5796.7838 | N20: =Aannames!$C$28+G20*Aannames!$C$29 -> 79.951155 | O20: =Aannames!$C$30*(1+IF(A20>=Aannames!$C$24,1,0)) -> 80 | P20: =Aannames!$C$31 -> 70 | Q20: =IF(MOD(A20-1,12)=0,Aannames!$C$32,0) -> 150 | R20: =Aannames!$C$33+IF(MOD(A20-1,12)=0,Aannames!$C$34,0) -> 950 | S20: =IF(A20=1,Aannames!$C$35,0) -> 0 | T20: =SUM(N20:S20) -> 1329.9512 | U20: =M20-T20 -> 4466.8326 | V20: =V19+U20 -> 1399.9903
A21: 14 | B21: okt-27 | C21: =Aannames!$C$5*(1+Aannames!$C$6)^(A21-2)*(1+IF(MOD(A21-1,12)=0,Aannames!$C$7,0)) -> 416.26838 | D21: =IF(A21>=Aannames!$C$24,Aannames!$C$26*(1+Aannames!$C$6)^(A21-Aannames!$C$24),0) -> 0 | E21: =C21+D21 -> 416.26838 | F21: =E21*Aannames!$C$8 -> 228.94761 | G21: =CohortBasis!O$38 -> 838.68579 | H21: =G21*Aannames!$C$9 -> 20.967145 | I21: =H21*Aannames!$C$10*(1-Aannames!$C$11) -> 80.021108 | J21: =MIN(J20*(1-Aannames!$C$18)+IF(A21>=Aannames!$C$14,Aannames!$C$15*Aannames!$C$16,0),(Aannames!$C$19+IF(A21>=Aannames!$C$24,Aannames!$C$25,0))*Aannames!$C$20) -> 17.601427 | K21: =J21*Aannames!$C$17 -> 792.06421 | L21: =IF(AND(A21>12,MOD(A21-1,12)=0),Aannames!$C$37,0) -> 0 | M21: =I21+K21+L21 -> 872.08532 | N21: =Aannames!$C$28+G21*Aannames!$C$29 -> 76.773716 | O21: =Aannames!$C$30*(1+IF(A21>=Aannames!$C$24,1,0)) -> 80 | P21: =Aannames!$C$31 -> 70 | Q21: =IF(MOD(A21-1,12)=0,Aannames!$C$32,0) -> 0 | R21: =Aannames!$C$33+IF(MOD(A21-1,12)=0,Aannames!$C$34,0) -> 150 | S21: =IF(A21=1,Aannames!$C$35,0) -> 0 | T21: =SUM(N21:S21) -> 376.77372 | U21: =M21-T21 -> 495.3116 | V21: =V20+U21 -> 1895.3019
A22: 15 | B22: nov-27 | C22: =Aannames!$C$5*(1+Aannames!$C$6)^(A22-2)*(1+IF(MOD(A22-1,12)=0,Aannames!$C$7,0)) -> 432.91911 | D22: =IF(A22>=Aannames!$C$24,Aannames!$C$26*(1+Aannames!$C$6)^(A22-Aannames!$C$24),0) -> 0 | E22: =C22+D22 -> 432.91911 | F22: =E22*Aannames!$C$8 -> 238.10551 | G22: =CohortBasis!P$38 -> 846.24412 | H22: =G22*Aannames!$C$9 -> 21.156103 | I22: =H22*Aannames!$C$10*(1-Aannames!$C$11) -> 80.742267 | J22: =MIN(J21*(1-Aannames!$C$18)+IF(A22>=Aannames!$C$14,Aannames!$C$15*Aannames!$C$16,0),(Aannames!$C$19+IF(A22>=Aannames!$C$24,Aannames!$C$25,0))*Aannames!$C$20) -> 19.561391 | K22: =J22*Aannames!$C$17 -> 880.2626 | L22: =IF(AND(A22>12,MOD(A22-1,12)=0),Aannames!$C$37,0) -> 0 | M22: =I22+K22+L22 -> 961.00487 | N22: =Aannames!$C$28+G22*Aannames!$C$29 -> 76.924882 | O22: =Aannames!$C$30*(1+IF(A22>=Aannames!$C$24,1,0)) -> 80 | P22: =Aannames!$C$31 -> 70 | Q22: =IF(MOD(A22-1,12)=0,Aannames!$C$32,0) -> 0 | R22: =Aannames!$C$33+IF(MOD(A22-1,12)=0,Aannames!$C$34,0) -> 150 | S22: =IF(A22=1,Aannames!$C$35,0) -> 0 | T22: =SUM(N22:S22) -> 376.92488 | U22: =M22-T22 -> 584.07999 | V22: =V21+U22 -> 2479.3819
A23: 16 | B23: dec-27 | C23: =Aannames!$C$5*(1+Aannames!$C$6)^(A23-2)*(1+IF(MOD(A23-1,12)=0,Aannames!$C$7,0)) -> 450.23588 | D23: =IF(A23>=Aannames!$C$24,Aannames!$C$26*(1+Aannames!$C$6)^(A23-Aannames!$C$24),0) -> 0 | E23: =C23+D23 -> 450.23588 | F23: =E23*Aannames!$C$8 -> 247.62973 | G23: =CohortBasis!Q$38 -> 868.38776 | H23: =G23*Aannames!$C$9 -> 21.709694 | I23: =H23*Aannames!$C$10*(1-Aannames!$C$11) -> 82.855047 | J23: =MIN(J22*(1-Aannames!$C$18)+IF(A23>=Aannames!$C$14,Aannames!$C$15*Aannames!$C$16,0),(Aannames!$C$19+IF(A23>=Aannames!$C$24,Aannames!$C$25,0))*Aannames!$C$20) -> 21.472356 | K23: =J23*Aannames!$C$17 -> 966.25604 | L23: =IF(AND(A23>12,MOD(A23-1,12)=0),Aannames!$C$37,0) -> 0 | M23: =I23+K23+L23 -> 1049.1111 | N23: =Aannames!$C$28+G23*Aannames!$C$29 -> 77.367755 | O23: =Aannames!$C$30*(1+IF(A23>=Aannames!$C$24,1,0)) -> 80 | P23: =Aannames!$C$31 -> 70 | Q23: =IF(MOD(A23-1,12)=0,Aannames!$C$32,0) -> 0 | R23: =Aannames!$C$33+IF(MOD(A23-1,12)=0,Aannames!$C$34,0) -> 150 | S23: =IF(A23=1,Aannames!$C$35,0) -> 0 | T23: =SUM(N23:S23) -> 377.36776 | U23: =M23-T23 -> 671.74333 | V23: =V22+U23 -> 3151.1252
A24: 17 | B24: jan-28 | C24: =Aannames!$C$5*(1+Aannames!$C$6)^(A24-2)*(1+IF(MOD(A24-1,12)=0,Aannames!$C$7,0)) -> 468.24531 | D24: =IF(A24>=Aannames!$C$24,Aannames!$C$26*(1+Aannames!$C$6)^(A24-Aannames!$C$24),0) -> 0 | E24: =C24+D24 -> 468.24531 | F24: =E24*Aannames!$C$8 -> 257.53492 | G24: =CohortBasis!R$38 -> 898.56751 | H24: =G24*Aannames!$C$9 -> 22.464188 | I24: =H24*Aannames!$C$10*(1-Aannames!$C$11) -> 85.734573 | J24: =MIN(J23*(1-Aannames!$C$18)+IF(A24>=Aannames!$C$14,Aannames!$C$15*Aannames!$C$16,0),(Aannames!$C$19+IF(A24>=Aannames!$C$24,Aannames!$C$25,0))*Aannames!$C$20) -> 23.335547 | K24: =J24*Aannames!$C$17 -> 1050.0996 | L24: =IF(AND(A24>12,MOD(A24-1,12)=0),Aannames!$C$37,0) -> 0 | M24: =I24+K24+L24 -> 1135.8342 | N24: =Aannames!$C$28+G24*Aannames!$C$29 -> 77.97135 | O24: =Aannames!$C$30*(1+IF(A24>=Aannames!$C$24,1,0)) -> 80 | P24: =Aannames!$C$31 -> 70 | Q24: =IF(MOD(A24-1,12)=0,Aannames!$C$32,0) -> 0 | R24: =Aannames!$C$33+IF(MOD(A24-1,12)=0,Aannames!$C$34,0) -> 150 | S24: =IF(A24=1,Aannames!$C$35,0) -> 0 | T24: =SUM(N24:S24) -> 377.97135 | U24: =M24-T24 -> 757.86286 | V24: =V23+U24 -> 3908.9881
A25: 18 | B25: feb-28 | C25: =Aannames!$C$5*(1+Aannames!$C$6)^(A25-2)*(1+IF(MOD(A25-1,12)=0,Aannames!$C$7,0)) -> 486.97512 | D25: =IF(A25>=Aannames!$C$24,Aannames!$C$26*(1+Aannames!$C$6)^(A25-Aannames!$C$24),0) -> 300 | E25: =C25+D25 -> 786.97512 | F25: =E25*Aannames!$C$8 -> 432.83632 | G25: =CohortBasis!S$38 -> 1101.8406 | H25: =G25*Aannames!$C$9 -> 27.546016 | I25: =H25*Aannames!$C$10*(1-Aannames!$C$11) -> 105.12937 | J25: =MIN(J24*(1-Aannames!$C$18)+IF(A25>=Aannames!$C$14,Aannames!$C$15*Aannames!$C$16,0),(Aannames!$C$19+IF(A25>=Aannames!$C$24,Aannames!$C$25,0))*Aannames!$C$20) -> 25.152159 | K25: =J25*Aannames!$C$17 -> 1131.8471 | L25: =IF(AND(A25>12,MOD(A25-1,12)=0),Aannames!$C$37,0) -> 0 | M25: =I25+K25+L25 -> 1236.9765 | N25: =Aannames!$C$28+G25*Aannames!$C$29 -> 82.036813 | O25: =Aannames!$C$30*(1+IF(A25>=Aannames!$C$24,1,0)) -> 160 | P25: =Aannames!$C$31 -> 70 | Q25: =IF(MOD(A25-1,12)=0,Aannames!$C$32,0) -> 0 | R25: =Aannames!$C$33+IF(MOD(A25-1,12)=0,Aannames!$C$34,0) -> 150 | S25: =IF(A25=1,Aannames!$C$35,0) -> 0 | T25: =SUM(N25:S25) -> 462.03681 | U25: =M25-T25 -> 774.9397 | V25: =V24+U25 -> 4683.9278
A26: 19 | B26: mrt-28 | C26: =Aannames!$C$5*(1+Aannames!$C$6)^(A26-2)*(1+IF(MOD(A26-1,12)=0,Aannames!$C$7,0)) -> 506.45413 | D26: =IF(A26>=Aannames!$C$24,Aannames!$C$26*(1+Aannames!$C$6)^(A26-Aannames!$C$24),0) -> 312 | E26: =C26+D26 -> 818.45413 | F26: =E26*Aannames!$C$8 -> 450.14977 | G26: =CohortBasis!T$38 -> 1214.2625 | H26: =G26*Aannames!$C$9 -> 30.356562 | I26: =H26*Aannames!$C$10*(1-Aannames!$C$11) -> 115.85582 | J26: =MIN(J25*(1-Aannames!$C$18)+IF(A26>=Aannames!$C$14,Aannames!$C$15*Aannames!$C$16,0),(Aannames!$C$19+IF(A26>=Aannames!$C$24,Aannames!$C$25,0))*Aannames!$C$20) -> 26.923355 | K26: =J26*Aannames!$C$17 -> 1211.551 | L26: =IF(AND(A26>12,MOD(A26-1,12)=0),Aannames!$C$37,0) -> 0 | M26: =I26+K26+L26 -> 1327.4068 | N26: =Aannames!$C$28+G26*Aannames!$C$29 -> 84.28525 | O26: =Aannames!$C$30*(1+IF(A26>=Aannames!$C$24,1,0)) -> 160 | P26: =Aannames!$C$31 -> 70 | Q26: =IF(MOD(A26-1,12)=0,Aannames!$C$32,0) -> 0 | R26: =Aannames!$C$33+IF(MOD(A26-1,12)=0,Aannames!$C$34,0) -> 150 | S26: =IF(A26=1,Aannames!$C$35,0) -> 0 | T26: =SUM(N26:S26) -> 464.28525 | U26: =M26-T26 -> 863.12154 | V26: =V25+U26 -> 5547.0493
A27: 20 | B27: apr-28 | C27: =Aannames!$C$5*(1+Aannames!$C$6)^(A27-2)*(1+IF(MOD(A27-1,12)=0,Aannames!$C$7,0)) -> 526.71229 | D27: =IF(A27>=Aannames!$C$24,Aannames!$C$26*(1+Aannames!$C$6)^(A27-Aannames!$C$24),0) -> 324.48 | E27: =C27+D27 -> 851.19229 | F27: =E27*Aannames!$C$8 -> 468.15576 | G27: =CohortBasis!U$38 -> 1318.4961 | H27: =G27*Aannames!$C$9 -> 32.962402 | I27: =H27*Aannames!$C$10*(1-Aannames!$C$11) -> 125.80101 | J27: =MIN(J26*(1-Aannames!$C$18)+IF(A27>=Aannames!$C$14,Aannames!$C$15*Aannames!$C$16,0),(Aannames!$C$19+IF(A27>=Aannames!$C$24,Aannames!$C$25,0))*Aannames!$C$20) -> 28.650271 | K27: =J27*Aannames!$C$17 -> 1289.2622 | L27: =IF(AND(A27>12,MOD(A27-1,12)=0),Aannames!$C$37,0) -> 0 | M27: =I27+K27+L27 -> 1415.0632 | N27: =Aannames!$C$28+G27*Aannames!$C$29 -> 86.369922 | O27: =Aannames!$C$30*(1+IF(A27>=Aannames!$C$24,1,0)) -> 160 | P27: =Aannames!$C$31 -> 70 | Q27: =IF(MOD(A27-1,12)=0,Aannames!$C$32,0) -> 0 | R27: =Aannames!$C$33+IF(MOD(A27-1,12)=0,Aannames!$C$34,0) -> 150 | S27: =IF(A27=1,Aannames!$C$35,0) -> 0 | T27: =SUM(N27:S27) -> 466.36992 | U27: =M27-T27 -> 948.69328 | V27: =V26+U27 -> 6495.7426
A28: 21 | B28: mei-28 | C28: =Aannames!$C$5*(1+Aannames!$C$6)^(A28-2)*(1+IF(MOD(A28-1,12)=0,Aannames!$C$7,0)) -> 547.78079 | D28: =IF(A28>=Aannames!$C$24,Aannames!$C$26*(1+Aannames!$C$6)^(A28-Aannames!$C$24),0) -> 337.4592 | E28: =C28+D28 -> 885.23999 | F28: =E28*Aannames!$C$8 -> 486.88199 | G28: =CohortBasis!V$38 -> 1417.0079 | H28: =G28*Aannames!$C$9 -> 35.425198 | I28: =H28*Aannames!$C$10*(1-Aannames!$C$11) -> 135.20027 | J28: =MIN(J27*(1-Aannames!$C$18)+IF(A28>=Aannames!$C$14,Aannames!$C$15*Aannames!$C$16,0),(Aannames!$C$19+IF(A28>=Aannames!$C$24,Aannames!$C$25,0))*Aannames!$C$20) -> 30.334014 | K28: =J28*Aannames!$C$17 -> 1365.0306 | L28: =IF(AND(A28>12,MOD(A28-1,12)=0),Aannames!$C$37,0) -> 0 | M28: =I28+K28+L28 -> 1500.2309 | N28: =Aannames!$C$28+G28*Aannames!$C$29 -> 88.340159 | O28: =Aannames!$C$30*(1+IF(A28>=Aannames!$C$24,1,0)) -> 160 | P28: =Aannames!$C$31 -> 70 | Q28: =IF(MOD(A28-1,12)=0,Aannames!$C$32,0) -> 0 | R28: =Aannames!$C$33+IF(MOD(A28-1,12)=0,Aannames!$C$34,0) -> 150 | S28: =IF(A28=1,Aannames!$C$35,0) -> 0 | T28: =SUM(N28:S28) -> 468.34016 | U28: =M28-T28 -> 1031.8907 | V28: =V27+U28 -> 7527.6333
A29: 22 | B29: jun-28 | C29: =Aannames!$C$5*(1+Aannames!$C$6)^(A29-2)*(1+IF(MOD(A29-1,12)=0,Aannames!$C$7,0)) -> 569.69202 | D29: =IF(A29>=Aannames!$C$24,Aannames!$C$26*(1+Aannames!$C$6)^(A29-Aannames!$C$24),0) -> 350.95757 | E29: =C29+D29 -> 920.64959 | F29: =E29*Aannames!$C$8 -> 506.35727 | G29: =CohortBasis!W$38 -> 1512.8691 | H29: =G29*Aannames!$C$9 -> 37.821728 | I29: =H29*Aannames!$C$10*(1-Aannames!$C$11) -> 144.34663 | J29: =MIN(J28*(1-Aannames!$C$18)+IF(A29>=Aannames!$C$14,Aannames!$C$15*Aannames!$C$16,0),(Aannames!$C$19+IF(A29>=Aannames!$C$24,Aannames!$C$25,0))*Aannames!$C$20) -> 31.975664 | K29: =J29*Aannames!$C$17 -> 1438.9049 | L29: =IF(AND(A29>12,MOD(A29-1,12)=0),Aannames!$C$37,0) -> 0 | M29: =I29+K29+L29 -> 1583.2515 | N29: =Aannames!$C$28+G29*Aannames!$C$29 -> 90.257383 | O29: =Aannames!$C$30*(1+IF(A29>=Aannames!$C$24,1,0)) -> 160 | P29: =Aannames!$C$31 -> 70 | Q29: =IF(MOD(A29-1,12)=0,Aannames!$C$32,0) -> 0 | R29: =Aannames!$C$33+IF(MOD(A29-1,12)=0,Aannames!$C$34,0) -> 150 | S29: =IF(A29=1,Aannames!$C$35,0) -> 0 | T29: =SUM(N29:S29) -> 470.25738 | U29: =M29-T29 -> 1112.9941 | V29: =V28+U29 -> 8640.6274
A30: 23 | B30: jul-28 | C30: =Aannames!$C$5*(1+Aannames!$C$6)^(A30-2)*(1+IF(MOD(A30-1,12)=0,Aannames!$C$7,0)) -> 592.4797 | D30: =IF(A30>=Aannames!$C$24,Aannames!$C$26*(1+Aannames!$C$6)^(A30-Aannames!$C$24),0) -> 364.99587 | E30: =C30+D30 -> 957.47557 | F30: =E30*Aannames!$C$8 -> 526.61156 | G30: =CohortBasis!X$38 -> 1609.2737 | H30: =G30*Aannames!$C$9 -> 40.231841 | I30: =H30*Aannames!$C$10*(1-Aannames!$C$11) -> 153.54482 | J30: =MIN(J29*(1-Aannames!$C$18)+IF(A30>=Aannames!$C$14,Aannames!$C$15*Aannames!$C$16,0),(Aannames!$C$19+IF(A30>=Aannames!$C$24,Aannames!$C$25,0))*Aannames!$C$20) -> 33.576272 | K30: =J30*Aannames!$C$17 -> 1510.9323 | L30: =IF(AND(A30>12,MOD(A30-1,12)=0),Aannames!$C$37,0) -> 0 | M30: =I30+K30+L30 -> 1664.4771 | N30: =Aannames!$C$28+G30*Aannames!$C$29 -> 92.185473 | O30: =Aannames!$C$30*(1+IF(A30>=Aannames!$C$24,1,0)) -> 160 | P30: =Aannames!$C$31 -> 70 | Q30: =IF(MOD(A30-1,12)=0,Aannames!$C$32,0) -> 0 | R30: =Aannames!$C$33+IF(MOD(A30-1,12)=0,Aannames!$C$34,0) -> 150 | S30: =IF(A30=1,Aannames!$C$35,0) -> 0 | T30: =SUM(N30:S30) -> 472.18547 | U30: =M30-T30 -> 1192.2916 | V30: =V29+U30 -> 9832.919
A31: 24 | B31: aug-28 | C31: =Aannames!$C$5*(1+Aannames!$C$6)^(A31-2)*(1+IF(MOD(A31-1,12)=0,Aannames!$C$7,0)) -> 616.17889 | D31: =IF(A31>=Aannames!$C$24,Aannames!$C$26*(1+Aannames!$C$6)^(A31-Aannames!$C$24),0) -> 379.59571 | E31: =C31+D31 -> 995.77459 | F31: =E31*Aannames!$C$8 -> 547.67603 | G31: =CohortBasis!Y$38 -> 1707.8943 | H31: =G31*Aannames!$C$9 -> 42.697358 | I31: =H31*Aannames!$C$10*(1-Aannames!$C$11) -> 162.95447 | J31: =MIN(J30*(1-Aannames!$C$18)+IF(A31>=Aannames!$C$14,Aannames!$C$15*Aannames!$C$16,0),(Aannames!$C$19+IF(A31>=Aannames!$C$24,Aannames!$C$25,0))*Aannames!$C$20) -> 35.136865 | K31: =J31*Aannames!$C$17 -> 1581.1589 | L31: =IF(AND(A31>12,MOD(A31-1,12)=0),Aannames!$C$37,0) -> 0 | M31: =I31+K31+L31 -> 1744.1134 | N31: =Aannames!$C$28+G31*Aannames!$C$29 -> 94.157886 | O31: =Aannames!$C$30*(1+IF(A31>=Aannames!$C$24,1,0)) -> 160 | P31: =Aannames!$C$31 -> 70 | Q31: =IF(MOD(A31-1,12)=0,Aannames!$C$32,0) -> 0 | R31: =Aannames!$C$33+IF(MOD(A31-1,12)=0,Aannames!$C$34,0) -> 150 | S31: =IF(A31=1,Aannames!$C$35,0) -> 0 | T31: =SUM(N31:S31) -> 474.15789 | U31: =M31-T31 -> 1269.9555 | V31: =V30+U31 -> 11102.875
A32: 25 | B32: sep-28 | C32: =Aannames!$C$5*(1+Aannames!$C$6)^(A32-2)*(1+IF(MOD(A32-1,12)=0,Aannames!$C$7,0)) -> 1602.0651 | D32: =IF(A32>=Aannames!$C$24,Aannames!$C$26*(1+Aannames!$C$6)^(A32-Aannames!$C$24),0) -> 394.77953 | E32: =C32+D32 -> 1996.8446 | F32: =E32*Aannames!$C$8 -> 1098.2646 | G32: =CohortBasis!Z$38 -> 2337.4341 | H32: =G32*Aannames!$C$9 -> 58.435853 | I32: =H32*Aannames!$C$10*(1-Aannames!$C$11) -> 223.02043 | J32: =MIN(J31*(1-Aannames!$C$18)+IF(A32>=Aannames!$C$14,Aannames!$C$15*Aannames!$C$16,0),(Aannames!$C$19+IF(A32>=Aannames!$C$24,Aannames!$C$25,0))*Aannames!$C$20) -> 36.658444 | K32: =J32*Aannames!$C$17 -> 1649.63 | L32: =IF(AND(A32>12,MOD(A32-1,12)=0),Aannames!$C$37,0) -> 5000 | M32: =I32+K32+L32 -> 6872.6504 | N32: =Aannames!$C$28+G32*Aannames!$C$29 -> 106.74868 | O32: =Aannames!$C$30*(1+IF(A32>=Aannames!$C$24,1,0)) -> 160 | P32: =Aannames!$C$31 -> 70 | Q32: =IF(MOD(A32-1,12)=0,Aannames!$C$32,0) -> 150 | R32: =Aannames!$C$33+IF(MOD(A32-1,12)=0,Aannames!$C$34,0) -> 950 | S32: =IF(A32=1,Aannames!$C$35,0) -> 0 | T32: =SUM(N32:S32) -> 1436.7487 | U32: =M32-T32 -> 5435.9017 | V32: =V31+U32 -> 16538.776
A33: 26 | B33: okt-28 | C33: =Aannames!$C$5*(1+Aannames!$C$6)^(A33-2)*(1+IF(MOD(A33-1,12)=0,Aannames!$C$7,0)) -> 666.45908 | D33: =IF(A33>=Aannames!$C$24,Aannames!$C$26*(1+Aannames!$C$6)^(A33-Aannames!$C$24),0) -> 410.57072 | E33: =C33+D33 -> 1077.0298 | F33: =E33*Aannames!$C$8 -> 592.36639 | G33: =CohortBasis!AA$38 -> 2124.4014 | H33: =G33*Aannames!$C$9 -> 53.110035 | I33: =H33*Aannames!$C$10*(1-Aannames!$C$11) -> 202.69445 | J33: =MIN(J32*(1-Aannames!$C$18)+IF(A33>=Aannames!$C$14,Aannames!$C$15*Aannames!$C$16,0),(Aannames!$C$19+IF(A33>=Aannames!$C$24,Aannames!$C$25,0))*Aannames!$C$20) -> 38.141983 | K33: =J33*Aannames!$C$17 -> 1716.3892 | L33: =IF(AND(A33>12,MOD(A33-1,12)=0),Aannames!$C$37,0) -> 0 | M33: =I33+K33+L33 -> 1919.0837 | N33: =Aannames!$C$28+G33*Aannames!$C$29 -> 102.48803 | O33: =Aannames!$C$30*(1+IF(A33>=Aannames!$C$24,1,0)) -> 160 | P33: =Aannames!$C$31 -> 70 | Q33: =IF(MOD(A33-1,12)=0,Aannames!$C$32,0) -> 0 | R33: =Aannames!$C$33+IF(MOD(A33-1,12)=0,Aannames!$C$34,0) -> 150 | S33: =IF(A33=1,Aannames!$C$35,0) -> 0 | T33: =SUM(N33:S33) -> 482.48803 | U33: =M33-T33 -> 1436.5956 | V33: =V32+U33 -> 17975.372
A34: 27 | B34: nov-28 | C34: =Aannames!$C$5*(1+Aannames!$C$6)^(A34-2)*(1+IF(MOD(A34-1,12)=0,Aannames!$C$7,0)) -> 693.11745 | D34: =IF(A34>=Aannames!$C$24,Aannames!$C$26*(1+Aannames!$C$6)^(A34-Aannames!$C$24),0) -> 426.99354 | E34: =C34+D34 -> 1120.111 | F34: =E34*Aannames!$C$8 -> 616.06104 | G34: =CohortBasis!AB$38 -> 2178.1296 | H34: =G34*Aannames!$C$9 -> 54.453241 | I34: =H34*Aannames!$C$10*(1-Aannames!$C$11) -> 207.82079 | J34: =MIN(J33*(1-Aannames!$C$18)+IF(A34>=Aannames!$C$14,Aannames!$C$15*Aannames!$C$16,0),(Aannames!$C$19+IF(A34>=Aannames!$C$24,Aannames!$C$25,0))*Aannames!$C$20) -> 39.588433 | K34: =J34*Aannames!$C$17 -> 1781.4795 | L34: =IF(AND(A34>12,MOD(A34-1,12)=0),Aannames!$C$37,0) -> 0 | M34: =I34+K34+L34 -> 1989.3003 | N34: =Aannames!$C$28+G34*Aannames!$C$29 -> 103.56259 | O34: =Aannames!$C$30*(1+IF(A34>=Aannames!$C$24,1,0)) -> 160 | P34: =Aannames!$C$31 -> 70 | Q34: =IF(MOD(A34-1,12)=0,Aannames!$C$32,0) -> 0 | R34: =Aannames!$C$33+IF(MOD(A34-1,12)=0,Aannames!$C$34,0) -> 150 | S34: =IF(A34=1,Aannames!$C$35,0) -> 0 | T34: =SUM(N34:S34) -> 483.56259 | U34: =M34-T34 -> 1505.7377 | V34: =V33+U34 -> 19481.11
A35: 28 | B35: dec-28 | C35: =Aannames!$C$5*(1+Aannames!$C$6)^(A35-2)*(1+IF(MOD(A35-1,12)=0,Aannames!$C$7,0)) -> 720.84214 | D35: =IF(A35>=Aannames!$C$24,Aannames!$C$26*(1+Aannames!$C$6)^(A35-Aannames!$C$24),0) -> 444.07329 | E35: =C35+D35 -> 1164.9154 | F35: =E35*Aannames!$C$8 -> 640.70349 | G35: =CohortBasis!AC$38 -> 2255.5222 | H35: =G35*Aannames!$C$9 -> 56.388056 | I35: =H35*Aannames!$C$10*(1-Aannames!$C$11) -> 215.20501 | J35: =MIN(J34*(1-Aannames!$C$18)+IF(A35>=Aannames!$C$14,Aannames!$C$15*Aannames!$C$16,0),(Aannames!$C$19+IF(A35>=Aannames!$C$24,Aannames!$C$25,0))*Aannames!$C$20) -> 40.998722 | K35: =J35*Aannames!$C$17 -> 1844.9425 | L35: =IF(AND(A35>12,MOD(A35-1,12)=0),Aannames!$C$37,0) -> 0 | M35: =I35+K35+L35 -> 2060.1475 | N35: =Aannames!$C$28+G35*Aannames!$C$29 -> 105.11044 | O35: =Aannames!$C$30*(1+IF(A35>=Aannames!$C$24,1,0)) -> 160 | P35: =Aannames!$C$31 -> 70 | Q35: =IF(MOD(A35-1,12)=0,Aannames!$C$32,0) -> 0 | R35: =Aannames!$C$33+IF(MOD(A35-1,12)=0,Aannames!$C$34,0) -> 150 | S35: =IF(A35=1,Aannames!$C$35,0) -> 0 | T35: =SUM(N35:S35) -> 485.11044 | U35: =M35-T35 -> 1575.0371 | V35: =V34+U35 -> 21056.147
A36: 29 | B36: jan-29 | C36: =Aannames!$C$5*(1+Aannames!$C$6)^(A36-2)*(1+IF(MOD(A36-1,12)=0,Aannames!$C$7,0)) -> 749.67583 | D36: =IF(A36>=Aannames!$C$24,Aannames!$C$26*(1+Aannames!$C$6)^(A36-Aannames!$C$24),0) -> 461.83622 | E36: =C36+D36 -> 1211.512 | F36: =E36*Aannames!$C$8 -> 666.33163 | G36: =CohortBasis!AD$38 -> 2346.9312 | H36: =G36*Aannames!$C$9 -> 58.67328 | I36: =H36*Aannames!$C$10*(1-Aannames!$C$11) -> 223.92657 | J36: =MIN(J35*(1-Aannames!$C$18)+IF(A36>=Aannames!$C$14,Aannames!$C$15*Aannames!$C$16,0),(Aannames!$C$19+IF(A36>=Aannames!$C$24,Aannames!$C$25,0))*Aannames!$C$20) -> 42.373754 | K36: =J36*Aannames!$C$17 -> 1906.8189 | L36: =IF(AND(A36>12,MOD(A36-1,12)=0),Aannames!$C$37,0) -> 0 | M36: =I36+K36+L36 -> 2130.7455 | N36: =Aannames!$C$28+G36*Aannames!$C$29 -> 106.93862 | O36: =Aannames!$C$30*(1+IF(A36>=Aannames!$C$24,1,0)) -> 160 | P36: =Aannames!$C$31 -> 70 | Q36: =IF(MOD(A36-1,12)=0,Aannames!$C$32,0) -> 0 | R36: =Aannames!$C$33+IF(MOD(A36-1,12)=0,Aannames!$C$34,0) -> 150 | S36: =IF(A36=1,Aannames!$C$35,0) -> 0 | T36: =SUM(N36:S36) -> 486.93862 | U36: =M36-T36 -> 1643.8069 | V36: =V35+U36 -> 22699.954
A37: 30 | B37: feb-29 | C37: =Aannames!$C$5*(1+Aannames!$C$6)^(A37-2)*(1+IF(MOD(A37-1,12)=0,Aannames!$C$7,0)) -> 779.66286 | D37: =IF(A37>=Aannames!$C$24,Aannames!$C$26*(1+Aannames!$C$6)^(A37-Aannames!$C$24),0) -> 480.30967 | E37: =C37+D37 -> 1259.9725 | F37: =E37*Aannames!$C$8 -> 692.98489 | G37: =CohortBasis!AE$38 -> 2452.4943 | H37: =G37*Aannames!$C$9 -> 61.312357 | I37: =H37*Aannames!$C$10*(1-Aannames!$C$11) -> 233.99861 | J37: =MIN(J36*(1-Aannames!$C$18)+IF(A37>=Aannames!$C$14,Aannames!$C$15*Aannames!$C$16,0),(Aannames!$C$19+IF(A37>=Aannames!$C$24,Aannames!$C$25,0))*Aannames!$C$20) -> 43.71441 | K37: =J37*Aannames!$C$17 -> 1967.1485 | L37: =IF(AND(A37>12,MOD(A37-1,12)=0),Aannames!$C$37,0) -> 0 | M37: =I37+K37+L37 -> 2201.1471 | N37: =Aannames!$C$28+G37*Aannames!$C$29 -> 109.04989 | O37: =Aannames!$C$30*(1+IF(A37>=Aannames!$C$24,1,0)) -> 160 | P37: =Aannames!$C$31 -> 70 | Q37: =IF(MOD(A37-1,12)=0,Aannames!$C$32,0) -> 0 | R37: =Aannames!$C$33+IF(MOD(A37-1,12)=0,Aannames!$C$34,0) -> 150 | S37: =IF(A37=1,Aannames!$C$35,0) -> 0 | T37: =SUM(N37:S37) -> 489.04989 | U37: =M37-T37 -> 1712.0972 | V37: =V36+U37 -> 24412.051
A38: 31 | B38: mrt-29 | C38: =Aannames!$C$5*(1+Aannames!$C$6)^(A38-2)*(1+IF(MOD(A38-1,12)=0,Aannames!$C$7,0)) -> 810.84938 | D38: =IF(A38>=Aannames!$C$24,Aannames!$C$26*(1+Aannames!$C$6)^(A38-Aannames!$C$24),0) -> 499.52205 | E38: =C38+D38 -> 1310.3714 | F38: =E38*Aannames!$C$8 -> 720.70429 | G38: =CohortBasis!AF$38 -> 2562.276 | H38: =G38*Aannames!$C$9 -> 64.056901 | I38: =H38*Aannames!$C$10*(1-Aannames!$C$11) -> 244.47316 | J38: =MIN(J37*(1-Aannames!$C$18)+IF(A38>=Aannames!$C$14,Aannames!$C$15*Aannames!$C$16,0),(Aannames!$C$19+IF(A38>=Aannames!$C$24,Aannames!$C$25,0))*Aannames!$C$20) -> 45.02155 | K38: =J38*Aannames!$C$17 -> 2025.9698 | L38: =IF(AND(A38>12,MOD(A38-1,12)=0),Aannames!$C$37,0) -> 0 | M38: =I38+K38+L38 -> 2270.4429 | N38: =Aannames!$C$28+G38*Aannames!$C$29 -> 111.24552 | O38: =Aannames!$C$30*(1+IF(A38>=Aannames!$C$24,1,0)) -> 160 | P38: =Aannames!$C$31 -> 70 | Q38: =IF(MOD(A38-1,12)=0,Aannames!$C$32,0) -> 0 | R38: =Aannames!$C$33+IF(MOD(A38-1,12)=0,Aannames!$C$34,0) -> 150 | S38: =IF(A38=1,Aannames!$C$35,0) -> 0 | T38: =SUM(N38:S38) -> 491.24552 | U38: =M38-T38 -> 1779.1974 | V38: =V37+U38 -> 26191.248
A39: 32 | B39: apr-29 | C39: =Aannames!$C$5*(1+Aannames!$C$6)^(A39-2)*(1+IF(MOD(A39-1,12)=0,Aannames!$C$7,0)) -> 843.28335 | D39: =IF(A39>=Aannames!$C$24,Aannames!$C$26*(1+Aannames!$C$6)^(A39-Aannames!$C$24),0) -> 519.50293 | E39: =C39+D39 -> 1362.7863 | F39: =E39*Aannames!$C$8 -> 749.53246 | G39: =CohortBasis!AG$38 -> 2682.0623 | H39: =G39*Aannames!$C$9 -> 67.051556 | I39: =H39*Aannames!$C$10*(1-Aannames!$C$11) -> 255.90226 | J39: =MIN(J38*(1-Aannames!$C$18)+IF(A39>=Aannames!$C$14,Aannames!$C$15*Aannames!$C$16,0),(Aannames!$C$19+IF(A39>=Aannames!$C$24,Aannames!$C$25,0))*Aannames!$C$20) -> 46.296011 | K39: =J39*Aannames!$C$17 -> 2083.3205 | L39: =IF(AND(A39>12,MOD(A39-1,12)=0),Aannames!$C$37,0) -> 0 | M39: =I39+K39+L39 -> 2339.2228 | N39: =Aannames!$C$28+G39*Aannames!$C$29 -> 113.64125 | O39: =Aannames!$C$30*(1+IF(A39>=Aannames!$C$24,1,0)) -> 160 | P39: =Aannames!$C$31 -> 70 | Q39: =IF(MOD(A39-1,12)=0,Aannames!$C$32,0) -> 0 | R39: =Aannames!$C$33+IF(MOD(A39-1,12)=0,Aannames!$C$34,0) -> 150 | S39: =IF(A39=1,Aannames!$C$35,0) -> 0 | T39: =SUM(N39:S39) -> 493.64125 | U39: =M39-T39 -> 1845.5815 | V39: =V38+U39 -> 28036.83
A40: 33 | B40: mei-29 | C40: =Aannames!$C$5*(1+Aannames!$C$6)^(A40-2)*(1+IF(MOD(A40-1,12)=0,Aannames!$C$7,0)) -> 877.01469 | D40: =IF(A40>=Aannames!$C$24,Aannames!$C$26*(1+Aannames!$C$6)^(A40-Aannames!$C$24),0) -> 540.28305 | E40: =C40+D40 -> 1417.2977 | F40: =E40*Aannames!$C$8 -> 779.51376 | G40: =CohortBasis!AH$38 -> 2806.4114 | H40: =G40*Aannames!$C$9 -> 70.160285 | I40: =H40*Aannames!$C$10*(1-Aannames!$C$11) -> 267.76673 | J40: =MIN(J39*(1-Aannames!$C$18)+IF(A40>=Aannames!$C$14,Aannames!$C$15*Aannames!$C$16,0),(Aannames!$C$19+IF(A40>=Aannames!$C$24,Aannames!$C$25,0))*Aannames!$C$20) -> 47.538611 | K40: =J40*Aannames!$C$17 -> 2139.2375 | L40: =IF(AND(A40>12,MOD(A40-1,12)=0),Aannames!$C$37,0) -> 0 | M40: =I40+K40+L40 -> 2407.0042 | N40: =Aannames!$C$28+G40*Aannames!$C$29 -> 116.12823 | O40: =Aannames!$C$30*(1+IF(A40>=Aannames!$C$24,1,0)) -> 160 | P40: =Aannames!$C$31 -> 70 | Q40: =IF(MOD(A40-1,12)=0,Aannames!$C$32,0) -> 0 | R40: =Aannames!$C$33+IF(MOD(A40-1,12)=0,Aannames!$C$34,0) -> 150 | S40: =IF(A40=1,Aannames!$C$35,0) -> 0 | T40: =SUM(N40:S40) -> 496.12823 | U40: =M40-T40 -> 1910.876 | V40: =V39+U40 -> 29947.706
A41: 34 | B41: jun-29 | C41: =Aannames!$C$5*(1+Aannames!$C$6)^(A41-2)*(1+IF(MOD(A41-1,12)=0,Aannames!$C$7,0)) -> 912.09527 | D41: =IF(A41>=Aannames!$C$24,Aannames!$C$26*(1+Aannames!$C$6)^(A41-Aannames!$C$24),0) -> 561.89437 | E41: =C41+D41 -> 1473.9896 | F41: =E41*Aannames!$C$8 -> 810.69431 | G41: =CohortBasis!AI$38 -> 2935.506 | H41: =G41*Aannames!$C$9 -> 73.38765 | I41: =H41*Aannames!$C$10*(1-Aannames!$C$11) -> 280.08397 | J41: =MIN(J40*(1-Aannames!$C$18)+IF(A41>=Aannames!$C$14,Aannames!$C$15*Aannames!$C$16,0),(Aannames!$C$19+IF(A41>=Aannames!$C$24,Aannames!$C$25,0))*Aannames!$C$20) -> 48.750146 | K41: =J41*Aannames!$C$17 -> 2193.7566 | L41: =IF(AND(A41>12,MOD(A41-1,12)=0),Aannames!$C$37,0) -> 0 | M41: =I41+K41+L41 -> 2473.8405 | N41: =Aannames!$C$28+G41*Aannames!$C$29 -> 118.71012 | O41: =Aannames!$C$30*(1+IF(A41>=Aannames!$C$24,1,0)) -> 160 | P41: =Aannames!$C$31 -> 70 | Q41: =IF(MOD(A41-1,12)=0,Aannames!$C$32,0) -> 0 | R41: =Aannames!$C$33+IF(MOD(A41-1,12)=0,Aannames!$C$34,0) -> 150 | S41: =IF(A41=1,Aannames!$C$35,0) -> 0 | T41: =SUM(N41:S41) -> 498.71012 | U41: =M41-T41 -> 1975.1304 | V41: =V40+U41 -> 31922.836
A42: 35 | B42: jul-29 | C42: =Aannames!$C$5*(1+Aannames!$C$6)^(A42-2)*(1+IF(MOD(A42-1,12)=0,Aannames!$C$7,0)) -> 948.57909 | D42: =IF(A42>=Aannames!$C$24,Aannames!$C$26*(1+Aannames!$C$6)^(A42-Aannames!$C$24),0) -> 584.37015 | E42: =C42+D42 -> 1532.9492 | F42: =E42*Aannames!$C$8 -> 843.12208 | G42: =CohortBasis!AJ$38 -> 3069.5359 | H42: =G42*Aannames!$C$9 -> 76.738396 | I42: =H42*Aannames!$C$10*(1-Aannames!$C$11) -> 292.87209 | J42: =MIN(J41*(1-Aannames!$C$18)+IF(A42>=Aannames!$C$14,Aannames!$C$15*Aannames!$C$16,0),(Aannames!$C$19+IF(A42>=Aannames!$C$24,Aannames!$C$25,0))*Aannames!$C$20) -> 49.931392 | K42: =J42*Aannames!$C$17 -> 2246.9126 | L42: =IF(AND(A42>12,MOD(A42-1,12)=0),Aannames!$C$37,0) -> 0 | M42: =I42+K42+L42 -> 2539.7847 | N42: =Aannames!$C$28+G42*Aannames!$C$29 -> 121.39072 | O42: =Aannames!$C$30*(1+IF(A42>=Aannames!$C$24,1,0)) -> 160 | P42: =Aannames!$C$31 -> 70 | Q42: =IF(MOD(A42-1,12)=0,Aannames!$C$32,0) -> 0 | R42: =Aannames!$C$33+IF(MOD(A42-1,12)=0,Aannames!$C$34,0) -> 150 | S42: =IF(A42=1,Aannames!$C$35,0) -> 0 | T42: =SUM(N42:S42) -> 501.39072 | U42: =M42-T42 -> 2038.394 | V42: =V41+U42 -> 33961.23
A43: 36 | B43: aug-29 | C43: =Aannames!$C$5*(1+Aannames!$C$6)^(A43-2)*(1+IF(MOD(A43-1,12)=0,Aannames!$C$7,0)) -> 986.52225 | D43: =IF(A43>=Aannames!$C$24,Aannames!$C$26*(1+Aannames!$C$6)^(A43-Aannames!$C$24),0) -> 607.74495 | E43: =C43+D43 -> 1594.2672 | F43: =E43*Aannames!$C$8 -> 876.84696 | G43: =CohortBasis!AK$38 -> 3211.3418 | H43: =G43*Aannames!$C$9 -> 80.283545 | I43: =H43*Aannames!$C$10*(1-Aannames!$C$11) -> 306.40215 | J43: =MIN(J42*(1-Aannames!$C$18)+IF(A43>=Aannames!$C$14,Aannames!$C$15*Aannames!$C$16,0),(Aannames!$C$19+IF(A43>=Aannames!$C$24,Aannames!$C$25,0))*Aannames!$C$20) -> 51.083107 | K43: =J43*Aannames!$C$17 -> 2298.7398 | L43: =IF(AND(A43>12,MOD(A43-1,12)=0),Aannames!$C$37,0) -> 0 | M43: =I43+K43+L43 -> 2605.142 | N43: =Aannames!$C$28+G43*Aannames!$C$29 -> 124.22684 | O43: =Aannames!$C$30*(1+IF(A43>=Aannames!$C$24,1,0)) -> 160 | P43: =Aannames!$C$31 -> 70 | Q43: =IF(MOD(A43-1,12)=0,Aannames!$C$32,0) -> 0 | R43: =Aannames!$C$33+IF(MOD(A43-1,12)=0,Aannames!$C$34,0) -> 150 | S43: =IF(A43=1,Aannames!$C$35,0) -> 0 | T43: =SUM(N43:S43) -> 504.22684 | U43: =M43-T43 -> 2100.9151 | V43: =V42+U43 -> 36062.145
A45: KPI's
A46: MAU M12 | C46: =G19 -> 630.43446
A47: MAU M24 | C47: =G31 -> 1707.8943
A48: MAU M36 | C48: =G43 -> 3211.3418
A49: Betalende venues M36 | C49: =J43 -> 51.083107
A50: MRR M36 (venue + consumer) | C50: =K43+I43 -> 2605.142
A51: Omzet jaar 3 (M25-M36) | C51: =SUM(M32:M43) -> 31808.512
A52: Blended ARPU M36 (A$/MAU/mnd) | C52: =IF(G43=0,0,M43/G43) -> 0.81123161
A53: Consumer-LTV per geactiveerde gebruiker | C53: =Retentie!$C$38*Aannames!$C$9*Aannames!$C$10*(1-Aannames!$C$11) -> 0.5129376
A54: Blended consumer-CAC (marketing/actieve) | C54: =SUM(R8:R43)/SUM(F8:F43) -> 0.47410893
A55: LTV:CAC consumer | C55: =IF(C54=0,0,C53/C54) -> 1.0818982
A56: Venue-LTV (prijs x marge / churn) | C56: =Aannames!$C$17*Aannames!$C$22/Aannames!$C$18 -> 1692
A57: Venue-CAC | C57: =Aannames!$C$21 -> 120
A58: LTV:CAC venue | C58: =IF(C57=0,0,C56/C57) -> 14.1
A59: Venue-payback (mnd) | C59: =Aannames!$C$21/(Aannames!$C$17*Aannames!$C$22) -> 2.8368794
A60: Max. cumulatieve burn | C60: =-MIN(V8:V43) -> 3660.0616
A61: Cumulatieve cashflow M36 | C61: =V43 -> 36062.145
A62: Break-even (cumulatief), maand # | C62: =IF(V43<0,"niet in 36 mnd",SUMPRODUCT(--($V$8:$V$43<0))+1) -> 13 | E62: Break-even-telling klopt zodra het cumulatief na de eerste kruising positief blijft (in alle drie scenario's het geval).

Sheet CohortBasis
A1: Cohort \ kalendermaand | B1: 1 | C1: 2 | D1: 3 | E1: 4 | F1: 5 | G1: 6 | H1: 7 | I1: 8 | J1: 9 | K1: 10 | L1: 11 | M1: 12 | N1: 13 | O1: 14 | P1: 15 | Q1: 16 | R1: 17 | S1: 18 | T1: 19 | U1: 20 | V1: 21 | W1: 22 | X1: 23 | Y1: 24 | Z1: 25 | AA1: 26 | AB1: 27 | AC1: 28 | AD1: 29 | AE1: 30 | AF1: 31 | AG1: 32 | AH1: 33 | AI1: 34 | AJ1: 35 | AK1: 36
A2: 1 | B2: =ModelBasis!$F$8*Retentie!$C$2 -> 495 | C2: =ModelBasis!$F$8*Retentie!$C$3 -> 198 | D2: =ModelBasis!$F$8*Retentie!$C$4 -> 148.5 | E2: =ModelBasis!$F$8*Retentie!$C$5 -> 118.8 | F2: =ModelBasis!$F$8*Retentie!$C$6 -> 99 | G2: =ModelBasis!$F$8*Retentie!$C$7 -> 89.1 | H2: =ModelBasis!$F$8*Retentie!$C$8 -> 79.2 | I2: =ModelBasis!$F$8*Retentie!$C$9 -> 74.25 | J2: =ModelBasis!$F$8*Retentie!$C$10 -> 69.3 | K2: =ModelBasis!$F$8*Retentie!$C$11 -> 64.35 | L2: =ModelBasis!$F$8*Retentie!$C$12 -> 59.4 | M2: =ModelBasis!$F$8*Retentie!$C$13 -> 56.925 | N2: =ModelBasis!$F$8*Retentie!$C$14 -> 54.45 | O2: =ModelBasis!$F$8*Retentie!$C$15 -> 53.46 | P2: =ModelBasis!$F$8*Retentie!$C$16 -> 52.47 | Q2: =ModelBasis!$F$8*Retentie!$C$17 -> 51.48 | R2: =ModelBasis!$F$8*Retentie!$C$18 -> 50.49 | S2: =ModelBasis!$F$8*Retentie!$C$19 -> 49.5 | T2: =ModelBasis!$F$8*Retentie!$C$20 -> 48.51 | U2: =ModelBasis!$F$8*Retentie!$C$21 -> 48.015 | V2: =ModelBasis!$F$8*Retentie!$C$22 -> 47.52 | W2: =ModelBasis!$F$8*Retentie!$C$23 -> 47.025 | X2: =ModelBasis!$F$8*Retentie!$C$24 -> 46.53 | Y2: =ModelBasis!$F$8*Retentie!$C$25 -> 46.035 | Z2: =ModelBasis!$F$8*Retentie!$C$26 -> 45.54 | AA2: =ModelBasis!$F$8*Retentie!$C$27 -> 45.045 | AB2: =ModelBasis!$F$8*Retentie!$C$28 -> 44.55 | AC2: =ModelBasis!$F$8*Retentie!$C$29 -> 44.055 | AD2: =ModelBasis!$F$8*Retentie!$C$30 -> 43.56 | AE2: =ModelBasis!$F$8*Retentie!$C$31 -> 43.065 | AF2: =ModelBasis!$F$8*Retentie!$C$32 -> 42.57 | AG2: =ModelBasis!$F$8*Retentie!$C$33 -> 42.075 | AH2: =ModelBasis!$F$8*Retentie!$C$34 -> 41.58 | AI2: =ModelBasis!$F$8*Retentie!$C$35 -> 41.085 | AJ2: =ModelBasis!$F$8*Retentie!$C$36 -> 40.59 | AK2: =ModelBasis!$F$8*Retentie!$C$37 -> 40.095
A3: 2 | C3: =ModelBasis!$F$9*Retentie!$C$2 -> 143 | D3: =ModelBasis!$F$9*Retentie!$C$3 -> 57.2 | E3: =ModelBasis!$F$9*Retentie!$C$4 -> 42.9 | F3: =ModelBasis!$F$9*Retentie!$C$5 -> 34.32 | G3: =ModelBasis!$F$9*Retentie!$C$6 -> 28.6 | H3: =ModelBasis!$F$9*Retentie!$C$7 -> 25.74 | I3: =ModelBasis!$F$9*Retentie!$C$8 -> 22.88 | J3: =ModelBasis!$F$9*Retentie!$C$9 -> 21.45 | K3: =ModelBasis!$F$9*Retentie!$C$10 -> 20.02 | L3: =ModelBasis!$F$9*Retentie!$C$11 -> 18.59 | M3: =ModelBasis!$F$9*Retentie!$C$12 -> 17.16 | N3: =ModelBasis!$F$9*Retentie!$C$13 -> 16.445 | O3: =ModelBasis!$F$9*Retentie!$C$14 -> 15.73 | P3: =ModelBasis!$F$9*Retentie!$C$15 -> 15.444 | Q3: =ModelBasis!$F$9*Retentie!$C$16 -> 15.158 | R3: =ModelBasis!$F$9*Retentie!$C$17 -> 14.872 | S3: =ModelBasis!$F$9*Retentie!$C$18 -> 14.586 | T3: =ModelBasis!$F$9*Retentie!$C$19 -> 14.3 | U3: =ModelBasis!$F$9*Retentie!$C$20 -> 14.014 | V3: =ModelBasis!$F$9*Retentie!$C$21 -> 13.871 | W3: =ModelBasis!$F$9*Retentie!$C$22 -> 13.728 | X3: =ModelBasis!$F$9*Retentie!$C$23 -> 13.585 | Y3: =ModelBasis!$F$9*Retentie!$C$24 -> 13.442 | Z3: =ModelBasis!$F$9*Retentie!$C$25 -> 13.299 | AA3: =ModelBasis!$F$9*Retentie!$C$26 -> 13.156 | AB3: =ModelBasis!$F$9*Retentie!$C$27 -> 13.013 | AC3: =ModelBasis!$F$9*Retentie!$C$28 -> 12.87 | AD3: =ModelBasis!$F$9*Retentie!$C$29 -> 12.727 | AE3: =ModelBasis!$F$9*Retentie!$C$30 -> 12.584 | AF3: =ModelBasis!$F$9*Retentie!$C$31 -> 12.441 | AG3: =ModelBasis!$F$9*Retentie!$C$32 -> 12.298 | AH3: =ModelBasis!$F$9*Retentie!$C$33 -> 12.155 | AI3: =ModelBasis!$F$9*Retentie!$C$34 -> 12.012 | AJ3: =ModelBasis!$F$9*Retentie!$C$35 -> 11.869 | AK3: =ModelBasis!$F$9*Retentie!$C$36 -> 11.726
A4: 3 | D4: =ModelBasis!$F$10*Retentie!$C$2 -> 148.72 | E4: =ModelBasis!$F$10*Retentie!$C$3 -> 59.488 | F4: =ModelBasis!$F$10*Retentie!$C$4 -> 44.616 | G4: =ModelBasis!$F$10*Retentie!$C$5 -> 35.6928 | H4: =ModelBasis!$F$10*Retentie!$C$6 -> 29.744 | I4: =ModelBasis!$F$10*Retentie!$C$7 -> 26.7696 | J4: =ModelBasis!$F$10*Retentie!$C$8 -> 23.7952 | K4: =ModelBasis!$F$10*Retentie!$C$9 -> 22.308 | L4: =ModelBasis!$F$10*Retentie!$C$10 -> 20.8208 | M4: =ModelBasis!$F$10*Retentie!$C$11 -> 19.3336 | N4: =ModelBasis!$F$10*Retentie!$C$12 -> 17.8464 | O4: =ModelBasis!$F$10*Retentie!$C$13 -> 17.1028 | P4: =ModelBasis!$F$10*Retentie!$C$14 -> 16.3592 | Q4: =ModelBasis!$F$10*Retentie!$C$15 -> 16.06176 | R4: =ModelBasis!$F$10*Retentie!$C$16 -> 15.76432 | S4: =ModelBasis!$F$10*Retentie!$C$17 -> 15.46688 | T4: =ModelBasis!$F$10*Retentie!$C$18 -> 15.16944 | U4: =ModelBasis!$F$10*Retentie!$C$19 -> 14.872 | V4: =ModelBasis!$F$10*Retentie!$C$20 -> 14.57456 | W4: =ModelBasis!$F$10*Retentie!$C$21 -> 14.42584 | X4: =ModelBasis!$F$10*Retentie!$C$22 -> 14.27712 | Y4: =ModelBasis!$F$10*Retentie!$C$23 -> 14.1284 | Z4: =ModelBasis!$F$10*Retentie!$C$24 -> 13.97968 | AA4: =ModelBasis!$F$10*Retentie!$C$25 -> 13.83096 | AB4: =ModelBasis!$F$10*Retentie!$C$26 -> 13.68224 | AC4: =ModelBasis!$F$10*Retentie!$C$27 -> 13.53352 | AD4: =ModelBasis!$F$10*Retentie!$C$28 -> 13.3848 | AE4: =ModelBasis!$F$10*Retentie!$C$29 -> 13.23608 | AF4: =ModelBasis!$F$10*Retentie!$C$30 -> 13.08736 | AG4: =ModelBasis!$F$10*Retentie!$C$31 -> 12.93864 | AH4: =ModelBasis!$F$10*Retentie!$C$32 -> 12.78992 | AI4: =ModelBasis!$F$10*Retentie!$C$33 -> 12.6412 | AJ4: =ModelBasis!$F$10*Retentie!$C$34 -> 12.49248 | AK4: =ModelBasis!$F$10*Retentie!$C$35 -> 12.34376
A5: 4 | E5: =ModelBasis!$F$11*Retentie!$C$2 -> 154.6688 | F5: =ModelBasis!$F$11*Retentie!$C$3 -> 61.86752 | G5: =ModelBasis!$F$11*Retentie!$C$4 -> 46.40064 | H5: =ModelBasis!$F$11*Retentie!$C$5 -> 37.120512 | I5: =ModelBasis!$F$11*Retentie!$C$6 -> 30.93376 | J5: =ModelBasis!$F$11*Retentie!$C$7 -> 27.840384 | K5: =ModelBasis!$F$11*Retentie!$C$8 -> 24.747008 | L5: =ModelBasis!$F$11*Retentie!$C$9 -> 23.20032 | M5: =ModelBasis!$F$11*Retentie!$C$10 -> 21.653632 | N5: =ModelBasis!$F$11*Retentie!$C$11 -> 20.106944 | O5: =ModelBasis!$F$11*Retentie!$C$12 -> 18.560256 | P5: =ModelBasis!$F$11*Retentie!$C$13 -> 17.786912 | Q5: =ModelBasis!$F$11*Retentie!$C$14 -> 17.013568 | R5: =ModelBasis!$F$11*Retentie!$C$15 -> 16.70423 | S5: =ModelBasis!$F$11*Retentie!$C$16 -> 16.394893 | T5: =ModelBasis!$F$11*Retentie!$C$17 -> 16.085555 | U5: =ModelBasis!$F$11*Retentie!$C$18 -> 15.776218 | V5: =ModelBasis!$F$11*Retentie!$C$19 -> 15.46688 | W5: =ModelBasis!$F$11*Retentie!$C$20 -> 15.157542 | X5: =ModelBasis!$F$11*Retentie!$C$21 -> 15.002874 | Y5: =ModelBasis!$F$11*Retentie!$C$22 -> 14.848205 | Z5: =ModelBasis!$F$11*Retentie!$C$23 -> 14.693536 | AA5: =ModelBasis!$F$11*Retentie!$C$24 -> 14.538867 | AB5: =ModelBasis!$F$11*Retentie!$C$25 -> 14.384198 | AC5: =ModelBasis!$F$11*Retentie!$C$26 -> 14.22953 | AD5: =ModelBasis!$F$11*Retentie!$C$27 -> 14.074861 | AE5: =ModelBasis!$F$11*Retentie!$C$28 -> 13.920192 | AF5: =ModelBasis!$F$11*Retentie!$C$29 -> 13.765523 | AG5: =ModelBasis!$F$11*Retentie!$C$30 -> 13.610854 | AH5: =ModelBasis!$F$11*Retentie!$C$31 -> 13.456186 | AI5: =ModelBasis!$F$11*Retentie!$C$32 -> 13.301517 | AJ5: =ModelBasis!$F$11*Retentie!$C$33 -> 13.146848 | AK5: =ModelBasis!$F$11*Retentie!$C$34 -> 12.992179
A6: 5 | F6: =ModelBasis!$F$12*Retentie!$C$2 -> 160.85555 | G6: =ModelBasis!$F$12*Retentie!$C$3 -> 64.342221 | H6: =ModelBasis!$F$12*Retentie!$C$4 -> 48.256666 | I6: =ModelBasis!$F$12*Retentie!$C$5 -> 38.605332 | J6: =ModelBasis!$F$12*Retentie!$C$6 -> 32.17111 | K6: =ModelBasis!$F$12*Retentie!$C$7 -> 28.953999 | L6: =ModelBasis!$F$12*Retentie!$C$8 -> 25.736888 | M6: =ModelBasis!$F$12*Retentie!$C$9 -> 24.128333 | N6: =ModelBasis!$F$12*Retentie!$C$10 -> 22.519777 | O6: =ModelBasis!$F$12*Retentie!$C$11 -> 20.911222 | P6: =ModelBasis!$F$12*Retentie!$C$12 -> 19.302666 | Q6: =ModelBasis!$F$12*Retentie!$C$13 -> 18.498388 | R6: =ModelBasis!$F$12*Retentie!$C$14 -> 17.694111 | S6: =ModelBasis!$F$12*Retentie!$C$15 -> 17.3724 | T6: =ModelBasis!$F$12*Retentie!$C$16 -> 17.050689 | U6: =ModelBasis!$F$12*Retentie!$C$17 -> 16.728977 | V6: =ModelBasis!$F$12*Retentie!$C$18 -> 16.407266 | W6: =ModelBasis!$F$12*Retentie!$C$19 -> 16.085555 | X6: =ModelBasis!$F$12*Retentie!$C$20 -> 15.763844 | Y6: =ModelBasis!$F$12*Retentie!$C$21 -> 15.602989 | Z6: =ModelBasis!$F$12*Retentie!$C$22 -> 15.442133 | AA6: =ModelBasis!$F$12*Retentie!$C$23 -> 15.281277 | AB6: =ModelBasis!$F$12*Retentie!$C$24 -> 15.120422 | AC6: =ModelBasis!$F$12*Retentie!$C$25 -> 14.959566 | AD6: =ModelBasis!$F$12*Retentie!$C$26 -> 14.798711 | AE6: =ModelBasis!$F$12*Retentie!$C$27 -> 14.637855 | AF6: =ModelBasis!$F$12*Retentie!$C$28 -> 14.477 | AG6: =ModelBasis!$F$12*Retentie!$C$29 -> 14.316144 | AH6: =ModelBasis!$F$12*Retentie!$C$30 -> 14.155289 | AI6: =ModelBasis!$F$12*Retentie!$C$31 -> 13.994433 | AJ6: =ModelBasis!$F$12*Retentie!$C$32 -> 13.833577 | AK6: =ModelBasis!$F$12*Retentie!$C$33 -> 13.672722
A7: 6 | G7: =ModelBasis!$F$13*Retentie!$C$2 -> 167.28977 | H7: =ModelBasis!$F$13*Retentie!$C$3 -> 66.91591 | I7: =ModelBasis!$F$13*Retentie!$C$4 -> 50.186932 | J7: =ModelBasis!$F$13*Retentie!$C$5 -> 40.149546 | K7: =ModelBasis!$F$13*Retentie!$C$6 -> 33.457955 | L7: =ModelBasis!$F$13*Retentie!$C$7 -> 30.112159 | M7: =ModelBasis!$F$13*Retentie!$C$8 -> 26.766364 | N7: =ModelBasis!$F$13*Retentie!$C$9 -> 25.093466 | O7: =ModelBasis!$F$13*Retentie!$C$10 -> 23.420568 | P7: =ModelBasis!$F$13*Retentie!$C$11 -> 21.747671 | Q7: =ModelBasis!$F$13*Retentie!$C$12 -> 20.074773 | R7: =ModelBasis!$F$13*Retentie!$C$13 -> 19.238324 | S7: =ModelBasis!$F$13*Retentie!$C$14 -> 18.401875 | T7: =ModelBasis!$F$13*Retentie!$C$15 -> 18.067296 | U7: =ModelBasis!$F$13*Retentie!$C$16 -> 17.732716 | V7: =ModelBasis!$F$13*Retentie!$C$17 -> 17.398137 | W7: =ModelBasis!$F$13*Retentie!$C$18 -> 17.063557 | X7: =ModelBasis!$F$13*Retentie!$C$19 -> 16.728977 | Y7: =ModelBasis!$F$13*Retentie!$C$20 -> 16.394398 | Z7: =ModelBasis!$F$13*Retentie!$C$21 -> 16.227108 | AA7: =ModelBasis!$F$13*Retentie!$C$22 -> 16.059818 | AB7: =ModelBasis!$F$13*Retentie!$C$23 -> 15.892529 | AC7: =ModelBasis!$F$13*Retentie!$C$24 -> 15.725239 | AD7: =ModelBasis!$F$13*Retentie!$C$25 -> 15.557949 | AE7: =ModelBasis!$F$13*Retentie!$C$26 -> 15.390659 | AF7: =ModelBasis!$F$13*Retentie!$C$27 -> 15.223369 | AG7: =ModelBasis!$F$13*Retentie!$C$28 -> 15.05608 | AH7: =ModelBasis!$F$13*Retentie!$C$29 -> 14.88879 | AI7: =ModelBasis!$F$13*Retentie!$C$30 -> 14.7215 | AJ7: =ModelBasis!$F$13*Retentie!$C$31 -> 14.55421 | AK7: =ModelBasis!$F$13*Retentie!$C$32 -> 14.386921
A8: 7 | H8: =ModelBasis!$F$14*Retentie!$C$2 -> 173.98137 | I8: =ModelBasis!$F$14*Retentie!$C$3 -> 69.592546 | J8: =ModelBasis!$F$14*Retentie!$C$4 -> 52.19441 | K8: =ModelBasis!$F$14*Retentie!$C$5 -> 41.755528 | L8: =ModelBasis!$F$14*Retentie!$C$6 -> 34.796273 | M8: =ModelBasis!$F$14*Retentie!$C$7 -> 31.316646 | N8: =ModelBasis!$F$14*Retentie!$C$8 -> 27.837018 | O8: =ModelBasis!$F$14*Retentie!$C$9 -> 26.097205 | P8: =ModelBasis!$F$14*Retentie!$C$10 -> 24.357391 | Q8: =ModelBasis!$F$14*Retentie!$C$11 -> 22.617577 | R8: =ModelBasis!$F$14*Retentie!$C$12 -> 20.877764 | S8: =ModelBasis!$F$14*Retentie!$C$13 -> 20.007857 | T8: =ModelBasis!$F$14*Retentie!$C$14 -> 19.13795 | U8: =ModelBasis!$F$14*Retentie!$C$15 -> 18.789987 | V8: =ModelBasis!$F$14*Retentie!$C$16 -> 18.442025 | W8: =ModelBasis!$F$14*Retentie!$C$17 -> 18.094062 | X8: =ModelBasis!$F$14*Retentie!$C$18 -> 17.746099 | Y8: =ModelBasis!$F$14*Retentie!$C$19 -> 17.398137 | Z8: =ModelBasis!$F$14*Retentie!$C$20 -> 17.050174 | AA8: =ModelBasis!$F$14*Retentie!$C$21 -> 16.876192 | AB8: =ModelBasis!$F$14*Retentie!$C$22 -> 16.702211 | AC8: =ModelBasis!$F$14*Retentie!$C$23 -> 16.52823 | AD8: =ModelBasis!$F$14*Retentie!$C$24 -> 16.354248 | AE8: =ModelBasis!$F$14*Retentie!$C$25 -> 16.180267 | AF8: =ModelBasis!$F$14*Retentie!$C$26 -> 16.006286 | AG8: =ModelBasis!$F$14*Retentie!$C$27 -> 15.832304 | AH8: =ModelBasis!$F$14*Retentie!$C$28 -> 15.658323 | AI8: =ModelBasis!$F$14*Retentie!$C$29 -> 15.484341 | AJ8: =ModelBasis!$F$14*Retentie!$C$30 -> 15.31036 | AK8: =ModelBasis!$F$14*Retentie!$C$31 -> 15.136379
A9: 8 | I9: =ModelBasis!$F$15*Retentie!$C$2 -> 180.94062 | J9: =ModelBasis!$F$15*Retentie!$C$3 -> 72.376248 | K9: =ModelBasis!$F$15*Retentie!$C$4 -> 54.282186 | L9: =ModelBasis!$F$15*Retentie!$C$5 -> 43.425749 | M9: =ModelBasis!$F$15*Retentie!$C$6 -> 36.188124 | N9: =ModelBasis!$F$15*Retentie!$C$7 -> 32.569312 | O9: =ModelBasis!$F$15*Retentie!$C$8 -> 28.950499 | P9: =ModelBasis!$F$15*Retentie!$C$9 -> 27.141093 | Q9: =ModelBasis!$F$15*Retentie!$C$10 -> 25.331687 | R9: =ModelBasis!$F$15*Retentie!$C$11 -> 23.522281 | S9: =ModelBasis!$F$15*Retentie!$C$12 -> 21.712874 | T9: =ModelBasis!$F$15*Retentie!$C$13 -> 20.808171 | U9: =ModelBasis!$F$15*Retentie!$C$14 -> 19.903468 | V9: =ModelBasis!$F$15*Retentie!$C$15 -> 19.541587 | W9: =ModelBasis!$F$15*Retentie!$C$16 -> 19.179706 | X9: =ModelBasis!$F$15*Retentie!$C$17 -> 18.817824 | Y9: =ModelBasis!$F$15*Retentie!$C$18 -> 18.455943 | Z9: =ModelBasis!$F$15*Retentie!$C$19 -> 18.094062 | AA9: =ModelBasis!$F$15*Retentie!$C$20 -> 17.732181 | AB9: =ModelBasis!$F$15*Retentie!$C$21 -> 17.55124 | AC9: =ModelBasis!$F$15*Retentie!$C$22 -> 17.370299 | AD9: =ModelBasis!$F$15*Retentie!$C$23 -> 17.189359 | AE9: =ModelBasis!$F$15*Retentie!$C$24 -> 17.008418 | AF9: =ModelBasis!$F$15*Retentie!$C$25 -> 16.827478 | AG9: =ModelBasis!$F$15*Retentie!$C$26 -> 16.646537 | AH9: =ModelBasis!$F$15*Retentie!$C$27 -> 16.465596 | AI9: =ModelBasis!$F$15*Retentie!$C$28 -> 16.284656 | AJ9: =ModelBasis!$F$15*Retentie!$C$29 -> 16.103715 | AK9: =ModelBasis!$F$15*Retentie!$C$30 -> 15.922775
A10: 9 | J10: =ModelBasis!$F$16*Retentie!$C$2 -> 188.17824 | K10: =ModelBasis!$F$16*Retentie!$C$3 -> 75.271298 | L10: =ModelBasis!$F$16*Retentie!$C$4 -> 56.453473 | M10: =ModelBasis!$F$16*Retentie!$C$5 -> 45.162779 | N10: =ModelBasis!$F$16*Retentie!$C$6 -> 37.635649 | O10: =ModelBasis!$F$16*Retentie!$C$7 -> 33.872084 | P10: =ModelBasis!$F$16*Retentie!$C$8 -> 30.108519 | Q10: =ModelBasis!$F$16*Retentie!$C$9 -> 28.226737 | R10: =ModelBasis!$F$16*Retentie!$C$10 -> 26.344954 | S10: =ModelBasis!$F$16*Retentie!$C$11 -> 24.463172 | T10: =ModelBasis!$F$16*Retentie!$C$12 -> 22.581389 | U10: =ModelBasis!$F$16*Retentie!$C$13 -> 21.640498 | V10: =ModelBasis!$F$16*Retentie!$C$14 -> 20.699607 | W10: =ModelBasis!$F$16*Retentie!$C$15 -> 20.32325 | X10: =ModelBasis!$F$16*Retentie!$C$16 -> 19.946894 | Y10: =ModelBasis!$F$16*Retentie!$C$17 -> 19.570537 | Z10: =ModelBasis!$F$16*Retentie!$C$18 -> 19.194181 | AA10: =ModelBasis!$F$16*Retentie!$C$19 -> 18.817824 | AB10: =ModelBasis!$F$16*Retentie!$C$20 -> 18.441468 | AC10: =ModelBasis!$F$16*Retentie!$C$21 -> 18.25329 | AD10: =ModelBasis!$F$16*Retentie!$C$22 -> 18.065111 | AE10: =ModelBasis!$F$16*Retentie!$C$23 -> 17.876933 | AF10: =ModelBasis!$F$16*Retentie!$C$24 -> 17.688755 | AG10: =ModelBasis!$F$16*Retentie!$C$25 -> 17.500577 | AH10: =ModelBasis!$F$16*Retentie!$C$26 -> 17.312398 | AI10: =ModelBasis!$F$16*Retentie!$C$27 -> 17.12422 | AJ10: =ModelBasis!$F$16*Retentie!$C$28 -> 16.936042 | AK10: =ModelBasis!$F$16*Retentie!$C$29 -> 16.747864
A11: 10 | K11: =ModelBasis!$F$17*Retentie!$C$2 -> 195.70537 | L11: =ModelBasis!$F$17*Retentie!$C$3 -> 78.28215 | M11: =ModelBasis!$F$17*Retentie!$C$4 -> 58.711612 | N11: =ModelBasis!$F$17*Retentie!$C$5 -> 46.96929 | O11: =ModelBasis!$F$17*Retentie!$C$6 -> 39.141075 | P11: =ModelBasis!$F$17*Retentie!$C$7 -> 35.226967 | Q11: =ModelBasis!$F$17*Retentie!$C$8 -> 31.31286 | R11: =ModelBasis!$F$17*Retentie!$C$9 -> 29.355806 | S11: =ModelBasis!$F$17*Retentie!$C$10 -> 27.398752 | T11: =ModelBasis!$F$17*Retentie!$C$11 -> 25.441699 | U11: =ModelBasis!$F$17*Retentie!$C$12 -> 23.484645 | V11: =ModelBasis!$F$17*Retentie!$C$13 -> 22.506118 | W11: =ModelBasis!$F$17*Retentie!$C$14 -> 21.527591 | X11: =ModelBasis!$F$17*Retentie!$C$15 -> 21.13618 | Y11: =ModelBasis!$F$17*Retentie!$C$16 -> 20.74477 | Z11: =ModelBasis!$F$17*Retentie!$C$17 -> 20.353359 | AA11: =ModelBasis!$F$17*Retentie!$C$18 -> 19.961948 | AB11: =ModelBasis!$F$17*Retentie!$C$19 -> 19.570537 | AC11: =ModelBasis!$F$17*Retentie!$C$20 -> 19.179127 | AD11: =ModelBasis!$F$17*Retentie!$C$21 -> 18.983421 | AE11: =ModelBasis!$F$17*Retentie!$C$22 -> 18.787716 | AF11: =ModelBasis!$F$17*Retentie!$C$23 -> 18.592011 | AG11: =ModelBasis!$F$17*Retentie!$C$24 -> 18.396305 | AH11: =ModelBasis!$F$17*Retentie!$C$25 -> 18.2006 | AI11: =ModelBasis!$F$17*Retentie!$C$26 -> 18.004894 | AJ11: =ModelBasis!$F$17*Retentie!$C$27 -> 17.809189 | AK11: =ModelBasis!$F$17*Retentie!$C$28 -> 17.613484
A12: 11 | L12: =ModelBasis!$F$18*Retentie!$C$2 -> 203.53359 | M12: =ModelBasis!$F$18*Retentie!$C$3 -> 81.413436 | N12: =ModelBasis!$F$18*Retentie!$C$4 -> 61.060077 | O12: =ModelBasis!$F$18*Retentie!$C$5 -> 48.848061 | P12: =ModelBasis!$F$18*Retentie!$C$6 -> 40.706718 | Q12: =ModelBasis!$F$18*Retentie!$C$7 -> 36.636046 | R12: =ModelBasis!$F$18*Retentie!$C$8 -> 32.565374 | S12: =ModelBasis!$F$18*Retentie!$C$9 -> 30.530038 | T12: =ModelBasis!$F$18*Retentie!$C$10 -> 28.494702 | U12: =ModelBasis!$F$18*Retentie!$C$11 -> 26.459367 | V12: =ModelBasis!$F$18*Retentie!$C$12 -> 24.424031 | W12: =ModelBasis!$F$18*Retentie!$C$13 -> 23.406363 | X12: =ModelBasis!$F$18*Retentie!$C$14 -> 22.388695 | Y12: =ModelBasis!$F$18*Retentie!$C$15 -> 21.981628 | Z12: =ModelBasis!$F$18*Retentie!$C$16 -> 21.57456 | AA12: =ModelBasis!$F$18*Retentie!$C$17 -> 21.167493 | AB12: =ModelBasis!$F$18*Retentie!$C$18 -> 20.760426 | AC12: =ModelBasis!$F$18*Retentie!$C$19 -> 20.353359 | AD12: =ModelBasis!$F$18*Retentie!$C$20 -> 19.946292 | AE12: =ModelBasis!$F$18*Retentie!$C$21 -> 19.742758 | AF12: =ModelBasis!$F$18*Retentie!$C$22 -> 19.539225 | AG12: =ModelBasis!$F$18*Retentie!$C$23 -> 19.335691 | AH12: =ModelBasis!$F$18*Retentie!$C$24 -> 19.132157 | AI12: =ModelBasis!$F$18*Retentie!$C$25 -> 18.928624 | AJ12: =ModelBasis!$F$18*Retentie!$C$26 -> 18.72509 | AK12: =ModelBasis!$F$18*Retentie!$C$27 -> 18.521557
A13: 12 | M13: =ModelBasis!$F$19*Retentie!$C$2 -> 211.67493 | N13: =ModelBasis!$F$19*Retentie!$C$3 -> 84.669973 | O13: =ModelBasis!$F$19*Retentie!$C$4 -> 63.50248 | P13: =ModelBasis!$F$19*Retentie!$C$5 -> 50.801984 | Q13: =ModelBasis!$F$19*Retentie!$C$6 -> 42.334987 | R13: =ModelBasis!$F$19*Retentie!$C$7 -> 38.101488 | S13: =ModelBasis!$F$19*Retentie!$C$8 -> 33.867989 | T13: =ModelBasis!$F$19*Retentie!$C$9 -> 31.75124 | U13: =ModelBasis!$F$19*Retentie!$C$10 -> 29.634491 | V13: =ModelBasis!$F$19*Retentie!$C$11 -> 27.517741 | W13: =ModelBasis!$F$19*Retentie!$C$12 -> 25.400992 | X13: =ModelBasis!$F$19*Retentie!$C$13 -> 24.342617 | Y13: =ModelBasis!$F$19*Retentie!$C$14 -> 23.284243 | Z13: =ModelBasis!$F$19*Retentie!$C$15 -> 22.860893 | AA13: =ModelBasis!$F$19*Retentie!$C$16 -> 22.437543 | AB13: =ModelBasis!$F$19*Retentie!$C$17 -> 22.014193 | AC13: =ModelBasis!$F$19*Retentie!$C$18 -> 21.590843 | AD13: =ModelBasis!$F$19*Retentie!$C$19 -> 21.167493 | AE13: =ModelBasis!$F$19*Retentie!$C$20 -> 20.744143 | AF13: =ModelBasis!$F$19*Retentie!$C$21 -> 20.532468 | AG13: =ModelBasis!$F$19*Retentie!$C$22 -> 20.320794 | AH13: =ModelBasis!$F$19*Retentie!$C$23 -> 20.109119 | AI13: =ModelBasis!$F$19*Retentie!$C$24 -> 19.897444 | AJ13: =ModelBasis!$F$19*Retentie!$C$25 -> 19.685769 | AK13: =ModelBasis!$F$19*Retentie!$C$26 -> 19.474094
A14: 13 | N14: =ModelBasis!$F$20*Retentie!$C$2 -> 550.35483 | O14: =ModelBasis!$F$20*Retentie!$C$3 -> 220.14193 | P14: =ModelBasis!$F$20*Retentie!$C$4 -> 165.10645 | Q14: =ModelBasis!$F$20*Retentie!$C$5 -> 132.08516 | R14: =ModelBasis!$F$20*Retentie!$C$6 -> 110.07097 | S14: =ModelBasis!$F$20*Retentie!$C$7 -> 99.063869 | T14: =ModelBasis!$F$20*Retentie!$C$8 -> 88.056772 | U14: =ModelBasis!$F$20*Retentie!$C$9 -> 82.553224 | V14: =ModelBasis!$F$20*Retentie!$C$10 -> 77.049676 | W14: =ModelBasis!$F$20*Retentie!$C$11 -> 71.546127 | X14: =ModelBasis!$F$20*Retentie!$C$12 -> 66.042579 | Y14: =ModelBasis!$F$20*Retentie!$C$13 -> 63.290805 | Z14: =ModelBasis!$F$20*Retentie!$C$14 -> 60.539031 | AA14: =ModelBasis!$F$20*Retentie!$C$15 -> 59.438321 | AB14: =ModelBasis!$F$20*Retentie!$C$16 -> 58.337611 | AC14: =ModelBasis!$F$20*Retentie!$C$17 -> 57.236902 | AD14: =ModelBasis!$F$20*Retentie!$C$18 -> 56.136192 | AE14: =ModelBasis!$F$20*Retentie!$C$19 -> 55.035483 | AF14: =ModelBasis!$F$20*Retentie!$C$20 -> 53.934773 | AG14: =ModelBasis!$F$20*Retentie!$C$21 -> 53.384418 | AH14: =ModelBasis!$F$20*Retentie!$C$22 -> 52.834063 | AI14: =ModelBasis!$F$20*Retentie!$C$23 -> 52.283708 | AJ14: =ModelBasis!$F$20*Retentie!$C$24 -> 51.733354 | AK14: =ModelBasis!$F$20*Retentie!$C$25 -> 51.182999
A15: 14 | O15: =ModelBasis!$F$21*Retentie!$C$2 -> 228.94761 | P15: =ModelBasis!$F$21*Retentie!$C$3 -> 91.579043 | Q15: =ModelBasis!$F$21*Retentie!$C$4 -> 68.684282 | R15: =ModelBasis!$F$21*Retentie!$C$5 -> 54.947426 | S15: =ModelBasis!$F$21*Retentie!$C$6 -> 45.789521 | T15: =ModelBasis!$F$21*Retentie!$C$7 -> 41.210569 | U15: =ModelBasis!$F$21*Retentie!$C$8 -> 36.631617 | V15: =ModelBasis!$F$21*Retentie!$C$9 -> 34.342141 | W15: =ModelBasis!$F$21*Retentie!$C$10 -> 32.052665 | X15: =ModelBasis!$F$21*Retentie!$C$11 -> 29.763189 | Y15: =ModelBasis!$F$21*Retentie!$C$12 -> 27.473713 | Z15: =ModelBasis!$F$21*Retentie!$C$13 -> 26.328975 | AA15: =ModelBasis!$F$21*Retentie!$C$14 -> 25.184237 | AB15: =ModelBasis!$F$21*Retentie!$C$15 -> 24.726342 | AC15: =ModelBasis!$F$21*Retentie!$C$16 -> 24.268446 | AD15: =ModelBasis!$F$21*Retentie!$C$17 -> 23.810551 | AE15: =ModelBasis!$F$21*Retentie!$C$18 -> 23.352656 | AF15: =ModelBasis!$F$21*Retentie!$C$19 -> 22.894761 | AG15: =ModelBasis!$F$21*Retentie!$C$20 -> 22.436866 | AH15: =ModelBasis!$F$21*Retentie!$C$21 -> 22.207918 | AI15: =ModelBasis!$F$21*Retentie!$C$22 -> 21.97897 | AJ15: =ModelBasis!$F$21*Retentie!$C$23 -> 21.750023 | AK15: =ModelBasis!$F$21*Retentie!$C$24 -> 21.521075
A16: 15 | P16: =ModelBasis!$F$22*Retentie!$C$2 -> 238.10551 | Q16: =ModelBasis!$F$22*Retentie!$C$3 -> 95.242205 | R16: =ModelBasis!$F$22*Retentie!$C$4 -> 71.431653 | S16: =ModelBasis!$F$22*Retentie!$C$5 -> 57.145323 | T16: =ModelBasis!$F$22*Retentie!$C$6 -> 47.621102 | U16: =ModelBasis!$F$22*Retentie!$C$7 -> 42.858992 | V16: =ModelBasis!$F$22*Retentie!$C$8 -> 38.096882 | W16: =ModelBasis!$F$22*Retentie!$C$9 -> 35.715827 | X16: =ModelBasis!$F$22*Retentie!$C$10 -> 33.334772 | Y16: =ModelBasis!$F$22*Retentie!$C$11 -> 30.953717 | Z16: =ModelBasis!$F$22*Retentie!$C$12 -> 28.572661 | AA16: =ModelBasis!$F$22*Retentie!$C$13 -> 27.382134 | AB16: =ModelBasis!$F$22*Retentie!$C$14 -> 26.191606 | AC16: =ModelBasis!$F$22*Retentie!$C$15 -> 25.715395 | AD16: =ModelBasis!$F$22*Retentie!$C$16 -> 25.239184 | AE16: =ModelBasis!$F$22*Retentie!$C$17 -> 24.762973 | AF16: =ModelBasis!$F$22*Retentie!$C$18 -> 24.286762 | AG16: =ModelBasis!$F$22*Retentie!$C$19 -> 23.810551 | AH16: =ModelBasis!$F$22*Retentie!$C$20 -> 23.33434 | AI16: =ModelBasis!$F$22*Retentie!$C$21 -> 23.096235 | AJ16: =ModelBasis!$F$22*Retentie!$C$22 -> 22.858129 | AK16: =ModelBasis!$F$22*Retentie!$C$23 -> 22.620024
A17: 16 | Q17: =ModelBasis!$F$23*Retentie!$C$2 -> 247.62973 | R17: =ModelBasis!$F$23*Retentie!$C$3 -> 99.051893 | S17: =ModelBasis!$F$23*Retentie!$C$4 -> 74.28892 | T17: =ModelBasis!$F$23*Retentie!$C$5 -> 59.431136 | U17: =ModelBasis!$F$23*Retentie!$C$6 -> 49.525946 | V17: =ModelBasis!$F$23*Retentie!$C$7 -> 44.573352 | W17: =ModelBasis!$F$23*Retentie!$C$8 -> 39.620757 | X17: =ModelBasis!$F$23*Retentie!$C$9 -> 37.14446 | Y17: =ModelBasis!$F$23*Retentie!$C$10 -> 34.668162 | Z17: =ModelBasis!$F$23*Retentie!$C$11 -> 32.191865 | AA17: =ModelBasis!$F$23*Retentie!$C$12 -> 29.715568 | AB17: =ModelBasis!$F$23*Retentie!$C$13 -> 28.477419 | AC17: =ModelBasis!$F$23*Retentie!$C$14 -> 27.239271 | AD17: =ModelBasis!$F$23*Retentie!$C$15 -> 26.744011 | AE17: =ModelBasis!$F$23*Retentie!$C$16 -> 26.248752 | AF17: =ModelBasis!$F$23*Retentie!$C$17 -> 25.753492 | AG17: =ModelBasis!$F$23*Retentie!$C$18 -> 25.258233 | AH17: =ModelBasis!$F$23*Retentie!$C$19 -> 24.762973 | AI17: =ModelBasis!$F$23*Retentie!$C$20 -> 24.267714 | AJ17: =ModelBasis!$F$23*Retentie!$C$21 -> 24.020084 | AK17: =ModelBasis!$F$23*Retentie!$C$22 -> 23.772454
A18: 17 | R18: =ModelBasis!$F$24*Retentie!$C$2 -> 257.53492 | S18: =ModelBasis!$F$24*Retentie!$C$3 -> 103.01397 | T18: =ModelBasis!$F$24*Retentie!$C$4 -> 77.260476 | U18: =ModelBasis!$F$24*Retentie!$C$5 -> 61.808381 | V18: =ModelBasis!$F$24*Retentie!$C$6 -> 51.506984 | W18: =ModelBasis!$F$24*Retentie!$C$7 -> 46.356286 | X18: =ModelBasis!$F$24*Retentie!$C$8 -> 41.205587 | Y18: =ModelBasis!$F$24*Retentie!$C$9 -> 38.630238 | Z18: =ModelBasis!$F$24*Retentie!$C$10 -> 36.054889 | AA18: =ModelBasis!$F$24*Retentie!$C$11 -> 33.47954 | AB18: =ModelBasis!$F$24*Retentie!$C$12 -> 30.904191 | AC18: =ModelBasis!$F$24*Retentie!$C$13 -> 29.616516 | AD18: =ModelBasis!$F$24*Retentie!$C$14 -> 28.328841 | AE18: =ModelBasis!$F$24*Retentie!$C$15 -> 27.813771 | AF18: =ModelBasis!$F$24*Retentie!$C$16 -> 27.298702 | AG18: =ModelBasis!$F$24*Retentie!$C$17 -> 26.783632 | AH18: =ModelBasis!$F$24*Retentie!$C$18 -> 26.268562 | AI18: =ModelBasis!$F$24*Retentie!$C$19 -> 25.753492 | AJ18: =ModelBasis!$F$24*Retentie!$C$20 -> 25.238422 | AK18: =ModelBasis!$F$24*Retentie!$C$21 -> 24.980887
A19: 18 | S19: =ModelBasis!$F$25*Retentie!$C$2 -> 432.83632 | T19: =ModelBasis!$F$25*Retentie!$C$3 -> 173.13453 | U19: =ModelBasis!$F$25*Retentie!$C$4 -> 129.8509 | V19: =ModelBasis!$F$25*Retentie!$C$5 -> 103.88072 | W19: =ModelBasis!$F$25*Retentie!$C$6 -> 86.567264 | X19: =ModelBasis!$F$25*Retentie!$C$7 -> 77.910537 | Y19: =ModelBasis!$F$25*Retentie!$C$8 -> 69.253811 | Z19: =ModelBasis!$F$25*Retentie!$C$9 -> 64.925448 | AA19: =ModelBasis!$F$25*Retentie!$C$10 -> 60.597085 | AB19: =ModelBasis!$F$25*Retentie!$C$11 -> 56.268721 | AC19: =ModelBasis!$F$25*Retentie!$C$12 -> 51.940358 | AD19: =ModelBasis!$F$25*Retentie!$C$13 -> 49.776177 | AE19: =ModelBasis!$F$25*Retentie!$C$14 -> 47.611995 | AF19: =ModelBasis!$F$25*Retentie!$C$15 -> 46.746322 | AG19: =ModelBasis!$F$25*Retentie!$C$16 -> 45.88065 | AH19: =ModelBasis!$F$25*Retentie!$C$17 -> 45.014977 | AI19: =ModelBasis!$F$25*Retentie!$C$18 -> 44.149304 | AJ19: =ModelBasis!$F$25*Retentie!$C$19 -> 43.283632 | AK19: =ModelBasis!$F$25*Retentie!$C$20 -> 42.417959
A20: 19 | T20: =ModelBasis!$F$26*Retentie!$C$2 -> 450.14977 | U20: =ModelBasis!$F$26*Retentie!$C$3 -> 180.05991 | V20: =ModelBasis!$F$26*Retentie!$C$4 -> 135.04493 | W20: =ModelBasis!$F$26*Retentie!$C$5 -> 108.03595 | X20: =ModelBasis!$F$26*Retentie!$C$6 -> 90.029954 | Y20: =ModelBasis!$F$26*Retentie!$C$7 -> 81.026959 | Z20: =ModelBasis!$F$26*Retentie!$C$8 -> 72.023963 | AA20: =ModelBasis!$F$26*Retentie!$C$9 -> 67.522466 | AB20: =ModelBasis!$F$26*Retentie!$C$10 -> 63.020968 | AC20: =ModelBasis!$F$26*Retentie!$C$11 -> 58.51947 | AD20: =ModelBasis!$F$26*Retentie!$C$12 -> 54.017973 | AE20: =ModelBasis!$F$26*Retentie!$C$13 -> 51.767224 | AF20: =ModelBasis!$F$26*Retentie!$C$14 -> 49.516475 | AG20: =ModelBasis!$F$26*Retentie!$C$15 -> 48.616175 | AH20: =ModelBasis!$F$26*Retentie!$C$16 -> 47.715876 | AI20: =ModelBasis!$F$26*Retentie!$C$17 -> 46.815576 | AJ20: =ModelBasis!$F$26*Retentie!$C$18 -> 45.915277 | AK20: =ModelBasis!$F$26*Retentie!$C$19 -> 45.014977
A21: 20 | U21: =ModelBasis!$F$27*Retentie!$C$2 -> 468.15576 | V21: =ModelBasis!$F$27*Retentie!$C$3 -> 187.2623 | W21: =ModelBasis!$F$27*Retentie!$C$4 -> 140.44673 | X21: =ModelBasis!$F$27*Retentie!$C$5 -> 112.35738 | Y21: =ModelBasis!$F$27*Retentie!$C$6 -> 93.631152 | Z21: =ModelBasis!$F$27*Retentie!$C$7 -> 84.268037 | AA21: =ModelBasis!$F$27*Retentie!$C$8 -> 74.904922 | AB21: =ModelBasis!$F$27*Retentie!$C$9 -> 70.223364 | AC21: =ModelBasis!$F$27*Retentie!$C$10 -> 65.541807 | AD21: =ModelBasis!$F$27*Retentie!$C$11 -> 60.860249 | AE21: =ModelBasis!$F$27*Retentie!$C$12 -> 56.178691 | AF21: =ModelBasis!$F$27*Retentie!$C$13 -> 53.837913 | AG21: =ModelBasis!$F$27*Retentie!$C$14 -> 51.497134 | AH21: =ModelBasis!$F$27*Retentie!$C$15 -> 50.560822 | AI21: =ModelBasis!$F$27*Retentie!$C$16 -> 49.624511 | AJ21: =ModelBasis!$F$27*Retentie!$C$17 -> 48.688199 | AK21: =ModelBasis!$F$27*Retentie!$C$18 -> 47.751888
A22: 21 | V22: =ModelBasis!$F$28*Retentie!$C$2 -> 486.88199 | W22: =ModelBasis!$F$28*Retentie!$C$3 -> 194.7528 | X22: =ModelBasis!$F$28*Retentie!$C$4 -> 146.0646 | Y22: =ModelBasis!$F$28*Retentie!$C$5 -> 116.85168 | Z22: =ModelBasis!$F$28*Retentie!$C$6 -> 97.376398 | AA22: =ModelBasis!$F$28*Retentie!$C$7 -> 87.638759 | AB22: =ModelBasis!$F$28*Retentie!$C$8 -> 77.901119 | AC22: =ModelBasis!$F$28*Retentie!$C$9 -> 73.032299 | AD22: =ModelBasis!$F$28*Retentie!$C$10 -> 68.163479 | AE22: =ModelBasis!$F$28*Retentie!$C$11 -> 63.294659 | AF22: =ModelBasis!$F$28*Retentie!$C$12 -> 58.425839 | AG22: =ModelBasis!$F$28*Retentie!$C$13 -> 55.991429 | AH22: =ModelBasis!$F$28*Retentie!$C$14 -> 53.557019 | AI22: =ModelBasis!$F$28*Retentie!$C$15 -> 52.583255 | AJ22: =ModelBasis!$F$28*Retentie!$C$16 -> 51.609491 | AK22: =ModelBasis!$F$28*Retentie!$C$17 -> 50.635727
A23: 22 | W23: =ModelBasis!$F$29*Retentie!$C$2 -> 506.35727 | X23: =ModelBasis!$F$29*Retentie!$C$3 -> 202.54291 | Y23: =ModelBasis!$F$29*Retentie!$C$4 -> 151.90718 | Z23: =ModelBasis!$F$29*Retentie!$C$5 -> 121.52575 | AA23: =ModelBasis!$F$29*Retentie!$C$6 -> 101.27145 | AB23: =ModelBasis!$F$29*Retentie!$C$7 -> 91.144309 | AC23: =ModelBasis!$F$29*Retentie!$C$8 -> 81.017163 | AD23: =ModelBasis!$F$29*Retentie!$C$9 -> 75.953591 | AE23: =ModelBasis!$F$29*Retentie!$C$10 -> 70.890018 | AF23: =ModelBasis!$F$29*Retentie!$C$11 -> 65.826445 | AG23: =ModelBasis!$F$29*Retentie!$C$12 -> 60.762873 | AH23: =ModelBasis!$F$29*Retentie!$C$13 -> 58.231086 | AI23: =ModelBasis!$F$29*Retentie!$C$14 -> 55.6993 | AJ23: =ModelBasis!$F$29*Retentie!$C$15 -> 54.686585 | AK23: =ModelBasis!$F$29*Retentie!$C$16 -> 53.673871
A24: 23 | X24: =ModelBasis!$F$30*Retentie!$C$2 -> 526.61156 | Y24: =ModelBasis!$F$30*Retentie!$C$3 -> 210.64463 | Z24: =ModelBasis!$F$30*Retentie!$C$4 -> 157.98347 | AA24: =ModelBasis!$F$30*Retentie!$C$5 -> 126.38678 | AB24: =ModelBasis!$F$30*Retentie!$C$6 -> 105.32231 | AC24: =ModelBasis!$F$30*Retentie!$C$7 -> 94.790081 | AD24: =ModelBasis!$F$30*Retentie!$C$8 -> 84.25785 | AE24: =ModelBasis!$F$30*Retentie!$C$9 -> 78.991734 | AF24: =ModelBasis!$F$30*Retentie!$C$10 -> 73.725619 | AG24: =ModelBasis!$F$30*Retentie!$C$11 -> 68.459503 | AH24: =ModelBasis!$F$30*Retentie!$C$12 -> 63.193388 | AI24: =ModelBasis!$F$30*Retentie!$C$13 -> 60.56033 | AJ24: =ModelBasis!$F$30*Retentie!$C$14 -> 57.927272 | AK24: =ModelBasis!$F$30*Retentie!$C$15 -> 56.874049
A25: 24 | Y25: =ModelBasis!$F$31*Retentie!$C$2 -> 547.67603 | Z25: =ModelBasis!$F$31*Retentie!$C$3 -> 219.07041 | AA25: =ModelBasis!$F$31*Retentie!$C$4 -> 164.30281 | AB25: =ModelBasis!$F$31*Retentie!$C$5 -> 131.44225 | AC25: =ModelBasis!$F$31*Retentie!$C$6 -> 109.53521 | AD25: =ModelBasis!$F$31*Retentie!$C$7 -> 98.581685 | AE25: =ModelBasis!$F$31*Retentie!$C$8 -> 87.628164 | AF25: =ModelBasis!$F$31*Retentie!$C$9 -> 82.151404 | AG25: =ModelBasis!$F$31*Retentie!$C$10 -> 76.674644 | AH25: =ModelBasis!$F$31*Retentie!$C$11 -> 71.197883 | AI25: =ModelBasis!$F$31*Retentie!$C$12 -> 65.721123 | AJ25: =ModelBasis!$F$31*Retentie!$C$13 -> 62.982743 | AK25: =ModelBasis!$F$31*Retentie!$C$14 -> 60.244363
A26: 25 | Z26: =ModelBasis!$F$32*Retentie!$C$2 -> 1098.2646 | AA26: =ModelBasis!$F$32*Retentie!$C$3 -> 439.30582 | AB26: =ModelBasis!$F$32*Retentie!$C$4 -> 329.47937 | AC26: =ModelBasis!$F$32*Retentie!$C$5 -> 263.58349 | AD26: =ModelBasis!$F$32*Retentie!$C$6 -> 219.65291 | AE26: =ModelBasis!$F$32*Retentie!$C$7 -> 197.68762 | AF26: =ModelBasis!$F$32*Retentie!$C$8 -> 175.72233 | AG26: =ModelBasis!$F$32*Retentie!$C$9 -> 164.73968 | AH26: =ModelBasis!$F$32*Retentie!$C$10 -> 153.75704 | AI26: =ModelBasis!$F$32*Retentie!$C$11 -> 142.77439 | AJ26: =ModelBasis!$F$32*Retentie!$C$12 -> 131.79175 | AK26: =ModelBasis!$F$32*Retentie!$C$13 -> 126.30042
A27: 26 | AA27: =ModelBasis!$F$33*Retentie!$C$2 -> 592.36639 | AB27: =ModelBasis!$F$33*Retentie!$C$3 -> 236.94656 | AC27: =ModelBasis!$F$33*Retentie!$C$4 -> 177.70992 | AD27: =ModelBasis!$F$33*Retentie!$C$5 -> 142.16793 | AE27: =ModelBasis!$F$33*Retentie!$C$6 -> 118.47328 | AF27: =ModelBasis!$F$33*Retentie!$C$7 -> 106.62595 | AG27: =ModelBasis!$F$33*Retentie!$C$8 -> 94.778622 | AH27: =ModelBasis!$F$33*Retentie!$C$9 -> 88.854958 | AI27: =ModelBasis!$F$33*Retentie!$C$10 -> 82.931294 | AJ27: =ModelBasis!$F$33*Retentie!$C$11 -> 77.007631 | AK27: =ModelBasis!$F$33*Retentie!$C$12 -> 71.083967
A28: 27 | AB28: =ModelBasis!$F$34*Retentie!$C$2 -> 616.06104 | AC28: =ModelBasis!$F$34*Retentie!$C$3 -> 246.42442 | AD28: =ModelBasis!$F$34*Retentie!$C$4 -> 184.81831 | AE28: =ModelBasis!$F$34*Retentie!$C$5 -> 147.85465 | AF28: =ModelBasis!$F$34*Retentie!$C$6 -> 123.21221 | AG28: =ModelBasis!$F$34*Retentie!$C$7 -> 110.89099 | AH28: =ModelBasis!$F$34*Retentie!$C$8 -> 98.569767 | AI28: =ModelBasis!$F$34*Retentie!$C$9 -> 92.409157 | AJ28: =ModelBasis!$F$34*Retentie!$C$10 -> 86.248546 | AK28: =ModelBasis!$F$34*Retentie!$C$11 -> 80.087936
A29: 28 | AC29: =ModelBasis!$F$35*Retentie!$C$2 -> 640.70349 | AD29: =ModelBasis!$F$35*Retentie!$C$3 -> 256.28139 | AE29: =ModelBasis!$F$35*Retentie!$C$4 -> 192.21105 | AF29: =ModelBasis!$F$35*Retentie!$C$5 -> 153.76884 | AG29: =ModelBasis!$F$35*Retentie!$C$6 -> 128.1407 | AH29: =ModelBasis!$F$35*Retentie!$C$7 -> 115.32663 | AI29: =ModelBasis!$F$35*Retentie!$C$8 -> 102.51256 | AJ29: =ModelBasis!$F$35*Retentie!$C$9 -> 96.105523 | AK29: =ModelBasis!$F$35*Retentie!$C$10 -> 89.698488
A30: 29 | AD30: =ModelBasis!$F$36*Retentie!$C$2 -> 666.33163 | AE30: =ModelBasis!$F$36*Retentie!$C$3 -> 266.53265 | AF30: =ModelBasis!$F$36*Retentie!$C$4 -> 199.89949 | AG30: =ModelBasis!$F$36*Retentie!$C$5 -> 159.91959 | AH30: =ModelBasis!$F$36*Retentie!$C$6 -> 133.26633 | AI30: =ModelBasis!$F$36*Retentie!$C$7 -> 119.93969 | AJ30: =ModelBasis!$F$36*Retentie!$C$8 -> 106.61306 | AK30: =ModelBasis!$F$36*Retentie!$C$9 -> 99.949744
A31: 30 | AE31: =ModelBasis!$F$37*Retentie!$C$2 -> 692.98489 | AF31: =ModelBasis!$F$37*Retentie!$C$3 -> 277.19396 | AG31: =ModelBasis!$F$37*Retentie!$C$4 -> 207.89547 | AH31: =ModelBasis!$F$37*Retentie!$C$5 -> 166.31637 | AI31: =ModelBasis!$F$37*Retentie!$C$6 -> 138.59698 | AJ31: =ModelBasis!$F$37*Retentie!$C$7 -> 124.73728 | AK31: =ModelBasis!$F$37*Retentie!$C$8 -> 110.87758
A32: 31 | AF32: =ModelBasis!$F$38*Retentie!$C$2 -> 720.70429 | AG32: =ModelBasis!$F$38*Retentie!$C$3 -> 288.28171 | AH32: =ModelBasis!$F$38*Retentie!$C$4 -> 216.21129 | AI32: =ModelBasis!$F$38*Retentie!$C$5 -> 172.96903 | AJ32: =ModelBasis!$F$38*Retentie!$C$6 -> 144.14086 | AK32: =ModelBasis!$F$38*Retentie!$C$7 -> 129.72677
A33: 32 | AG33: =ModelBasis!$F$39*Retentie!$C$2 -> 749.53246 | AH33: =ModelBasis!$F$39*Retentie!$C$3 -> 299.81298 | AI33: =ModelBasis!$F$39*Retentie!$C$4 -> 224.85974 | AJ33: =ModelBasis!$F$39*Retentie!$C$5 -> 179.88779 | AK33: =ModelBasis!$F$39*Retentie!$C$6 -> 149.90649
A34: 33 | AH34: =ModelBasis!$F$40*Retentie!$C$2 -> 779.51376 | AI34: =ModelBasis!$F$40*Retentie!$C$3 -> 311.8055 | AJ34: =ModelBasis!$F$40*Retentie!$C$4 -> 233.85413 | AK34: =ModelBasis!$F$40*Retentie!$C$5 -> 187.0833
A35: 34 | AI35: =ModelBasis!$F$41*Retentie!$C$2 -> 810.69431 | AJ35: =ModelBasis!$F$41*Retentie!$C$3 -> 324.27772 | AK35: =ModelBasis!$F$41*Retentie!$C$4 -> 243.20829
A36: 35 | AJ36: =ModelBasis!$F$42*Retentie!$C$2 -> 843.12208 | AK36: =ModelBasis!$F$42*Retentie!$C$3 -> 337.24883
A37: 36 | AK37: =ModelBasis!$F$43*Retentie!$C$2 -> 876.84696
A38: MAU | B38: =SUM(B2:B37) -> 495 | C38: =SUM(C2:C37) -> 341 | D38: =SUM(D2:D37) -> 354.42 | E38: =SUM(E2:E37) -> 375.8568 | F38: =SUM(F2:F37) -> 400.65907 | G38: =SUM(G2:G37) -> 431.42543 | H38: =SUM(H2:H37) -> 460.95845 | I38: =SUM(I2:I37) -> 494.15879 | ... AK38: =SUM(AK2:AK37) -> 3211.3418

Sheet ModelBull
A1: ART EYE — scenario BULL (A$, M1 = sep 2026)
A2: Alle regels zijn formules op blad Aannames + Retentie. Niets hier hard aanpassen.
A7: Mnd | B7: Kalender | C7: Downloads Sydney | D7: Downloads stad 2+ | E7: Downloads totaal | F7: Nieuwe actieven | G7: MAU (cohort) | H7: Premium-abonnees | I7: Consumer-omzet netto | J7: Betalende venues | K7: Venue-MRR | L7: Fair/partnership | M7: Totale omzet | N7: Infra | O7: AI-pipeline | P7: Tools | Q7: Apple | R7: Marketing | S7: Eenmalig | T7: Totale kosten | U7: Netto cashflow | V7: Cumulatief
A8: 1 | B8: sep-26 | C8: =Aannames!$D$4 -> 1500 | D8: =IF(A8>=Aannames!$D$24,Aannames!$D$26*(1+Aannames!$D$6)^(A8-Aannames!$D$24),0) -> 0 | E8: =C8+D8 -> 1500 | F8: =E8*Aannames!$D$8 -> 930 | G8: =CohortBull!B$38 -> 930 | H8: =G8*Aannames!$D$9 -> 37.2 | I8: =H8*Aannames!$D$10*(1-Aannames!$D$11) -> 189.4038 | J8: =MIN(IF(A8>=Aannames!$D$14,Aannames!$D$15*Aannames!$D$16,0),(Aannames!$D$19+IF(A8>=Aannames!$D$24,Aannames!$D$25,0))*Aannames!$D$20) -> 0 | K8: =J8*Aannames!$D$17 -> 0 | L8: =IF(AND(A8>12,MOD(A8-1,12)=0),Aannames!$D$37,0) -> 0 | M8: =I8+K8+L8 -> 189.4038 | N8: =Aannames!$D$28+G8*Aannames!$D$29 -> 78.6 | O8: =Aannames!$D$30*(1+IF(A8>=Aannames!$D$24,1,0)) -> 80 | P8: =Aannames!$D$31 -> 70 | Q8: =IF(MOD(A8-1,12)=0,Aannames!$D$32,0) -> 150 | R8: =Aannames!$D$33+IF(MOD(A8-1,12)=0,Aannames!$D$34,0) -> 1800 | S8: =IF(A8=1,Aannames!$D$35,0) -> 400 | T8: =SUM(N8:S8) -> 2578.6 | U8: =M8-T8 -> -2389.1962 | V8: =U8 -> -2389.1962
A9: 2 | B9: okt-26 | C9: =Aannames!$D$5*(1+Aannames!$D$6)^(A9-2)*(1+IF(MOD(A9-1,12)=0,Aannames!$D$7,0)) -> 400 | D9: =IF(A9>=Aannames!$D$24,Aannames!$D$26*(1+Aannames!$D$6)^(A9-Aannames!$D$24),0) -> 0 | E9: =C9+D9 -> 400 | F9: =E9*Aannames!$D$8 -> 248 | G9: =CohortBull!C$38 -> 731.6 | H9: =G9*Aannames!$D$9 -> 29.264 | I9: =H9*Aannames!$D$10*(1-Aannames!$D$11) -> 148.99766 | J9: =MIN(J8*(1-Aannames!$D$18)+IF(A9>=Aannames!$D$14,Aannames!$D$15*Aannames!$D$16,0),(Aannames!$D$19+IF(A9>=Aannames!$D$24,Aannames!$D$25,0))*Aannames!$D$20) -> 0 | K9: =J9*Aannames!$D$17 -> 0 | L9: =IF(AND(A9>12,MOD(A9-1,12)=0),Aannames!$D$37,0) -> 0 | M9: =I9+K9+L9 -> 148.99766 | N9: =Aannames!$D$28+G9*Aannames!$D$29 -> 74.632 | O9: =Aannames!$D$30*(1+IF(A9>=Aannames!$D$24,1,0)) -> 80 | P9: =Aannames!$D$31 -> 70 | Q9: =IF(MOD(A9-1,12)=0,Aannames!$D$32,0) -> 0 | R9: =Aannames!$D$33+IF(MOD(A9-1,12)=0,Aannames!$D$34,0) -> 300 | S9: =IF(A9=1,Aannames!$D$35,0) -> 0 | T9: =SUM(N9:S9) -> 524.632 | U9: =M9-T9 -> -375.63434 | V9: =V8+U9 -> -2764.8305
A10: 3 | B10: nov-26 | C10: =Aannames!$D$5*(1+Aannames!$D$6)^(A10-2)*(1+IF(MOD(A10-1,12)=0,Aannames!$D$7,0)) -> 424 | D10: =IF(A10>=Aannames!$D$24,Aannames!$D$26*(1+Aannames!$D$6)^(A10-Aannames!$D$24),0) -> 0 | E10: =C10+D10 -> 424 | F10: =E10*Aannames!$D$8 -> 262.88 | G10: =CohortBull!D$38 -> 782.44 | H10: =G10*Aannames!$D$9 -> 31.2976 | I10: =H10*Aannames!$D$10*(1-Aannames!$D$11) -> 159.35173 | J10: =MIN(J9*(1-Aannames!$D$18)+IF(A10>=Aannames!$D$14,Aannames!$D$15*Aannames!$D$16,0),(Aannames!$D$19+IF(A10>=Aannames!$D$24,Aannames!$D$25,0))*Aannames!$D$20) -> 0 | K10: =J10*Aannames!$D$17 -> 0 | L10: =IF(AND(A10>12,MOD(A10-1,12)=0),Aannames!$D$37,0) -> 0 | M10: =I10+K10+L10 -> 159.35173 | N10: =Aannames!$D$28+G10*Aannames!$D$29 -> 75.6488 | O10: =Aannames!$D$30*(1+IF(A10>=Aannames!$D$24,1,0)) -> 80 | P10: =Aannames!$D$31 -> 70 | Q10: =IF(MOD(A10-1,12)=0,Aannames!$D$32,0) -> 0 | R10: =Aannames!$D$33+IF(MOD(A10-1,12)=0,Aannames!$D$34,0) -> 300 | S10: =IF(A10=1,Aannames!$D$35,0) -> 0 | T10: =SUM(N10:S10) -> 525.6488 | U10: =M10-T10 -> -366.29707 | V10: =V9+U10 -> -3131.1276
A11: 4 | B11: dec-26 | C11: =Aannames!$D$5*(1+Aannames!$D$6)^(A11-2)*(1+IF(MOD(A11-1,12)=0,Aannames!$D$7,0)) -> 449.44 | D11: =IF(A11>=Aannames!$D$24,Aannames!$D$26*(1+Aannames!$D$6)^(A11-Aannames!$D$24),0) -> 0 | E11: =C11+D11 -> 449.44 | F11: =E11*Aannames!$D$8 -> 278.6528 | G11: =CohortBull!E$38 -> 845.0104 | H11: =G11*Aannames!$D$9 -> 33.800416 | I11: =H11*Aannames!$D$10*(1-Aannames!$D$11) -> 172.09482 | J11: =MIN(J10*(1-Aannames!$D$18)+IF(A11>=Aannames!$D$14,Aannames!$D$15*Aannames!$D$16,0),(Aannames!$D$19+IF(A11>=Aannames!$D$24,Aannames!$D$25,0))*Aannames!$D$20) -> 0 | K11: =J11*Aannames!$D$17 -> 0 | L11: =IF(AND(A11>12,MOD(A11-1,12)=0),Aannames!$D$37,0) -> 0 | M11: =I11+K11+L11 -> 172.09482 | N11: =Aannames!$D$28+G11*Aannames!$D$29 -> 76.900208 | O11: =Aannames!$D$30*(1+IF(A11>=Aannames!$D$24,1,0)) -> 80 | P11: =Aannames!$D$31 -> 70 | Q11: =IF(MOD(A11-1,12)=0,Aannames!$D$32,0) -> 0 | R11: =Aannames!$D$33+IF(MOD(A11-1,12)=0,Aannames!$D$34,0) -> 300 | S11: =IF(A11=1,Aannames!$D$35,0) -> 0 | T11: =SUM(N11:S11) -> 526.90021 | U11: =M11-T11 -> -354.80539 | V11: =V10+U11 -> -3485.933
A12: 5 | B12: jan-27 | C12: =Aannames!$D$5*(1+Aannames!$D$6)^(A12-2)*(1+IF(MOD(A12-1,12)=0,Aannames!$D$7,0)) -> 476.4064 | D12: =IF(A12>=Aannames!$D$24,Aannames!$D$26*(1+Aannames!$D$6)^(A12-Aannames!$D$24),0) -> 0 | E12: =C12+D12 -> 476.4064 | F12: =E12*Aannames!$D$8 -> 295.37197 | G12: =CohortBull!F$38 -> 925.78102 | H12: =G12*Aannames!$D$9 -> 37.031241 | I12: =H12*Aannames!$D$10*(1-Aannames!$D$11) -> 188.54456 | J12: =MIN(J11*(1-Aannames!$D$18)+IF(A12>=Aannames!$D$14,Aannames!$D$15*Aannames!$D$16,0),(Aannames!$D$19+IF(A12>=Aannames!$D$24,Aannames!$D$25,0))*Aannames!$D$20) -> 0 | K12: =J12*Aannames!$D$17 -> 0 | L12: =IF(AND(A12>12,MOD(A12-1,12)=0),Aannames!$D$37,0) -> 0 | M12: =I12+K12+L12 -> 188.54456 | N12: =Aannames!$D$28+G12*Aannames!$D$29 -> 78.51562 | O12: =Aannames!$D$30*(1+IF(A12>=Aannames!$D$24,1,0)) -> 80 | P12: =Aannames!$D$31 -> 70 | Q12: =IF(MOD(A12-1,12)=0,Aannames!$D$32,0) -> 0 | R12: =Aannames!$D$33+IF(MOD(A12-1,12)=0,Aannames!$D$34,0) -> 300 | S12: =IF(A12=1,Aannames!$D$35,0) -> 0 | T12: =SUM(N12:S12) -> 528.51562 | U12: =M12-T12 -> -339.97106 | V12: =V11+U12 -> -3825.9041
A13: 6 | B13: feb-27 | C13: =Aannames!$D$5*(1+Aannames!$D$6)^(A13-2)*(1+IF(MOD(A13-1,12)=0,Aannames!$D$7,0)) -> 504.99078 | D13: =IF(A13>=Aannames!$D$24,Aannames!$D$26*(1+Aannames!$D$6)^(A13-Aannames!$D$24),0) -> 0 | E13: =C13+D13 -> 504.99078 | F13: =E13*Aannames!$D$8 -> 313.09429 | G13: =CohortBull!G$38 -> 1013.0099 | H13: =G13*Aannames!$D$9 -> 40.520395 | I13: =H13*Aannames!$D$10*(1-Aannames!$D$11) -> 206.30959 | J13: =MIN(J12*(1-Aannames!$D$18)+IF(A13>=Aannames!$D$14,Aannames!$D$15*Aannames!$D$16,0),(Aannames!$D$19+IF(A13>=Aannames!$D$24,Aannames!$D$25,0))*Aannames!$D$20) -> 4.5 | K13: =J13*Aannames!$D$17 -> 247.5 | L13: =IF(AND(A13>12,MOD(A13-1,12)=0),Aannames!$D$37,0) -> 0 | M13: =I13+K13+L13 -> 453.80959 | N13: =Aannames!$D$28+G13*Aannames!$D$29 -> 80.260198 | O13: =Aannames!$D$30*(1+IF(A13>=Aannames!$D$24,1,0)) -> 80 | P13: =Aannames!$D$31 -> 70 | Q13: =IF(MOD(A13-1,12)=0,Aannames!$D$32,0) -> 0 | R13: =Aannames!$D$33+IF(MOD(A13-1,12)=0,Aannames!$D$34,0) -> 300 | S13: =IF(A13=1,Aannames!$D$35,0) -> 0 | T13: =SUM(N13:S13) -> 530.2602 | U13: =M13-T13 -> -76.450604 | V13: =V12+U13 -> -3902.3547
A14: 7 | B14: mrt-27 | C14: =Aannames!$D$5*(1+Aannames!$D$6)^(A14-2)*(1+IF(MOD(A14-1,12)=0,Aannames!$D$7,0)) -> 535.29023 | D14: =IF(A14>=Aannames!$D$24,Aannames!$D$26*(1+Aannames!$D$6)^(A14-Aannames!$D$24),0) -> 0 | E14: =C14+D14 -> 535.29023 | F14: =E14*Aannames!$D$8 -> 331.87994 | G14: =CohortBull!H$38 -> 1109.0065 | H14: =G14*Aannames!$D$9 -> 44.360259 | I14: =H14*Aannames!$D$10*(1-Aannames!$D$11) -> 225.86026 | J14: =MIN(J13*(1-Aannames!$D$18)+IF(A14>=Aannames!$D$14,Aannames!$D$15*Aannames!$D$16,0),(Aannames!$D$19+IF(A14>=Aannames!$D$24,Aannames!$D$25,0))*Aannames!$D$20) -> 8.9325 | K14: =J14*Aannames!$D$17 -> 491.2875 | L14: =IF(AND(A14>12,MOD(A14-1,12)=0),Aannames!$D$37,0) -> 0 | M14: =I14+K14+L14 -> 717.14776 | N14: =Aannames!$D$28+G14*Aannames!$D$29 -> 82.18013 | O14: =Aannames!$D$30*(1+IF(A14>=Aannames!$D$24,1,0)) -> 80 | P14: =Aannames!$D$31 -> 70 | Q14: =IF(MOD(A14-1,12)=0,Aannames!$D$32,0) -> 0 | R14: =Aannames!$D$33+IF(MOD(A14-1,12)=0,Aannames!$D$34,0) -> 300 | S14: =IF(A14=1,Aannames!$D$35,0) -> 0 | T14: =SUM(N14:S14) -> 532.18013 | U14: =M14-T14 -> 184.96763 | V14: =V13+U14 -> -3717.387
A15: 8 | B15: apr-27 | C15: =Aannames!$D$5*(1+Aannames!$D$6)^(A15-2)*(1+IF(MOD(A15-1,12)=0,Aannames!$D$7,0)) -> 567.40764 | D15: =IF(A15>=Aannames!$D$24,Aannames!$D$26*(1+Aannames!$D$6)^(A15-Aannames!$D$24),0) -> 0 | E15: =C15+D15 -> 567.40764 | F15: =E15*Aannames!$D$8 -> 351.79274 | G15: =CohortBull!I$38 -> 1211.5689 | H15: =G15*Aannames!$D$9 -> 48.462755 | I15: =H15*Aannames!$D$10*(1-Aannames!$D$11) -> 246.74812 | J15: =MIN(J14*(1-Aannames!$D$18)+IF(A15>=Aannames!$D$14,Aannames!$D$15*Aannames!$D$16,0),(Aannames!$D$19+IF(A15>=Aannames!$D$24,Aannames!$D$25,0))*Aannames!$D$20) -> 13.298512 | K15: =J15*Aannames!$D$17 -> 731.41819 | L15: =IF(AND(A15>12,MOD(A15-1,12)=0),Aannames!$D$37,0) -> 0 | M15: =I15+K15+L15 -> 978.1663 | N15: =Aannames!$D$28+G15*Aannames!$D$29 -> 84.231377 | O15: =Aannames!$D$30*(1+IF(A15>=Aannames!$D$24,1,0)) -> 80 | P15: =Aannames!$D$31 -> 70 | Q15: =IF(MOD(A15-1,12)=0,Aannames!$D$32,0) -> 0 | R15: =Aannames!$D$33+IF(MOD(A15-1,12)=0,Aannames!$D$34,0) -> 300 | S15: =IF(A15=1,Aannames!$D$35,0) -> 0 | T15: =SUM(N15:S15) -> 534.23138 | U15: =M15-T15 -> 443.93493 | V15: =V14+U15 -> -3273.4521
A16: 9 | B16: mei-27 | C16: =Aannames!$D$5*(1+Aannames!$D$6)^(A16-2)*(1+IF(MOD(A16-1,12)=0,Aannames!$D$7,0)) -> 601.4521 | D16: =IF(A16>=Aannames!$D$24,Aannames!$D$26*(1+Aannames!$D$6)^(A16-Aannames!$D$24),0) -> 0 | E16: =C16+D16 -> 601.4521 | F16: =E16*Aannames!$D$8 -> 372.9003 | G16: =CohortBull!J$38 -> 1322.052 | H16: =G16*Aannames!$D$9 -> 52.88208 | I16: =H16*Aannames!$D$10*(1-Aannames!$D$11) -> 269.24911 | J16: =MIN(J15*(1-Aannames!$D$18)+IF(A16>=Aannames!$D$14,Aannames!$D$15*Aannames!$D$16,0),(Aannames!$D$19+IF(A16>=Aannames!$D$24,Aannames!$D$25,0))*Aannames!$D$20) -> 17.599035 | K16: =J16*Aannames!$D$17 -> 967.94691 | L16: =IF(AND(A16>12,MOD(A16-1,12)=0),Aannames!$D$37,0) -> 0 | M16: =I16+K16+L16 -> 1237.196 | N16: =Aannames!$D$28+G16*Aannames!$D$29 -> 86.44104 | O16: =Aannames!$D$30*(1+IF(A16>=Aannames!$D$24,1,0)) -> 80 | P16: =Aannames!$D$31 -> 70 | Q16: =IF(MOD(A16-1,12)=0,Aannames!$D$32,0) -> 0 | R16: =Aannames!$D$33+IF(MOD(A16-1,12)=0,Aannames!$D$34,0) -> 300 | S16: =IF(A16=1,Aannames!$D$35,0) -> 0 | T16: =SUM(N16:S16) -> 536.44104 | U16: =M16-T16 -> 700.75498 | V16: =V15+U16 -> -2572.6971
A17: 10 | B17: jun-27 | C17: =Aannames!$D$5*(1+Aannames!$D$6)^(A17-2)*(1+IF(MOD(A17-1,12)=0,Aannames!$D$7,0)) -> 637.53923 | D17: =IF(A17>=Aannames!$D$24,Aannames!$D$26*(1+Aannames!$D$6)^(A17-Aannames!$D$24),0) -> 0 | E17: =C17+D17 -> 637.53923 | F17: =E17*Aannames!$D$8 -> 395.27432 | G17: =CohortBull!K$38 -> 1437.2421 | H17: =G17*Aannames!$D$9 -> 57.489685 | I17: =H17*Aannames!$D$10*(1-Aannames!$D$11) -> 292.70873 | J17: =MIN(J16*(1-Aannames!$D$18)+IF(A17>=Aannames!$D$14,Aannames!$D$15*Aannames!$D$16,0),(Aannames!$D$19+IF(A17>=Aannames!$D$24,Aannames!$D$25,0))*Aannames!$D$20) -> 21.835049 | K17: =J17*Aannames!$D$17 -> 1200.9277 | L17: =IF(AND(A17>12,MOD(A17-1,12)=0),Aannames!$D$37,0) -> 0 | M17: =I17+K17+L17 -> 1493.6364 | N17: =Aannames!$D$28+G17*Aannames!$D$29 -> 88.744842 | O17: =Aannames!$D$30*(1+IF(A17>=Aannames!$D$24,1,0)) -> 80 | P17: =Aannames!$D$31 -> 70 | Q17: =IF(MOD(A17-1,12)=0,Aannames!$D$32,0) -> 0 | R17: =Aannames!$D$33+IF(MOD(A17-1,12)=0,Aannames!$D$34,0) -> 300 | S17: =IF(A17=1,Aannames!$D$35,0) -> 0 | T17: =SUM(N17:S17) -> 538.74484 | U17: =M17-T17 -> 954.8916 | V17: =V16+U17 -> -1617.8055
A18: 11 | B18: jul-27 | C18: =Aannames!$D$5*(1+Aannames!$D$6)^(A18-2)*(1+IF(MOD(A18-1,12)=0,Aannames!$D$7,0)) -> 675.79158 | D18: =IF(A18>=Aannames!$D$24,Aannames!$D$26*(1+Aannames!$D$6)^(A18-Aannames!$D$24),0) -> 0 | E18: =C18+D18 -> 675.79158 | F18: =E18*Aannames!$D$8 -> 418.99078 | G18: =CohortBull!L$38 -> 1557.4216 | H18: =G18*Aannames!$D$9 -> 62.296866 | I18: =H18*Aannames!$D$10*(1-Aannames!$D$11) -> 317.18449 | J18: =MIN(J17*(1-Aannames!$D$18)+IF(A18>=Aannames!$D$14,Aannames!$D$15*Aannames!$D$16,0),(Aannames!$D$19+IF(A18>=Aannames!$D$24,Aannames!$D$25,0))*Aannames!$D$20) -> 26.007524 | K18: =J18*Aannames!$D$17 -> 1430.4138 | L18: =IF(AND(A18>12,MOD(A18-1,12)=0),Aannames!$D$37,0) -> 0 | M18: =I18+K18+L18 -> 1747.5983 | N18: =Aannames!$D$28+G18*Aannames!$D$29 -> 91.148433 | O18: =Aannames!$D$30*(1+IF(A18>=Aannames!$D$24,1,0)) -> 80 | P18: =Aannames!$D$31 -> 70 | Q18: =IF(MOD(A18-1,12)=0,Aannames!$D$32,0) -> 0 | R18: =Aannames!$D$33+IF(MOD(A18-1,12)=0,Aannames!$D$34,0) -> 300 | S18: =IF(A18=1,Aannames!$D$35,0) -> 0 | T18: =SUM(N18:S18) -> 541.14843 | U18: =M18-T18 -> 1206.4499 | V18: =V17+U18 -> -411.35567
A19: 12 | B19: aug-27 | C19: =Aannames!$D$5*(1+Aannames!$D$6)^(A19-2)*(1+IF(MOD(A19-1,12)=0,Aannames!$D$7,0)) -> 716.33908 | D19: =IF(A19>=Aannames!$D$24,Aannames!$D$26*(1+Aannames!$D$6)^(A19-Aannames!$D$24),0) -> 0 | E19: =C19+D19 -> 716.33908 | F19: =E19*Aannames!$D$8 -> 444.13023 | G19: =CohortBull!M$38 -> 1687.5399 | H19: =G19*Aannames!$D$9 -> 67.501598 | I19: =H19*Aannames!$D$10*(1-Aannames!$D$11) -> 343.68439 | J19: =MIN(J18*(1-Aannames!$D$18)+IF(A19>=Aannames!$D$14,Aannames!$D$15*Aannames!$D$16,0),(Aannames!$D$19+IF(A19>=Aannames!$D$24,Aannames!$D$25,0))*Aannames!$D$20) -> 30.117411 | K19: =J19*Aannames!$D$17 -> 1656.4576 | L19: =IF(AND(A19>12,MOD(A19-1,12)=0),Aannames!$D$37,0) -> 0 | M19: =I19+K19+L19 -> 2000.142 | N19: =Aannames!$D$28+G19*Aannames!$D$29 -> 93.750799 | O19: =Aannames!$D$30*(1+IF(A19>=Aannames!$D$24,1,0)) -> 80 | P19: =Aannames!$D$31 -> 70 | Q19: =IF(MOD(A19-1,12)=0,Aannames!$D$32,0) -> 0 | R19: =Aannames!$D$33+IF(MOD(A19-1,12)=0,Aannames!$D$34,0) -> 300 | S19: =IF(A19=1,Aannames!$D$35,0) -> 0 | T19: =SUM(N19:S19) -> 543.7508 | U19: =M19-T19 -> 1456.3912 | V19: =V18+U19 -> 1045.0355
A20: 13 | B20: sep-27 | C20: =Aannames!$D$5*(1+Aannames!$D$6)^(A20-2)*(1+IF(MOD(A20-1,12)=0,Aannames!$D$7,0)) -> 2657.618 | D20: =IF(A20>=Aannames!$D$24,Aannames!$D$26*(1+Aannames!$D$6)^(A20-Aannames!$D$24),0) -> 500 | E20: =C20+D20 -> 3157.618 | F20: =E20*Aannames!$D$8 -> 1957.7231 | G20: =CohortBull!N$38 -> 3311.4494 | H20: =G20*Aannames!$D$9 -> 132.45798 | I20: =H20*Aannames!$D$10*(1-Aannames!$D$11) -> 674.40979 | J20: =MIN(J19*(1-Aannames!$D$18)+IF(A20>=Aannames!$D$14,Aannames!$D$15*Aannames!$D$16,0),(Aannames!$D$19+IF(A20>=Aannames!$D$24,Aannames!$D$25,0))*Aannames!$D$20) -> 34.16565 | K20: =J20*Aannames!$D$17 -> 1879.1107 | L20: =IF(AND(A20>12,MOD(A20-1,12)=0),Aannames!$D$37,0) -> 10000 | M20: =I20+K20+L20 -> 12553.521 | N20: =Aannames!$D$28+G20*Aannames!$D$29 -> 126.22899 | O20: =Aannames!$D$30*(1+IF(A20>=Aannames!$D$24,1,0)) -> 160 | P20: =Aannames!$D$31 -> 70 | Q20: =IF(MOD(A20-1,12)=0,Aannames!$D$32,0) -> 150 | R20: =Aannames!$D$33+IF(MOD(A20-1,12)=0,Aannames!$D$34,0) -> 1800 | S20: =IF(A20=1,Aannames!$D$35,0) -> 0 | T20: =SUM(N20:S20) -> 2306.229 | U20: =M20-T20 -> 10247.292 | V20: =V19+U20 -> 11292.327
A21: 14 | B21: okt-27 | C21: =Aannames!$D$5*(1+Aannames!$D$6)^(A21-2)*(1+IF(MOD(A21-1,12)=0,Aannames!$D$7,0)) -> 804.87859 | D21: =IF(A21>=Aannames!$D$24,Aannames!$D$26*(1+Aannames!$D$6)^(A21-Aannames!$D$24),0) -> 530 | E21: =C21+D21 -> 1334.8786 | F21: =E21*Aannames!$D$8 -> 827.62473 | G21: =CohortBull!O$38 -> 3070.5371 | H21: =G21*Aannames!$D$9 -> 122.82148 | I21: =H21*Aannames!$D$10*(1-Aannames!$D$11) -> 625.34558 | J21: =MIN(J20*(1-Aannames!$D$18)+IF(A21>=Aannames!$D$14,Aannames!$D$15*Aannames!$D$16,0),(Aannames!$D$19+IF(A21>=Aannames!$D$24,Aannames!$D$25,0))*Aannames!$D$20) -> 38.153165 | K21: =J21*Aannames!$D$17 -> 2098.4241 | L21: =IF(AND(A21>12,MOD(A21-1,12)=0),Aannames!$D$37,0) -> 0 | M21: =I21+K21+L21 -> 2723.7696 | N21: =Aannames!$D$28+G21*Aannames!$D$29 -> 121.41074 | O21: =Aannames!$D$30*(1+IF(A21>=Aannames!$D$24,1,0)) -> 160 | P21: =Aannames!$D$31 -> 70 | Q21: =IF(MOD(A21-1,12)=0,Aannames!$D$32,0) -> 0 | R21: =Aannames!$D$33+IF(MOD(A21-1,12)=0,Aannames!$D$34,0) -> 300 | S21: =IF(A21=1,Aannames!$D$35,0) -> 0 | T21: =SUM(N21:S21) -> 651.41074 | U21: =M21-T21 -> 2072.3589 | V21: =V20+U21 -> 13364.686
A22: 15 | B22: nov-27 | C22: =Aannames!$D$5*(1+Aannames!$D$6)^(A22-2)*(1+IF(MOD(A22-1,12)=0,Aannames!$D$7,0)) -> 853.1713 | D22: =IF(A22>=Aannames!$D$24,Aannames!$D$26*(1+Aannames!$D$6)^(A22-Aannames!$D$24),0) -> 561.8 | E22: =C22+D22 -> 1414.9713 | F22: =E22*Aannames!$D$8 -> 877.28221 | G22: =CohortBull!P$38 -> 3267.1341 | H22: =G22*Aannames!$D$9 -> 130.68536 | I22: =H22*Aannames!$D$10*(1-Aannames!$D$11) -> 665.38453 | J22: =MIN(J21*(1-Aannames!$D$18)+IF(A22>=Aannames!$D$14,Aannames!$D$15*Aannames!$D$16,0),(Aannames!$D$19+IF(A22>=Aannames!$D$24,Aannames!$D$25,0))*Aannames!$D$20) -> 42.080867 | K22: =J22*Aannames!$D$17 -> 2314.4477 | L22: =IF(AND(A22>12,MOD(A22-1,12)=0),Aannames!$D$37,0) -> 0 | M22: =I22+K22+L22 -> 2979.8322 | N22: =Aannames!$D$28+G22*Aannames!$D$29 -> 125.34268 | O22: =Aannames!$D$30*(1+IF(A22>=Aannames!$D$24,1,0)) -> 160 | P22: =Aannames!$D$31 -> 70 | Q22: =IF(MOD(A22-1,12)=0,Aannames!$D$32,0) -> 0 | R22: =Aannames!$D$33+IF(MOD(A22-1,12)=0,Aannames!$D$34,0) -> 300 | S22: =IF(A22=1,Aannames!$D$35,0) -> 0 | T22: =SUM(N22:S22) -> 655.34268 | U22: =M22-T22 -> 2324.4895 | V22: =V21+U22 -> 15689.175
A23: 16 | B23: dec-27 | C23: =Aannames!$D$5*(1+Aannames!$D$6)^(A23-2)*(1+IF(MOD(A23-1,12)=0,Aannames!$D$7,0)) -> 904.36158 | D23: =IF(A23>=Aannames!$D$24,Aannames!$D$26*(1+Aannames!$D$6)^(A23-Aannames!$D$24),0) -> 595.508 | E23: =C23+D23 -> 1499.8696 | F23: =E23*Aannames!$D$8 -> 929.91914 | G23: =CohortBull!Q$38 -> 3495.8126 | H23: =G23*Aannames!$D$9 -> 139.8325 | I23: =H23*Aannames!$D$10*(1-Aannames!$D$11) -> 711.95718 | J23: =MIN(J22*(1-Aannames!$D$18)+IF(A23>=Aannames!$D$14,Aannames!$D$15*Aannames!$D$16,0),(Aannames!$D$19+IF(A23>=Aannames!$D$24,Aannames!$D$25,0))*Aannames!$D$20) -> 45.949654 | K23: =J23*Aannames!$D$17 -> 2527.231 | L23: =IF(AND(A23>12,MOD(A23-1,12)=0),Aannames!$D$37,0) -> 0 | M23: =I23+K23+L23 -> 3239.1882 | N23: =Aannames!$D$28+G23*Aannames!$D$29 -> 129.91625 | O23: =Aannames!$D$30*(1+IF(A23>=Aannames!$D$24,1,0)) -> 160 | P23: =Aannames!$D$31 -> 70 | Q23: =IF(MOD(A23-1,12)=0,Aannames!$D$32,0) -> 0 | R23: =Aannames!$D$33+IF(MOD(A23-1,12)=0,Aannames!$D$34,0) -> 300 | S23: =IF(A23=1,Aannames!$D$35,0) -> 0 | T23: =SUM(N23:S23) -> 659.91625 | U23: =M23-T23 -> 2579.2719 | V23: =V22+U23 -> 18268.447
A24: 17 | B24: jan-28 | C24: =Aannames!$D$5*(1+Aannames!$D$6)^(A24-2)*(1+IF(MOD(A24-1,12)=0,Aannames!$D$7,0)) -> 958.62328 | D24: =IF(A24>=Aannames!$D$24,Aannames!$D$26*(1+Aannames!$D$6)^(A24-Aannames!$D$24),0) -> 631.23848 | E24: =C24+D24 -> 1589.8618 | F24: =E24*Aannames!$D$8 -> 985.71429 | G24: =CohortBull!R$38 -> 3765.6789 | H24: =G24*Aannames!$D$9 -> 150.62715 | I24: =H24*Aannames!$D$10*(1-Aannames!$D$11) -> 766.91816 | J24: =MIN(J23*(1-Aannames!$D$18)+IF(A24>=Aannames!$D$14,Aannames!$D$15*Aannames!$D$16,0),(Aannames!$D$19+IF(A24>=Aannames!$D$24,Aannames!$D$25,0))*Aannames!$D$20) -> 49.760409 | K24: =J24*Aannames!$D$17 -> 2736.8225 | L24: =IF(AND(A24>12,MOD(A24-1,12)=0),Aannames!$D$37,0) -> 0 | M24: =I24+K24+L24 -> 3503.7407 | N24: =Aannames!$D$28+G24*Aannames!$D$29 -> 135.31358 | O24: =Aannames!$D$30*(1+IF(A24>=Aannames!$D$24,1,0)) -> 160 | P24: =Aannames!$D$31 -> 70 | Q24: =IF(MOD(A24-1,12)=0,Aannames!$D$32,0) -> 0 | R24: =Aannames!$D$33+IF(MOD(A24-1,12)=0,Aannames!$D$34,0) -> 300 | S24: =IF(A24=1,Aannames!$D$35,0) -> 0 | T24: =SUM(N24:S24) -> 665.31358 | U24: =M24-T24 -> 2838.4271 | V24: =V23+U24 -> 21106.875
A25: 18 | B25: feb-28 | C25: =Aannames!$D$5*(1+Aannames!$D$6)^(A25-2)*(1+IF(MOD(A25-1,12)=0,Aannames!$D$7,0)) -> 1016.1407 | D25: =IF(A25>=Aannames!$D$24,Aannames!$D$26*(1+Aannames!$D$6)^(A25-Aannames!$D$24),0) -> 669.11279 | E25: =C25+D25 -> 1685.2535 | F25: =E25*Aannames!$D$8 -> 1044.8571 | G25: =CohortBull!S$38 -> 4056.6469 | H25: =G25*Aannames!$D$9 -> 162.26587 | I25: =H25*Aannames!$D$10*(1-Aannames!$D$11) -> 826.1767 | J25: =MIN(J24*(1-Aannames!$D$18)+IF(A25>=Aannames!$D$14,Aannames!$D$15*Aannames!$D$16,0),(Aannames!$D$19+IF(A25>=Aannames!$D$24,Aannames!$D$25,0))*Aannames!$D$20) -> 53.514003 | K25: =J25*Aannames!$D$17 -> 2943.2702 | L25: =IF(AND(A25>12,MOD(A25-1,12)=0),Aannames!$D$37,0) -> 0 | M25: =I25+K25+L25 -> 3769.4469 | N25: =Aannames!$D$28+G25*Aannames!$D$29 -> 141.13294 | O25: =Aannames!$D$30*(1+IF(A25>=Aannames!$D$24,1,0)) -> 160 | P25: =Aannames!$D$31 -> 70 | Q25: =IF(MOD(A25-1,12)=0,Aannames!$D$32,0) -> 0 | R25: =Aannames!$D$33+IF(MOD(A25-1,12)=0,Aannames!$D$34,0) -> 300 | S25: =IF(A25=1,Aannames!$D$35,0) -> 0 | T25: =SUM(N25:S25) -> 671.13294 | U25: =M25-T25 -> 3098.3139 | V25: =V24+U25 -> 24205.188
A26: 19 | B26: mrt-28 | C26: =Aannames!$D$5*(1+Aannames!$D$6)^(A26-2)*(1+IF(MOD(A26-1,12)=0,Aannames!$D$7,0)) -> 1077.1091 | D26: =IF(A26>=Aannames!$D$24,Aannames!$D$26*(1+Aannames!$D$6)^(A26-Aannames!$D$24),0) -> 709.25956 | E26: =C26+D26 -> 1786.3687 | F26: =E26*Aannames!$D$8 -> 1107.5486 | G26: =CohortBull!T$38 -> 4372.3765 | H26: =G26*Aannames!$D$9 -> 174.89506 | I26: =H26*Aannames!$D$10*(1-Aannames!$D$11) -> 890.4782 | J26: =MIN(J25*(1-Aannames!$D$18)+IF(A26>=Aannames!$D$14,Aannames!$D$15*Aannames!$D$16,0),(Aannames!$D$19+IF(A26>=Aannames!$D$24,Aannames!$D$25,0))*Aannames!$D$20) -> 57.211293 | K26: =J26*Aannames!$D$17 -> 3146.6211 | L26: =IF(AND(A26>12,MOD(A26-1,12)=0),Aannames!$D$37,0) -> 0 | M26: =I26+K26+L26 -> 4037.0993 | N26: =Aannames!$D$28+G26*Aannames!$D$29 -> 147.44753 | O26: =Aannames!$D$30*(1+IF(A26>=Aannames!$D$24,1,0)) -> 160 | P26: =Aannames!$D$31 -> 70 | Q26: =IF(MOD(A26-1,12)=0,Aannames!$D$32,0) -> 0 | R26: =Aannames!$D$33+IF(MOD(A26-1,12)=0,Aannames!$D$34,0) -> 300 | S26: =IF(A26=1,Aannames!$D$35,0) -> 0 | T26: =SUM(N26:S26) -> 677.44753 | U26: =M26-T26 -> 3359.6518 | V26: =V25+U26 -> 27564.84
A27: 20 | B27: apr-28 | C27: =Aannames!$D$5*(1+Aannames!$D$6)^(A27-2)*(1+IF(MOD(A27-1,12)=0,Aannames!$D$7,0)) -> 1141.7357 | D27: =IF(A27>=Aannames!$D$24,Aannames!$D$26*(1+Aannames!$D$6)^(A27-Aannames!$D$24),0) -> 751.81513 | E27: =C27+D27 -> 1893.5508 | F27: =E27*Aannames!$D$8 -> 1174.0015 | G27: =CohortBull!U$38 -> 4709.3126 | H27: =G27*Aannames!$D$9 -> 188.3725 | I27: =H27*Aannames!$D$10*(1-Aannames!$D$11) -> 959.0986 | J27: =MIN(J26*(1-Aannames!$D$18)+IF(A27>=Aannames!$D$14,Aannames!$D$15*Aannames!$D$16,0),(Aannames!$D$19+IF(A27>=Aannames!$D$24,Aannames!$D$25,0))*Aannames!$D$20) -> 60.853124 | K27: =J27*Aannames!$D$17 -> 3346.9218 | L27: =IF(AND(A27>12,MOD(A27-1,12)=0),Aannames!$D$37,0) -> 0 | M27: =I27+K27+L27 -> 4306.0204 | N27: =Aannames!$D$28+G27*Aannames!$D$29 -> 154.18625 | O27: =Aannames!$D$30*(1+IF(A27>=Aannames!$D$24,1,0)) -> 160 | P27: =Aannames!$D$31 -> 70 | Q27: =IF(MOD(A27-1,12)=0,Aannames!$D$32,0) -> 0 | R27: =Aannames!$D$33+IF(MOD(A27-1,12)=0,Aannames!$D$34,0) -> 300 | S27: =IF(A27=1,Aannames!$D$35,0) -> 0 | T27: =SUM(N27:S27) -> 684.18625 | U27: =M27-T27 -> 3621.8342 | V27: =V26+U27 -> 31186.674
A28: 21 | B28: mei-28 | C28: =Aannames!$D$5*(1+Aannames!$D$6)^(A28-2)*(1+IF(MOD(A28-1,12)=0,Aannames!$D$7,0)) -> 1210.2398 | D28: =IF(A28>=Aannames!$D$24,Aannames!$D$26*(1+Aannames!$D$6)^(A28-Aannames!$D$24),0) -> 796.92404 | E28: =C28+D28 -> 2007.1638 | F28: =E28*Aannames!$D$8 -> 1244.4416 | G28: =CohortBull!V$38 -> 5069.9244 | H28: =G28*Aannames!$D$9 -> 202.79697 | I28: =H28*Aannames!$D$10*(1-Aannames!$D$11) -> 1032.5408 | J28: =MIN(J27*(1-Aannames!$D$18)+IF(A28>=Aannames!$D$14,Aannames!$D$15*Aannames!$D$16,0),(Aannames!$D$19+IF(A28>=Aannames!$D$24,Aannames!$D$25,0))*Aannames!$D$20) -> 64.440327 | K28: =J28*Aannames!$D$17 -> 3544.218 | L28: =IF(AND(A28>12,MOD(A28-1,12)=0),Aannames!$D$37,0) -> 0 | M28: =I28+K28+L28 -> 4576.7588 | N28: =Aannames!$D$28+G28*Aannames!$D$29 -> 161.39849 | O28: =Aannames!$D$30*(1+IF(A28>=Aannames!$D$24,1,0)) -> 160 | P28: =Aannames!$D$31 -> 70 | Q28: =IF(MOD(A28-1,12)=0,Aannames!$D$32,0) -> 0 | R28: =Aannames!$D$33+IF(MOD(A28-1,12)=0,Aannames!$D$34,0) -> 300 | S28: =IF(A28=1,Aannames!$D$35,0) -> 0 | T28: =SUM(N28:S28) -> 691.39849 | U28: =M28-T28 -> 3885.3603 | V28: =V27+U28 -> 35072.035
A29: 22 | B29: jun-28 | C29: =Aannames!$D$5*(1+Aannames!$D$6)^(A29-2)*(1+IF(MOD(A29-1,12)=0,Aannames!$D$7,0)) -> 1282.8542 | D29: =IF(A29>=Aannames!$D$24,Aannames!$D$26*(1+Aannames!$D$6)^(A29-Aannames!$D$24),0) -> 844.73948 | E29: =C29+D29 -> 2127.5937 | F29: =E29*Aannames!$D$8 -> 1319.1081 | G29: =CohortBull!W$38 -> 5449.3946 | H29: =G29*Aannames!$D$9 -> 217.97579 | I29: =H29*Aannames!$D$10*(1-Aannames!$D$11) -> 1109.8237 | J29: =MIN(J28*(1-Aannames!$D$18)+IF(A29>=Aannames!$D$14,Aannames!$D$15*Aannames!$D$16,0),(Aannames!$D$19+IF(A29>=Aannames!$D$24,Aannames!$D$25,0))*Aannames!$D$20) -> 67.973722 | K29: =J29*Aannames!$D$17 -> 3738.5547 | L29: =IF(AND(A29>12,MOD(A29-1,12)=0),Aannames!$D$37,0) -> 0 | M29: =I29+K29+L29 -> 4848.3784 | N29: =Aannames!$D$28+G29*Aannames!$D$29 -> 168.98789 | O29: =Aannames!$D$30*(1+IF(A29>=Aannames!$D$24,1,0)) -> 160 | P29: =Aannames!$D$31 -> 70 | Q29: =IF(MOD(A29-1,12)=0,Aannames!$D$32,0) -> 0 | R29: =Aannames!$D$33+IF(MOD(A29-1,12)=0,Aannames!$D$34,0) -> 300 | S29: =IF(A29=1,Aannames!$D$35,0) -> 0 | T29: =SUM(N29:S29) -> 698.98789 | U29: =M29-T29 -> 4149.3905 | V29: =V28+U29 -> 39221.425
A30: 23 | B30: jul-28 | C30: =Aannames!$D$5*(1+Aannames!$D$6)^(A30-2)*(1+IF(MOD(A30-1,12)=0,Aannames!$D$7,0)) -> 1359.8254 | D30: =IF(A30>=Aannames!$D$24,Aannames!$D$26*(1+Aannames!$D$6)^(A30-Aannames!$D$24),0) -> 895.42385 | E30: =C30+D30 -> 2255.2493 | F30: =E30*Aannames!$D$8 -> 1398.2546 | G30: =CohortBull!X$38 -> 5849.7849 | H30: =G30*Aannames!$D$9 -> 233.9914 | I30: =H30*Aannames!$D$10*(1-Aannames!$D$11) -> 1191.3672 | J30: =MIN(J29*(1-Aannames!$D$18)+IF(A30>=Aannames!$D$14,Aannames!$D$15*Aannames!$D$16,0),(Aannames!$D$19+IF(A30>=Aannames!$D$24,Aannames!$D$25,0))*Aannames!$D$20) -> 71.454116 | K30: =J30*Aannames!$D$17 -> 3929.9764 | L30: =IF(AND(A30>12,MOD(A30-1,12)=0),Aannames!$D$37,0) -> 0 | M30: =I30+K30+L30 -> 5121.3436 | N30: =Aannames!$D$28+G30*Aannames!$D$29 -> 176.9957 | O30: =Aannames!$D$30*(1+IF(A30>=Aannames!$D$24,1,0)) -> 160 | P30: =Aannames!$D$31 -> 70 | Q30: =IF(MOD(A30-1,12)=0,Aannames!$D$32,0) -> 0 | R30: =Aannames!$D$33+IF(MOD(A30-1,12)=0,Aannames!$D$34,0) -> 300 | S30: =IF(A30=1,Aannames!$D$35,0) -> 0 | T30: =SUM(N30:S30) -> 706.9957 | U30: =M30-T30 -> 4414.3479 | V30: =V29+U30 -> 43635.773
A31: 24 | B31: aug-28 | C31: =Aannames!$D$5*(1+Aannames!$D$6)^(A31-2)*(1+IF(MOD(A31-1,12)=0,Aannames!$D$7,0)) -> 1441.415 | D31: =IF(A31>=Aannames!$D$24,Aannames!$D$26*(1+Aannames!$D$6)^(A31-Aannames!$D$24),0) -> 949.14928 | E31: =C31+D31 -> 2390.5642 | F31: =E31*Aannames!$D$8 -> 1482.1498 | G31: =CohortBull!Y$38 -> 6279.0473 | H31: =G31*Aannames!$D$9 -> 251.16189 | I31: =H31*Aannames!$D$10*(1-Aannames!$D$11) -> 1278.7908 | J31: =MIN(J30*(1-Aannames!$D$18)+IF(A31>=Aannames!$D$14,Aannames!$D$15*Aannames!$D$16,0),(Aannames!$D$19+IF(A31>=Aannames!$D$24,Aannames!$D$25,0))*Aannames!$D$20) -> 74.882305 | K31: =J31*Aannames!$D$17 -> 4118.5268 | L31: =IF(AND(A31>12,MOD(A31-1,12)=0),Aannames!$D$37,0) -> 0 | M31: =I31+K31+L31 -> 5397.3175 | N31: =Aannames!$D$28+G31*Aannames!$D$29 -> 185.58095 | O31: =Aannames!$D$30*(1+IF(A31>=Aannames!$D$24,1,0)) -> 160 | P31: =Aannames!$D$31 -> 70 | Q31: =IF(MOD(A31-1,12)=0,Aannames!$D$32,0) -> 0 | R31: =Aannames!$D$33+IF(MOD(A31-1,12)=0,Aannames!$D$34,0) -> 300 | S31: =IF(A31=1,Aannames!$D$35,0) -> 0 | T31: =SUM(N31:S31) -> 715.58095 | U31: =M31-T31 -> 4681.7366 | V31: =V30+U31 -> 48317.51
A32: 25 | B32: sep-28 | C32: =Aannames!$D$5*(1+Aannames!$D$6)^(A32-2)*(1+IF(MOD(A32-1,12)=0,Aannames!$D$7,0)) -> 5347.6495 | D32: =IF(A32>=Aannames!$D$24,Aannames!$D$26*(1+Aannames!$D$6)^(A32-Aannames!$D$24),0) -> 1006.0982 | E32: =C32+D32 -> 6353.7478 | F32: =E32*Aannames!$D$8 -> 3939.3236 | G32: =CohortBull!Z$38 -> 9100.9211 | H32: =G32*Aannames!$D$9 -> 364.03684 | I32: =H32*Aannames!$D$10*(1-Aannames!$D$11) -> 1853.4936 | J32: =MIN(J31*(1-Aannames!$D$18)+IF(A32>=Aannames!$D$14,Aannames!$D$15*Aannames!$D$16,0),(Aannames!$D$19+IF(A32>=Aannames!$D$24,Aannames!$D$25,0))*Aannames!$D$20) -> 78.25907 | K32: =J32*Aannames!$D$17 -> 4304.2488 | L32: =IF(AND(A32>12,MOD(A32-1,12)=0),Aannames!$D$37,0) -> 10000 | M32: =I32+K32+L32 -> 16157.742 | N32: =Aannames!$D$28+G32*Aannames!$D$29 -> 242.01842 | O32: =Aannames!$D$30*(1+IF(A32>=Aannames!$D$24,1,0)) -> 160 | P32: =Aannames!$D$31 -> 70 | Q32: =IF(MOD(A32-1,12)=0,Aannames!$D$32,0) -> 150 | R32: =Aannames!$D$33+IF(MOD(A32-1,12)=0,Aannames!$D$34,0) -> 1800 | S32: =IF(A32=1,Aannames!$D$35,0) -> 0 | T32: =SUM(N32:S32) -> 2422.0184 | U32: =M32-T32 -> 13735.724 | V32: =V31+U32 -> 62053.234
A33: 26 | B33: okt-28 | C33: =Aannames!$D$5*(1+Aannames!$D$6)^(A33-2)*(1+IF(MOD(A33-1,12)=0,Aannames!$D$7,0)) -> 1619.5739 | D33: =IF(A33>=Aannames!$D$24,Aannames!$D$26*(1+Aannames!$D$6)^(A33-Aannames!$D$24),0) -> 1066.4641 | E33: =C33+D33 -> 2686.038 | F33: =E33*Aannames!$D$8 -> 1665.3436 | G33: =CohortBull!AA$38 -> 8443.6212 | H33: =G33*Aannames!$D$9 -> 337.74485 | I33: =H33*Aannames!$D$10*(1-Aannames!$D$11) -> 1719.6279 | J33: =MIN(J32*(1-Aannames!$D$18)+IF(A33>=Aannames!$D$14,Aannames!$D$15*Aannames!$D$16,0),(Aannames!$D$19+IF(A33>=Aannames!$D$24,Aannames!$D$25,0))*Aannames!$D$20) -> 81.585184 | K33: =J33*Aannames!$D$17 -> 4487.1851 | L33: =IF(AND(A33>12,MOD(A33-1,12)=0),Aannames!$D$37,0) -> 0 | M33: =I33+K33+L33 -> 6206.813 | N33: =Aannames!$D$28+G33*Aannames!$D$29 -> 228.87242 | O33: =Aannames!$D$30*(1+IF(A33>=Aannames!$D$24,1,0)) -> 160 | P33: =Aannames!$D$31 -> 70 | Q33: =IF(MOD(A33-1,12)=0,Aannames!$D$32,0) -> 0 | R33: =Aannames!$D$33+IF(MOD(A33-1,12)=0,Aannames!$D$34,0) -> 300 | S33: =IF(A33=1,Aannames!$D$35,0) -> 0 | T33: =SUM(N33:S33) -> 758.87242 | U33: =M33-T33 -> 5447.9406 | V33: =V32+U33 -> 67501.174
A34: 27 | B34: nov-28 | C34: =Aannames!$D$5*(1+Aannames!$D$6)^(A34-2)*(1+IF(MOD(A34-1,12)=0,Aannames!$D$7,0)) -> 1716.7483 | D34: =IF(A34>=Aannames!$D$24,Aannames!$D$26*(1+Aannames!$D$6)^(A34-Aannames!$D$24),0) -> 1130.452 | E34: =C34+D34 -> 2847.2003 | F34: =E34*Aannames!$D$8 -> 1765.2642 | G34: =CohortBull!AB$38 -> 8718.0935 | H34: =G34*Aannames!$D$9 -> 348.72374 | I34: =H34*Aannames!$D$10*(1-Aannames!$D$11) -> 1775.5269 | J34: =MIN(J33*(1-Aannames!$D$18)+IF(A34>=Aannames!$D$14,Aannames!$D$15*Aannames!$D$16,0),(Aannames!$D$19+IF(A34>=Aannames!$D$24,Aannames!$D$25,0))*Aannames!$D$20) -> 84.861406 | K34: =J34*Aannames!$D$17 -> 4667.3773 | L34: =IF(AND(A34>12,MOD(A34-1,12)=0),Aannames!$D$37,0) -> 0 | M34: =I34+K34+L34 -> 6442.9043 | N34: =Aannames!$D$28+G34*Aannames!$D$29 -> 234.36187 | O34: =Aannames!$D$30*(1+IF(A34>=Aannames!$D$24,1,0)) -> 160 | P34: =Aannames!$D$31 -> 70 | Q34: =IF(MOD(A34-1,12)=0,Aannames!$D$32,0) -> 0 | R34: =Aannames!$D$33+IF(MOD(A34-1,12)=0,Aannames!$D$34,0) -> 300 | S34: =IF(A34=1,Aannames!$D$35,0) -> 0 | T34: =SUM(N34:S34) -> 764.36187 | U34: =M34-T34 -> 5678.5424 | V34: =V33+U34 -> 73179.717
A35: 28 | B35: dec-28 | C35: =Aannames!$D$5*(1+Aannames!$D$6)^(A35-2)*(1+IF(MOD(A35-1,12)=0,Aannames!$D$7,0)) -> 1819.7532 | D35: =IF(A35>=Aannames!$D$24,Aannames!$D$26*(1+Aannames!$D$6)^(A35-Aannames!$D$24),0) -> 1198.2791 | E35: =C35+D35 -> 3018.0323 | F35: =E35*Aannames!$D$8 -> 1871.18 | G35: =CohortBull!AC$38 -> 9093.6201 | H35: =G35*Aannames!$D$9 -> 363.7448 | I35: =H35*Aannames!$D$10*(1-Aannames!$D$11) -> 1852.0067 | J35: =MIN(J34*(1-Aannames!$D$18)+IF(A35>=Aannames!$D$14,Aannames!$D$15*Aannames!$D$16,0),(Aannames!$D$19+IF(A35>=Aannames!$D$24,Aannames!$D$25,0))*Aannames!$D$20) -> 88.088485 | K35: =J35*Aannames!$D$17 -> 4844.8667 | L35: =IF(AND(A35>12,MOD(A35-1,12)=0),Aannames!$D$37,0) -> 0 | M35: =I35+K35+L35 -> 6696.8733 | N35: =Aannames!$D$28+G35*Aannames!$D$29 -> 241.8724 | O35: =Aannames!$D$30*(1+IF(A35>=Aannames!$D$24,1,0)) -> 160 | P35: =Aannames!$D$31 -> 70 | Q35: =IF(MOD(A35-1,12)=0,Aannames!$D$32,0) -> 0 | R35: =Aannames!$D$33+IF(MOD(A35-1,12)=0,Aannames!$D$34,0) -> 300 | S35: =IF(A35=1,Aannames!$D$35,0) -> 0 | T35: =SUM(N35:S35) -> 771.8724 | U35: =M35-T35 -> 5925.0009 | V35: =V34+U35 -> 79104.718
A36: 29 | B36: jan-29 | C36: =Aannames!$D$5*(1+Aannames!$D$6)^(A36-2)*(1+IF(MOD(A36-1,12)=0,Aannames!$D$7,0)) -> 1928.9384 | D36: =IF(A36>=Aannames!$D$24,Aannames!$D$26*(1+Aannames!$D$6)^(A36-Aannames!$D$24),0) -> 1270.1758 | E36: =C36+D36 -> 3199.1142 | F36: =E36*Aannames!$D$8 -> 1983.4508 | G36: =CohortBull!AD$38 -> 9572.0012 | H36: =G36*Aannames!$D$9 -> 382.88005 | I36: =H36*Aannames!$D$10*(1-Aannames!$D$11) -> 1949.4338 | J36: =MIN(J35*(1-Aannames!$D$18)+IF(A36>=Aannames!$D$14,Aannames!$D$15*Aannames!$D$16,0),(Aannames!$D$19+IF(A36>=Aannames!$D$24,Aannames!$D$25,0))*Aannames!$D$20) -> 91.267158 | K36: =J36*Aannames!$D$17 -> 5019.6937 | L36: =IF(AND(A36>12,MOD(A36-1,12)=0),Aannames!$D$37,0) -> 0 | M36: =I36+K36+L36 -> 6969.1274 | N36: =Aannames!$D$28+G36*Aannames!$D$29 -> 251.44002 | O36: =Aannames!$D$30*(1+IF(A36>=Aannames!$D$24,1,0)) -> 160 | P36: =Aannames!$D$31 -> 70 | Q36: =IF(MOD(A36-1,12)=0,Aannames!$D$32,0) -> 0 | R36: =Aannames!$D$33+IF(MOD(A36-1,12)=0,Aannames!$D$34,0) -> 300 | S36: =IF(A36=1,Aannames!$D$35,0) -> 0 | T36: =SUM(N36:S36) -> 781.44002 | U36: =M36-T36 -> 6187.6874 | V36: =V35+U36 -> 85292.405
A37: 30 | B37: feb-29 | C37: =Aannames!$D$5*(1+Aannames!$D$6)^(A37-2)*(1+IF(MOD(A37-1,12)=0,Aannames!$D$7,0)) -> 2044.6747 | D37: =IF(A37>=Aannames!$D$24,Aannames!$D$26*(1+Aannames!$D$6)^(A37-Aannames!$D$24),0) -> 1346.3864 | E37: =C37+D37 -> 3391.0611 | F37: =E37*Aannames!$D$8 -> 2102.4579 | G37: =CohortBull!AE$38 -> 10107.78 | H37: =G37*Aannames!$D$9 -> 404.31122 | I37: =H37*Aannames!$D$10*(1-Aannames!$D$11) -> 2058.5506 | J37: =MIN(J36*(1-Aannames!$D$18)+IF(A37>=Aannames!$D$14,Aannames!$D$15*Aannames!$D$16,0),(Aannames!$D$19+IF(A37>=Aannames!$D$24,Aannames!$D$25,0))*Aannames!$D$20) -> 94.39815 | K37: =J37*Aannames!$D$17 -> 5191.8983 | L37: =IF(AND(A37>12,MOD(A37-1,12)=0),Aannames!$D$37,0) -> 0 | M37: =I37+K37+L37 -> 7250.4488 | N37: =Aannames!$D$28+G37*Aannames!$D$29 -> 262.15561 | O37: =Aannames!$D$30*(1+IF(A37>=Aannames!$D$24,1,0)) -> 160 | P37: =Aannames!$D$31 -> 70 | Q37: =IF(MOD(A37-1,12)=0,Aannames!$D$32,0) -> 0 | R37: =Aannames!$D$33+IF(MOD(A37-1,12)=0,Aannames!$D$34,0) -> 300 | S37: =IF(A37=1,Aannames!$D$35,0) -> 0 | T37: =SUM(N37:S37) -> 792.15561 | U37: =M37-T37 -> 6458.2932 | V37: =V36+U37 -> 91750.698
A38: 31 | B38: mrt-29 | C38: =Aannames!$D$5*(1+Aannames!$D$6)^(A38-2)*(1+IF(MOD(A38-1,12)=0,Aannames!$D$7,0)) -> 2167.3552 | D38: =IF(A38>=Aannames!$D$24,Aannames!$D$26*(1+Aannames!$D$6)^(A38-Aannames!$D$24),0) -> 1427.1696 | E38: =C38+D38 -> 3594.5247 | F38: =E38*Aannames!$D$8 -> 2228.6053 | G38: =CohortBull!AF$38 -> 10702.981 | H38: =G38*Aannames!$D$9 -> 428.11923 | I38: =H38*Aannames!$D$10*(1-Aannames!$D$11) -> 2179.7691 | J38: =MIN(J37*(1-Aannames!$D$18)+IF(A38>=Aannames!$D$14,Aannames!$D$15*Aannames!$D$16,0),(Aannames!$D$19+IF(A38>=Aannames!$D$24,Aannames!$D$25,0))*Aannames!$D$20) -> 97.482178 | K38: =J38*Aannames!$D$17 -> 5361.5198 | L38: =IF(AND(A38>12,MOD(A38-1,12)=0),Aannames!$D$37,0) -> 0 | M38: =I38+K38+L38 -> 7541.2889 | N38: =Aannames!$D$28+G38*Aannames!$D$29 -> 274.05961 | O38: =Aannames!$D$30*(1+IF(A38>=Aannames!$D$24,1,0)) -> 160 | P38: =Aannames!$D$31 -> 70 | Q38: =IF(MOD(A38-1,12)=0,Aannames!$D$32,0) -> 0 | R38: =Aannames!$D$33+IF(MOD(A38-1,12)=0,Aannames!$D$34,0) -> 300 | S38: =IF(A38=1,Aannames!$D$35,0) -> 0 | T38: =SUM(N38:S38) -> 804.05961 | U38: =M38-T38 -> 6737.2292 | V38: =V37+U38 -> 98487.928
A39: 32 | B39: apr-29 | C39: =Aannames!$D$5*(1+Aannames!$D$6)^(A39-2)*(1+IF(MOD(A39-1,12)=0,Aannames!$D$7,0)) -> 2297.3965 | D39: =IF(A39>=Aannames!$D$24,Aannames!$D$26*(1+Aannames!$D$6)^(A39-Aannames!$D$24),0) -> 1512.7998 | E39: =C39+D39 -> 3810.1962 | F39: =E39*Aannames!$D$8 -> 2362.3217 | G39: =CohortBull!AG$38 -> 11347.905 | H39: =G39*Aannames!$D$9 -> 453.91621 | I39: =H39*Aannames!$D$10*(1-Aannames!$D$11) -> 2311.1144 | J39: =MIN(J38*(1-Aannames!$D$18)+IF(A39>=Aannames!$D$14,Aannames!$D$15*Aannames!$D$16,0),(Aannames!$D$19+IF(A39>=Aannames!$D$24,Aannames!$D$25,0))*Aannames!$D$20) -> 100.51995 | K39: =J39*Aannames!$D$17 -> 5528.597 | L39: =IF(AND(A39>12,MOD(A39-1,12)=0),Aannames!$D$37,0) -> 0 | M39: =I39+K39+L39 -> 7839.7114 | N39: =Aannames!$D$28+G39*Aannames!$D$29 -> 286.9581 | O39: =Aannames!$D$30*(1+IF(A39>=Aannames!$D$24,1,0)) -> 160 | P39: =Aannames!$D$31 -> 70 | Q39: =IF(MOD(A39-1,12)=0,Aannames!$D$32,0) -> 0 | R39: =Aannames!$D$33+IF(MOD(A39-1,12)=0,Aannames!$D$34,0) -> 300 | S39: =IF(A39=1,Aannames!$D$35,0) -> 0 | T39: =SUM(N39:S39) -> 816.9581 | U39: =M39-T39 -> 7022.7533 | V39: =V38+U39 -> 105510.68
A40: 33 | B40: mei-29 | C40: =Aannames!$D$5*(1+Aannames!$D$6)^(A40-2)*(1+IF(MOD(A40-1,12)=0,Aannames!$D$7,0)) -> 2435.2403 | D40: =IF(A40>=Aannames!$D$24,Aannames!$D$26*(1+Aannames!$D$6)^(A40-Aannames!$D$24),0) -> 1603.5677 | E40: =C40+D40 -> 4038.808 | F40: =E40*Aannames!$D$8 -> 2504.061 | G40: =CohortBull!AH$38 -> 12044.827 | H40: =G40*Aannames!$D$9 -> 481.79307 | I40: =H40*Aannames!$D$10*(1-Aannames!$D$11) -> 2453.0494 | J40: =MIN(J39*(1-Aannames!$D$18)+IF(A40>=Aannames!$D$14,Aannames!$D$15*Aannames!$D$16,0),(Aannames!$D$19+IF(A40>=Aannames!$D$24,Aannames!$D$25,0))*Aannames!$D$20) -> 103.51215 | K40: =J40*Aannames!$D$17 -> 5693.168 | L40: =IF(AND(A40>12,MOD(A40-1,12)=0),Aannames!$D$37,0) -> 0 | M40: =I40+K40+L40 -> 8146.2175 | N40: =Aannames!$D$28+G40*Aannames!$D$29 -> 300.89654 | O40: =Aannames!$D$30*(1+IF(A40>=Aannames!$D$24,1,0)) -> 160 | P40: =Aannames!$D$31 -> 70 | Q40: =IF(MOD(A40-1,12)=0,Aannames!$D$32,0) -> 0 | R40: =Aannames!$D$33+IF(MOD(A40-1,12)=0,Aannames!$D$34,0) -> 300 | S40: =IF(A40=1,Aannames!$D$35,0) -> 0 | T40: =SUM(N40:S40) -> 830.89654 | U40: =M40-T40 -> 7315.3209 | V40: =V39+U40 -> 112826
A41: 34 | B41: jun-29 | C41: =Aannames!$D$5*(1+Aannames!$D$6)^(A41-2)*(1+IF(MOD(A41-1,12)=0,Aannames!$D$7,0)) -> 2581.3547 | D41: =IF(A41>=Aannames!$D$24,Aannames!$D$26*(1+Aannames!$D$6)^(A41-Aannames!$D$24),0) -> 1699.7818 | E41: =C41+D41 -> 4281.1365 | F41: =E41*Aannames!$D$8 -> 2654.3046 | G41: =CohortBull!AI$38 -> 12784.314 | H41: =G41*Aannames!$D$9 -> 511.37255 | I41: =H41*Aannames!$D$10*(1-Aannames!$D$11) -> 2603.6533 | J41: =MIN(J40*(1-Aannames!$D$18)+IF(A41>=Aannames!$D$14,Aannames!$D$15*Aannames!$D$16,0),(Aannames!$D$19+IF(A41>=Aannames!$D$24,Aannames!$D$25,0))*Aannames!$D$20) -> 106.45946 | K41: =J41*Aannames!$D$17 -> 5855.2705 | L41: =IF(AND(A41>12,MOD(A41-1,12)=0),Aannames!$D$37,0) -> 0 | M41: =I41+K41+L41 -> 8458.9239 | N41: =Aannames!$D$28+G41*Aannames!$D$29 -> 315.68628 | O41: =Aannames!$D$30*(1+IF(A41>=Aannames!$D$24,1,0)) -> 160 | P41: =Aannames!$D$31 -> 70 | Q41: =IF(MOD(A41-1,12)=0,Aannames!$D$32,0) -> 0 | R41: =Aannames!$D$33+IF(MOD(A41-1,12)=0,Aannames!$D$34,0) -> 300 | S41: =IF(A41=1,Aannames!$D$35,0) -> 0 | T41: =SUM(N41:S41) -> 845.68628 | U41: =M41-T41 -> 7613.2376 | V41: =V40+U41 -> 120439.24
A42: 35 | B42: jul-29 | C42: =Aannames!$D$5*(1+Aannames!$D$6)^(A42-2)*(1+IF(MOD(A42-1,12)=0,Aannames!$D$7,0)) -> 2736.236 | D42: =IF(A42>=Aannames!$D$24,Aannames!$D$26*(1+Aannames!$D$6)^(A42-Aannames!$D$24),0) -> 1801.7687 | E42: =C42+D42 -> 4538.0047 | F42: =E42*Aannames!$D$8 -> 2813.5629 | G42: =CohortBull!AJ$38 -> 13570.407 | H42: =G42*Aannames!$D$9 -> 542.81627 | I42: =H42*Aannames!$D$10*(1-Aannames!$D$11) -> 2763.7491 | J42: =MIN(J41*(1-Aannames!$D$18)+IF(A42>=Aannames!$D$14,Aannames!$D$15*Aannames!$D$16,0),(Aannames!$D$19+IF(A42>=Aannames!$D$24,Aannames!$D$25,0))*Aannames!$D$20) -> 109.36257 | K42: =J42*Aannames!$D$17 -> 6014.9415 | L42: =IF(AND(A42>12,MOD(A42-1,12)=0),Aannames!$D$37,0) -> 0 | M42: =I42+K42+L42 -> 8778.6905 | N42: =Aannames!$D$28+G42*Aannames!$D$29 -> 331.40814 | O42: =Aannames!$D$30*(1+IF(A42>=Aannames!$D$24,1,0)) -> 160 | P42: =Aannames!$D$31 -> 70 | Q42: =IF(MOD(A42-1,12)=0,Aannames!$D$32,0) -> 0 | R42: =Aannames!$D$33+IF(MOD(A42-1,12)=0,Aannames!$D$34,0) -> 300 | S42: =IF(A42=1,Aannames!$D$35,0) -> 0 | T42: =SUM(N42:S42) -> 861.40814 | U42: =M42-T42 -> 7917.2824 | V42: =V41+U42 -> 128356.52
A43: 36 | B43: aug-29 | C43: =Aannames!$D$5*(1+Aannames!$D$6)^(A43-2)*(1+IF(MOD(A43-1,12)=0,Aannames!$D$7,0)) -> 2900.4101 | D43: =IF(A43>=Aannames!$D$24,Aannames!$D$26*(1+Aannames!$D$6)^(A43-Aannames!$D$24),0) -> 1909.8748 | E43: =C43+D43 -> 4810.2849 | F43: =E43*Aannames!$D$8 -> 2982.3767 | G43: =CohortBull!AK$38 -> 14416.496 | H43: =G43*Aannames!$D$9 -> 576.65984 | I43: =H43*Aannames!$D$10*(1-Aannames!$D$11) -> 2936.0636 | J43: =MIN(J42*(1-Aannames!$D$18)+IF(A43>=Aannames!$D$14,Aannames!$D$15*Aannames!$D$16,0),(Aannames!$D$19+IF(A43>=Aannames!$D$24,Aannames!$D$25,0))*Aannames!$D$20) -> 112.22213 | K43: =J43*Aannames!$D$17 -> 6172.2173 | L43: =IF(AND(A43>12,MOD(A43-1,12)=0),Aannames!$D$37,0) -> 0 | M43: =I43+K43+L43 -> 9108.2809 | N43: =Aannames!$D$28+G43*Aannames!$D$29 -> 348.32992 | O43: =Aannames!$D$30*(1+IF(A43>=Aannames!$D$24,1,0)) -> 160 | P43: =Aannames!$D$31 -> 70 | Q43: =IF(MOD(A43-1,12)=0,Aannames!$D$32,0) -> 0 | R43: =Aannames!$D$33+IF(MOD(A43-1,12)=0,Aannames!$D$34,0) -> 300 | S43: =IF(A43=1,Aannames!$D$35,0) -> 0 | T43: =SUM(N43:S43) -> 878.32992 | U43: =M43-T43 -> 8229.951 | V43: =V42+U43 -> 136586.47
A45: KPI's
A46: MAU M12 | C46: =G19 -> 1687.5399
A47: MAU M24 | C47: =G31 -> 6279.0473
A48: MAU M36 | C48: =G43 -> 14416.496
A49: Betalende venues M36 | C49: =J43 -> 112.22213
A50: MRR M36 (venue + consumer) | C50: =K43+I43 -> 9108.2809
A51: Omzet jaar 3 (M25-M36) | C51: =SUM(M32:M43) -> 99597.022
A52: Blended ARPU M36 (A$/MAU/mnd) | C52: =IF(G43=0,0,M43/G43) -> 0.63179575
A53: Consumer-LTV per geactiveerde gebruiker | C53: =Retentie!$D$38*Aannames!$D$9*Aannames!$D$10*(1-Aannames!$D$11) -> 1.7665468
A54: Blended consumer-CAC (marketing/actieve) | C54: =SUM(R8:R43)/SUM(F8:F43) -> 0.31965673
